Workbook

Sheet LIST CUSTOMER
A1: LIST CUST NOV 2021
A2: No. | B2: Cust | C2: BL Number | D2: SHIPMENT | E2: PELAYARAN | F2: Cont/Package | G2: Qty | H2: SO No. | I2: No. AJU | J2: POL/POD | K2: LOKASI TIMBUN | L2: ETD | M2: ETA | N2: SPPB | O2: KIRIM CARGO | P2: BONGKAR | Q2: MOBIL | R2: KIRIM INV | S2: JO NO | T2: PAYMENT INV | U2: PROFIT | V2: REFUND CUST | W2: REK | X2: TRANSFER DATE
A3: IMPORT
A4: 1 | B4: PT. TOPCO TRADING INDONESIA | C4: YHJKT-046-016-21JP | D4: IMPORT | E4: NTL NAIGAI / CC | F4: 2.604CBM | G4: LCL | H4: 079/QUO-MCL/11-2021 | I4: 001303 | J4: YOKOHAMA | K4: AIRIN | L4: 14/10/2021 | M4: 44266 | N4: 44297 | O4: 44327 | P4: 44327 | Q4: DMV | R4: 29/11/2021 | S4: 101222 | T4: 24/12/2021 | U4: 1321000 | V4: 150000 | W4: BCA 0830129774 A/N FELIPE FANGIO CHUNG | X4: -
A5: 2 | B5: PT. TOPCO TRADING INDONESIA | C5: YHJKT-046-003-21JP | D5: IMPORT | E5: NTL NAIGAI / CC | F5: 0.940CBM | G5: LCL | H5: 002/QUO-MCL/11-2021 | I5: 001302 | J5: YOKOHAMA | K5: AIRIN | L5: 14/10/2021 | M5: 44266 | N5: 44297 | O5: 44327 | P5: 44327 | Q5: DMV | R5: 29/11/2021 | S5: 101211 | U5: 1950000 | V5: 150000
A6: 3 | B6: PT. POLYCHEMIE ASIA PACIFIC PERMAI | C6: SNKO010210907345 | D6: IMPORT | E6: SINOKOR / CC | F6: TCKU1593513, TEMU5861481 & HALU2052431 | G6: 3X20GP | H6: 012/QUO-VJL/11-2021 | I6: 000214 | J6: BUSAN | K6: UTC1 | L6: 23/10/2021 | M6: 44480 | N6: 44480 | O6: 44480 | P6: 44511 | Q6: PTP | R6: 25/11/2021 | S6: VJL21110050 101301 | T6: - | U6: 919000 | V6: 50000 | W6: CIMB 705899545600 A/N RONALD TOBING | X6: 44867
V7: 150000 | W7: BCA 5390525798 A/N ASIAH | X7: 44867
A8: 4 | B8: PT. POLYCHEMIE ASIA PACIFIC PERMAI | C8: HASLC01211001803 | D8: IMPORT | E8: HASPUL / CC | F8: GLDU9759745 & FCIU6060497 | G8: 2X20GP | H8: 013/QUO-VJL/11-2021 | I8: 000222 | J8: SHANGHAI | K8: UTC1 | L8: 44297 | M8: 44511 | N8: 44511 | O8: 44511 | P8: 44541 | Q8: PTP | R8: 44511 | S8: VJL21110052 101496(0450/INV-VJL/12-21) - 100395 | T8: - | U8: 475000 | V8: 50000 | W8: CIMB 705899545600 A/N RONALD TOBING | X8: -
V9: 100000 | W9: BCA 5390525798 A/N ASIAH | X9: -
A10: 5 | B10: PT. POLYCHEMIE ASIA PACIFIC PERMAI | C10: XBJD031400 | D10: IMPORT | E10: CNC / CC | F10: SEGU2000919 | G10: 1X20GP | H10: 014/QUO-VJL/11-2021 | I10: 000224 | J10: NINGBO | K10: UTC1 | L10: 44358 | M10: 13/11/2021 | N10: 15/11/2021 | O10: 15/11/2021 | P10: 16/11/2021 | Q10: MJT | R10: 26/11/2021 | S10: 10063 | T10: - | U10: 339000 | V10: 50000 | W10: CIMB 705899545600 A/N RONALD TOBING | X10: 44867
V11: 50000 | W11: BCA 5390525798 A/N ASIAH | X11: 44867
A12: 6 | B12: PT. POLYCHEMIE ASIA PACIFIC PERMAI | C12: HASLC01211100442 | D12: IMPORT | E12: HASPUL / CC | F12: BSIU3036391 | G12: 1X20GP | H12: 033/QUO-VJL/11-2021 | I12: 000225 | J12: SHANGHAI | K12: UTC1 | L12: 13/11/2021 | M12: 21/11/2021 | N12: 22/11/2021 | O12: 23/11/2021 | P12: 24/11/2021 | Q12: PTP | R12: 22/11/2021 | S12: VJL21110114 101303 | T12: - | U12: 387000 | V12: - | W12: CIMB 705899545600 A/N RONALD TOBING | X12: -
V13: - | W13: BCA 5390525798 A/N ASIAH | X13: -
A14: 7 | B14: PT. POLYCHEMIE ASIA PACIFIC PERMAI | C14: IRSINJKT2122705 | D14: IMPORT | E14: GANINDO / CC | F14: RFCU2021693 | G14: 1X20GP | H14: 051/QUO-VJL/11-2021 | I14: 000233 | J14: SINGAPORE | K14: UTC1 | L14: 22/11/2021 | M14: 24/11/2021 | N14: 25/11/2021 | O14: 25/11/2021 | P14: 26/11/2021 | Q14: MJT | R14: 23/11/2021 | S14: VJL21110127 101495 | T14: - | U14: 693050 | V14: 50000 | W14: CIMB 705899545600 A/N RONALD TOBING | X14: -
V15: 50000 | W15: BCA 5390525798 A/N ASIAH | X15: -
A16: 8 | B16: PT. POLYCHEMIE ASIA PACIFIC PERMAI | C16: HASLC01211005717 | D16: IMPORT | E16: HASPUL / CC | F16: BEAU2408236 & TCKU1762357 | G16: 2X20GP | H16: 034/QUO-VJL/11-2021 | I16: 000225 | J16: SHANGHAI | K16: KOJA | L16: 14/11/2021 | M16: 26/11/2021 | N16: 26/11/2021 | O16: 26/11/2021 | P16: 27/11/2021 | Q16: PMP | R16: 25/11/2021 | S16: VJL21110148 101198 | T16: - | U16: 579000 | V16: 50000 | W16: CIMB 705899545600 A/N RONALD TOBING | X16: -
V17: 100000 | W17: BCA 5390525798 A/N ASIAH | X17: -
A18: 9 | B18: PT. POLYOSHIKA | C18: COAU7234585500 | D18: IMPORT | E18: COSCO / CC | F18: CSNU1576346 & CSLU1126188 | G18: 2X20GP | H18: 052/QUO-VJL/11-2021 | I18: 000052 | J18: PASIR GUDANG | K18: UTC1 | L18: 19/11/2021 | M18: 26/11/2021 | N18: 26/11/2021 | O18: 27/11/2021 | P18: 28/11/2021 | Q18: MJT | R18: 25/11/2021 | S18: VJL21110149 101300 | T18: PAID | U18: 581000 | V18: 50000 | W18: CIMB 705899545600 A/N RONALD TOBING | X18: 31/12/2021
V19: 100000 | W19: BCA 5390525798 A/N ASIAH
A20: 10 | B20: PT. POLYCHEMIE ASIA PACIFIC PERMAI | C20: COAU7234686140 | D20: IMPORT | E20: COSCO / CC | F20: BMOU2718540 | G20: 1X20GP | H20: 053/QUO-VJL/11-2021 | I20: 000234 | J20: PASIR GUDANG | K20: UTC1 | L20: 19/11/2021 | M20: 26/11/2021 | N20: 26/11/2021 | O20: 27/11/2021 | P20: 28/11/2021 | Q20: PMP | R20: 29/11/2021 | S20: VJL21110165 101216 | T20: - | U20: 379000 | V20: 50000 | W20: CIMB 705899545600 A/N RONALD TOBING | X20: -
V21: 50000 | W21: BCA 5390525798 A/N ASIAH | X21: -
A22: 11 | B22: PT. POLYCHEMIE ASIA PACIFIC PERMAI | C22: SITGNBJT865988 | D22: IMPORT | E22: SITC / CC | F22: SEGU3465037 | G22: 1X20GP | H22: 059/QUO-VJL/11-2021 | I22: 000235 | J22: NINGBO | K22: UTC1 | L22: 20/11/2021 | M22: 30/11/2021 | N22: 44208 | O22: 44239 | P22: 44239 | Q22: PMP | R22: 29/11/2021 | S22: VJL21110165 101216 | T22: - | U22: 255000 | V22: 50000 | W22: CIMB 705899545600 A/N RONALD TOBING | X22: -
V23: 50000 | W23: BCA 5390525798 A/N ASIAH | X23: -
A24: EXPORT
A25: 12 | B25: PT. KALOSO ARTHA INFINITY | C25: JKT21-00012/ANR | D25: EXPORT | E25: SCL | F25: 5.185 CBM | G25: LCL | H25: 028/QUO-VJL/11-2021 | I25: - | J25: ANTWERP | K25: - | L25: - | M25: - | N25: - | O25: - | P25: - | Q25: - | R25: 17/11/2021 | S25: VJL21110090 101175 | T25: - | U25: 1710125 | V25: - | W25: - | X25: -
A26: 13 | B26: PT. TETUKO ANUGERAH NUSANTARA | C26: JKT21-00016/BKK | D26: EXPORT | E26: FM GLOBAL | F26: 12.672CBM | G26: LCL | H26: 017/QUO-VJL/11-2021 | I26: - | J26: BANGKOK | K26: APW | L26: 25/11/2021 | M26: 44328 | N26: - | O26: - | P26: - | Q26: TAN | R26: 26/11/2021 | S26: 101227 | T26: 30/11/2021 | U26: 2650043 | V26: 5372928 | W26: BCA 6240441533 A/N UMIYATI | X26: 44267
A27: 14 | B27: PT. POLYCHEMIE ASIA PACIFIC PERMAI | C27: JKT21-00027/PKG | D27: EXPORT | E27: SCL | F27: 2.470CBM | G27: LCL | H27: 015/QUO-VJL/11-2021 | I27: - | J27: PORTKLANG | K27: DMV | L27: 27/11/2021 | M27: 44239 | N27: - | O27: STUF: 25/11/2021 | P27: - | Q27: GAFA | R27: 44359 | S27: 101264 | T27: - | U27: 2339850 | V27: 172900 | W27: CIMB 705899545600 A/N RONALD TOBING | X27: 44867
V28: 500000 | W28: BCA 5390525798 A/N ASIAH | X28: 44867
A29: 15 | B29: PT. GARUDAFOOD PUTRA PUTRI JAYA TBK | C29: ONEYSUBB95625800 | D29: EXPORT | E29: MACOLINE SBY | F29: ONEU0138486 & KKFU8156765 | G29: 2X40HQ | H29: 018/QUO-VJL/11-2021 | I29: - | J29: YANGON | K29: SBY | L29: 28/11/2021 | M29: 14/12/2021 | N29: - | O29: STUF: 24/11/2021 | P29: - | Q29: GARUDA | R29: 44481 | S29: 101266 | T29: - | U29: 7585590 | V29: 750000 | W29: BCA 5390525798 A/N ASIAH | X29: -
T30: Total Profit | U30: =SUM(U4:U29) -> 22163658 | V30: =V7+V9+V11+V29+V17+V15+V19+V21+V28 -> 1850000 | W30: ASIAH
T31: Komisi Ika | U31: =U30*10/100 -> 2216365.8
A34: LIST CUST DES 2021
A35: No. | B35: Cust | C35: BL Number | D35: SHIPMENT | E35: PELAYARAN | F35: Cont/Package | G35: Qty | H35: Quot No. | I35: No. AJU | J35: POL/POD | K35: LOKASI TIMBUN | L35: ETD | M35: ETA | N35: SPPB | O35: KIRIM CARGO | P35: BONGKAR | Q35: MOBIL | R35: KIRIM INV | S35: JO NO | T35: PAYMENT INV | U35: PROFIT | V35: REFUND CUST | W35: REK | X35: TRANSFER DATE
A36: IMPORT
A37: 1 | B37: PT. POLYCHEMIE ASIA PACIFIC PERMAI | C37: SITTADJT037174 | D37: IMPORT | E37: SITC / CC | F37: SITU2816120 | G37: 1X20GP | H37: 051/QUO-VJL/12-2021 | I37: 000252 | J37: QINGDAO | K37: UTC1 | L37: 15/12/2021 | M37: 22/12/2021 | N37: 23/12/2021 | O37: 23/12 REPO KIRIM 26/12 | P37: 27/12/2021 | Q37: PMP / REPO | R37: 17/12/2021 | S37: VJL21120114 101353 | T37: - | U37: 1374500 | V37: 50000 | W37: CIMB 705899545600 A/N RONALD TOBING | X37: -
V38: 50000 | W38: BCA 5390525798 A/N ASIAH | X38: -
A39: 2 | B39: PT. POLYCHEMIE ASIA PACIFIC PERMAI | C39: OOLU4110288780 | D39: IMPORT | E39: OOCL / CC | F39: OOLU0412330 | G39: 1X20GP | H39: 036/QUO-VJL/11-2021 | I39: 000231 | J39: OSAKA | K39: KOJA | L39: 13/11/2021 | M39: 44208 | N39: 44208 | O39: 44239 | P39: 44267 | Q39: PMP | R39: 29/12/2021 | S39: VJL21110176 101217 | T39: - | U39: 339000 | V39: 50000 | W39: CIMB 705899545600 A/N RONALD TOBING | X39: -
V40: 50000 | W40: BCA 5390525798 A/N ASIAH | X40: -
A41: 3 | B41: PT. POLYOSHIKA | C41: EGLV020100582260 | D41: IMPORT | E41: EVERGREEN / CC | F41: DRYU2574593 | G41: 1X20GP | H41: 058/QUO-VJL/11-2021 | I41: 000051 | J41: OSAKA | K41: NPCT1 | L41: 44511 | M41: 44208 | N41: 44208 | O41: 44239 | P41: 44239 | Q41: PMP | R41: 29/12/2021 | S41: VJL21110177 101226 | T41: - | U41: 419000 | V41: 50000 | W41: CIMB 705899545600 A/N RONALD TOBING | X41: -
V42: 50000 | W42: BCA 5390525798 A/N ASIAH | X42: -
A43: 4 | B43: PT. POLYCHEMIE ASIA PACIFIC PERMAI | C43: CMZ0654835 | D43: IMPORT | E43: CNC / CC | F43: ECMU1899665 | G43: 1X20GP | H43: 068/QUO-VJL/11-2021 | I43: 000237 | J43: SHEKOU | K43: JICT1 | L43: 44267 | M43: 44239 | N43: 44267 | O43: 44267 | P43: 44298 | Q43: PMP | R43: 29/12/2021 | S43: VJL21120001 101237 | T43: - | U43: 339000 | V43: 50000 | W43: CIMB 705899545600 A/N RONALD TOBING | X43: -
V44: 50000 | W44: BCA 5390525798 A/N ASIAH | X44: -
A45: 5 | B45: PT. POLYCHEMIE ASIA PACIFIC PERMAI | C45: 214634575 | D45: IMPORT | E45: SEALAND / CC | F45: MSKU4042020 | G45: 1X20GP | H45: 004/QUO-VJL/12-2021 | I45: 000239 | J45: NANSHA | K45: NPCT1 | L45: 24/11/2021 | M45: 44298 | N45: 44359 | O45: 44359 | P45: 44389 | Q45: PMP | R45: 44632 | S45: VJL21120013 101252 | T45: - | U45: 339000 | V45: 50000 | W45: CIMB 705899545600 A/N RONALD TOBING | X45: -
V46: 50000 | W46: BCA 5390525798 A/N ASIAH | X46: -
A47: 6 | B47: PT. POLYCHEMIE ASIA PACIFIC PERMAI | C47: DLCA52886900B | D47: IMPORT | E47: FLI / CC | F47: HMMU2096336 | G47: 1X20GP | H47: 006/QUO-VJL/12-2021 | I47: 000241 | J47: DALIAN | K47: KOJA | L47: 23/11/2021 | M47: 44298 | N47: 44359 | O47: 44359 | P47: 44359 | Q47: PMP | R47: 29/12/2021 | S47: VJL21120014 101253 | T47: - | U47: 339000 | V47: 50000 | W47: CIMB 705899545600 A/N RONALD TOBING | X47: -
V48: 50000 | W48: BCA 5390525798 A/N ASIAH | X48: -
A49: 7 | B49: PT. POLYCHEMIE ASIA PACIFIC PERMAI | C49: ONEYBKKBBS839300 | D49: IMPORT | E49: ONE / CC | F49: NYKU9716490 | G49: 1X20GP | H49: 007/QUO-VJL/12-2021 | I49: 000240 | J49: LAEM CHABANG | K49: TMAL | L49: 44359 | M49: 44451 | N49: 44481 | O49: 44512 | P49: 44512 | Q49: MJT | R49: 29/12/2021 | S49: VJL21120048 101452 | T49: - | U49: 389000 | V49: 50000 | W49: CIMB 705899545600 A/N RONALD TOBING | X49: -
V50: 50000 | W50: BCA 5390525798 A/N ASIAH | X50: -
A51: 8 | B51: PT. POLYCHEMIE ASIA PACIFIC PERMAI | C51: AAPW603804 | D51: IMPORT | E51: CNC / CC | F51: TRLU9755129 | G51: 1X20GP | H51: 028/QUO-VJL/12-2021 | I51: 000236 | J51: QINGDAO | K51: JICT1 | L51: 44239 | M51: 44451 | N51: 44481 | O51: 44481 | P51: 44512 | Q51: PMP | R51: 29/12/2021 | S51: VJL21120049 101285 | T51: - | U51: 325000 | V51: 50000 | W51: CIMB 705899545600 A/N RONALD TOBING | X51: -
V52: 50000 | W52: BCA 5390525798 A/N ASIAH | X52: -
A53: 9 | B53: PT. POLYOSHIKA | C53: 131-58412992 | D53: IMPORT | E53: JP-AIR / OF & CC | F53: 836KG | G53: LCL UDARA | H53: 042/QUO-VJL/12-2021 | I53: 000054 | J53: NARITA | K53: RPX | L53: 44481 | M53: 44512 | N53: 13/12/2021 | O53: 14/12/2021 | P53: 14/12/2021 | Q53: JOHN | R53: 13/12/2022 | S53: VJL21120081 101314 | T53: PAID | U53: 32298630 | V53: 500000 | W53: CIMB 705899545600 A/N RONALD TOBING | X53: 31/12/2021
V54: 6000000 | W54: BCA 5390525798 A/N ASIAH
A55: 10 | B55: PT. POLYCHEMIE ASIA PACIFIC PERMAI | C55: SITYCJT2102603 | D55: IMPORT | E55: SITC / CC | F55: TRHU3140469 | G55: 1X20GP | H55: 009/QUO-VJL/12-2021 | I55: 000244 | J55: YOKKAICHI | K55: JICT1 | L55: 24/11/2021 | M55: 25/12/2021 | N55: 28/12/2021 | O55: 28/12/2021 | P55: 29/12/2021 | Q55: PMP | R55: 21/01/2021 | S55: VJL21120127 101362 | T55: - | U55: 331000 | V55: 50000 | W55: CIMB 705899545600 A/N RONALD TOBING | X55: -
V56: 50000 | W56: BCA 5390525798 A/N ASIAH | X56: -
A57: 11 | B57: PT. POLYCHEMIE ASIA PACIFIC PERMAI | C57: SITTQJT2101645 | D57: IMPORT | E57: SITC / CC | F57: TLLU3257982 | G57: 1X20GP | H57: 008/QUO-VJL/12-2021 | I57: 000246 | J57: TOKUYAMA | K57: JICT1 | L57: 23/11/2021 | M57: 25/12/2021 | N57: 28/12/2021 | O57: 28/12/2021 | P57: 29/12/2021 | Q57: PMP | R57: 21/01/2021 | S57: VJL21120126 101361 | T57: - | U57: 333000 | V57: 50000 | W57: CIMB 705899545600 A/N RONALD TOBING | X57: -
V58: 50000 | W58: BCA 5390525798 A/N ASIAH | X58: -
A59: 12 | B59: PT. POLYCHEMIE ASIA PACIFIC PERMAI | C59: HW21120887N | D59: IMPORT | E59: SCL / OF & CC | F59: 32 DRUM - 10 CBM | G59: LCL | H59: 059/QUO-VJL/12-2021 | I59: 000250 | J59: SHANGHAI | K59: APW / RAYA | L59: 15/12/2021 | M59: 26/12/2021 | N59: 28/12/2021 | O59: 29/12/2021 | P59: 30/12/2021 | Q59: GAFA | R59: 21/01/2021 | S59: VJL21120177 101538 | T59: - | U59: 5902700 | V59: 2728000 | W59: CIMB 705899545600 A/N RONALD TOBING | X59: -
V60: 1456000 | W60: BCA 5390525798 A/N ASIAH | X60: -
A61: EXPORT
A62: 13 | B62: PT. SATYA LIPRINDO | C62: JKTCB21010067 | D62: EXPORT | E62: RCL / OF | F62: REGU5117493 | G62: 1X40HQ | H62: 005/QUO-VJL/12-2021 | I62: - | J62: JKT-SINGAPORE | K62: - | L62: 23/12/2021 | M62: 27/12/2021 | N62: STUFF : 23/12/21 | O62: - | P62: - | Q62: SATYA | R62: 29/12/2021 | S62: VJL21120149 101376 | T62: - | U62: 2163550 | V62: 710000 | W62: BCA 8290299439 A/N PINDI PAULINA | X62: -
V63: 2130000 | W63: BCA 0830129774 A/N FELIPE FANGIO CHUNG | X63: -
T64: Total Profit | U64: =SUM(U37:U63) -> 44892380 | V64: =V38+V40+V42+V44+V46+V48+V50+V52+V54+V56+V58+V60 -> 7956000
T65: Target | U65: 30000000 | V65: (-)
T66: add 5% | U66: =U64-U65 -> 14892380
T67: Komisi 10% | U67: =U64*10/100 -> 4489238
T68: Komisi 5% | U68: =U66*5/100 -> 744619 | V68: (+)
U69: =U67+U68 -> 5233857 | W69: =U69+U31 -> 7450222.8 | X69: Nov- Des
A71: LIST CUST JAN 2022
A72: No. | B72: Cust | C72: BL Number | D72: SHIPMENT | E72: PELAYARAN | F72: Cont/Package | G72: Qty | H72: Quot No. | I72: No. AJU | J72: POL/POD | K72: LOKASI TIMBUN | L72: ETD | M72: ETA | N72: SPPB | O72: KIRIM CARGO | P72: BONGKAR | Q72: MOBIL | R72: KIRIM INV | S72: JO NO | T72: PAYMENT INV | U72: PROFIT | V72: REFUND CUST | W72: REK | X72: TRANSFER DATE
A73: IMPORT
A74: 1 | B74: PT. POLYOSHIKA | C74: EGLV020100638290 | D74: IMPORT | E74: EVERGREEN / CC | F74: OCGU2019199 | G74: 1X20GP | H74: 052/QUO-VJL/12-2021 | I74: 000053 | J74: OSAKA | K74: NPCT1 | L74: 44239 | M74: 31/12/2021 | N74: 44562 | O74: 44593 | P74: 44621 | Q74: PTP | R74: 21/01/2022 | S74: 101464 | T74: - | U74: 283000 | V74: 50000 | W74: BCA 8421242259 A/N RONAL L TOBING | X74: DONE
V75: 50000 | W75: BCA 5390525798 A/N ASIAH | X75: DONE
A76: 2 | B76: PT. POLYOSHIKA | C76: ONEYTYOBN3499300 | D76: IMPORT | E76: ONE / CC | F76: CXDU1755682 | G76: 1X20GP | H76: 084/QUO-VJL/12-2021 | I76: 000055 | J76: KOBE | K76: NPCT1 | L76: 27/12/2021 | M76: 44317 | N76: 44774 | O76: 44805 | P76: 44835 | Q76: PMP | R76: 26/01/2022 | S76: 10007 | T76: - | U76: 333000 | V76: 50000 | W76: BCA 8421242259 A/N RONAL L TOBING | X76: DONE
V77: 50000 | W77: BCA 5390525798 A/N ASIAH | X77: DONE
A78: 3 | B78: PT. POLYCHEMIE ASIA PACIFIC PERMAI | C78: YMLUI243769906 | D78: IMPORT | E78: YANGMING / CC | F78: CAIU6316240, SEGU2821133 & SEGU2856649 | G78: 3X20GP | H78: 010/QUO-VJL/12-2021 | I78: 000245 | J78: WUHAN | K78: TPK1 | L78: 19/11/2021 | M78: 44317 | N78: 44835 | O78: 44835 | P78: 44866 | Q78: PMP | R78: 26/01/2022 | S78: 101554 | T78: - | U78: 831000 | V78: 50000 | W78: BCA 8421242259 A/N RONAL L TOBING | X78: DONE
V79: 150000 | W79: BCA 5390525798 A/N ASIAH | X79: DONE
A80: 4 | B80: PT. POLYCHEMIE ASIA PACIFIC PERMAI | C80: EGLV003104672476 | D80: IMPORT | E80: EVERGREEN / CC | F80: MAGU2203362 | G80: 1X20GP | H80: 023/QUO-VJL/01/2022 | I80: 000256 | J80: KAOHSIUNG | K80: NPCT1 | L80: 44593 | M80: 44866 | N80: 44866 | O80: 44896 | P80: 13/01/2022 | Q80: PMP | R80: 19/03/2022 | S80: 10043 | T80: - | U80: 400000 | V80: 50000 | W80: BCA 8421242259 A/N RONAL L TOBING | X80: 44652
V81: 50000 | W81: BCA 5390525798 A/N ASIAH | X81: 44652
A82: 5 | B82: PT. POLYCHEMIE ASIA PACIFIC PERMAI | C82: KMTCXGG2071558 | D82: IMPORT | E82: KMTC / CC | F82: CAIU3596488 | G82: 1X20GP | H82: 085/QUO-VJL/12-2021 | I82: 000255 | J82: XINGANG | K82: KOJA | L82: 23/12/2021 | M82: 14/01/2022 | N82: 14/01/2022 | O82: 16/01/2022 | P82: 17/01/2022 | Q82: PMP | R82: 28/01/2022 | S82: 101582 | T82: 44672 | U82: 331000 | V82: 50000 | W82: BCA 8421242259 A/N RONAL L TOBING | X82: 44673
V83: 50000 | W83: BCA 5390525798 A/N ASIAH | X83: 44673
A84: 6 | B84: PT. POLYCHEMIE ASIA PACIFIC PERMAI | C84: KMTCSHAI621935 | D84: IMPORT | E84: KMTC / CC | F84: SEGU2407530 & SEGU2431876 | G84: 2X20GP | H84: 034/QUO-VJL/01/2022 | I84: 000257 | J84: SHANGHAI | K84: TPK1 | L84: 44621 | M84: 44866 | N84: 44866 | O84: 44896 | P84: 13/01/2022 | Q84: PMP | R84: 23/01/2022 | S84: 101555 | T84: 14/03/2022 | U84: 581000 | V84: 50000 | W84: BCA 8421242259 A/N RONAL L TOBING | X84: 44652
V85: 100000 | W85: BCA 5390525798 A/N ASIAH | X85: 44652
A86: 7 | B86: PT. AIR SURYA RADIATOR | C86: DSCCJTP22010007 | D86: IMPORT | E86: BINEX / CC | F86: 2 PKG - 104KG - 0.17 CBM | G86: LCL | H86: 062/QUO-VJL/01-2022 | I86: 001519 | J86: BUSAN | K86: APW / RAYA | L86: 44896 | M86: 22/01/2022 | N86: 25/01/2022 | O86: 26/01/2022 | P86: 26/01/2022 | Q86: JOHN | R86: 44806 | S86: 10114 | T86: - | U86: 1379000 | V86: 250000 | W86: BCA 5390525798 A/N ASIAH | X86: DONE
A87: 8 | B87: PT. POLYOSHIKA | C87: SITGNBJT876563 | D87: IMPORT | E87: SITC / CC | F87: BEAU2707685 & TLLU3126220 | G87: 2X20GP | H87: 075/QUO-VJL/01-2022 | I87: 000057 | J87: NINGBO | K87: TPK1 | L87: 19/01/2022 | M87: 27/01/2022 | N87: 27/01/2022 | O87: 29/01/2022 REPO - EDY | P87: 31/01/2022 | Q87: MJT | R87: 19/03/2022 | S87: 10125 | T87: 44662 | U87: 2281000 | V87: 50000 | W87: BCA 8421242259 A/N RONAL L TOBING | X87: 44665
V88: 500000 | W88: BCA 5390525798 A/N ASIAH | X88: 44665
A89: 9 | B89: PT. POLYOSHIKA | C89: ONEYTYOBP4090700 | D89: IMPORT | E89: ONE / CC | F89: UETU277354 | G89: 1X20GP | H89: 059/QUO-VJL/01-2022 | I89: 000056 | J89: KOBE | K89: NPCT1 | L89: 44713 | M89: 27/01/2022 | N89: 27/01/2022 | O89: 29/01/2022 REPO - EDY | P89: 31/01/2022 | Q89: MJT | R89: 19/03/2022 | S89: 10130 | T89: 44662 | U89: 1356000 | V89: 50000 | W89: BCA 8421242259 A/N RONAL L TOBING | X89: 44665
V90: 50000 | W90: BCA 5390525798 A/N ASIAH | X90: 44665
A91: 10 | B91: PT. POLYCHEMIE ASIA PACIFIC PERMAI | C91: EGLV003104402363 | D91: IMPORT | E91: EVERGREEN / CC | F91: EITU3051561 | G91: 1X20GP | H91: 077/QUO-VJL/01-2022 | I91: 000259 | J91: KAOHSIUNG | K91: NPCT1 | L91: 21/01/2022 | M91: 27/01/2022 | N91: 26/01/2022 | O91: 29/01/2022 REPO - PMP | P91: 31/01/2022 | Q91: PMP | R91: 19/03/2022 | S91: 10133 | T91: - | U91: 1593000 | V91: 50000 | W91: BCA 8421242259 A/N RONAL L TOBING | X91: 44652
V92: 50000 | W92: BCA 5390525798 A/N ASIAH | X92: 44652
A93: 11 | B93: PT. AIR SURYA RADIATOR | C93: 205-27024664 | D93: IMPORT | E93: NIPON / CC | F93: 122 KGS - 1 PLT | G93: LCL UDARA | H93: 061/QUO-VJL/01-2022 | I93: 001508 | J93: SHANGHAI | K93: UNEX | L93: 14/01/2022 | M93: 18/01/2022 | N93: 21/01/2022 | O93: 21/01/2022 | P93: 22/01/2022 | Q93: JOHN | R93: 27/01/2022 | S93: 10141 | T93: 14/03/2022 | U93: 910000 | V93: 650000 | W93: BCA 5390525798 A/N ASIAH | X93: DONE
A94: 12 | B94: PT. POLYCHEMIE ASIA PACIFIC PERMAI | C94: GXM22010100 / COAU7236523510 | D94: IMPORT | E94: GRAND / COSCO - CC & OF | F94: FCIU5761110 | G94: 1X20GP | H94: 028/QUO-VJL/01-2022 | I94: 000264 | J94: XIAMEN | K94: NPCT1 | L94: 26/01/2022 | M94: 44622 | N94: 44775 | O94: 44775 | P94: 44806 | Q94: PMP | R94: 19/03/2022 | S94: 10149 | T94: 44650 | U94: 4750000 | V94: 1050000 | W94: BCA 8421242259 A/N RONAL L TOBING | X94: 44659
V95: 500000 | W95: BCA 5390525798 A/N ASIAH | X95: 44659
A96: 13 | B96: PT. POLYCHEMIE ASIA PACIFIC PERMAI | C96: HASLC01211205452 | D96: IMPORT | E96: HASPUL / CC | F96: SKLU2030541 & TCKU3676664 | G96: 2X20GP | H96: 083/QUO-VJL/01-2022 | I96: 000258 | J96: SHANGHAI | K96: TPK1 | L96: 19/01/2022 | M96: 27/01/2022 | N96: 28/01/2022 | O96: 30/01/2022 | P96: 31/01/2022 | Q96: PTP | R96: 19/03/2022 | S96: 10150 | T96: 44650 | U96: 481000 | V96: 50000 | W96: BCA 8421242259 A/N RONAL L TOBING | X96: 44659
V97: 100000 | W97: BCA 5390525798 A/N ASIAH | X97: 44659
A98: 14 | B98: PT. POLYCHEMIE ASIA PACIFIC PERMAI | C98: EMJKT001B2641 | D98: IMPORT | E98: SCL / OF & CC | F98: 1 PLT / 2.30 CBM | G98: LCL | H98: 053/QUO-VJL/12-2021 | I98: 000254 | J98: GENOVA | K98: PESA | L98: 44481 | M98: 17/01/2022 | N98: 17/01/2022 | O98: 17/01/2022 | P98: 18/01/2022 | Q98: GAFA | R98: 44806 | S98: 100619 | T98: - | U98: 4543385 | V98: 2163300 | W98: BCA 8421242259 A/N RONAL L TOBING | X98: DONE
V99: 2000000 | W99: BCA 5390525798 A/N ASIAH | X99: DONE
A100: EXPORT
A101: 15 | B101: PT. POLYCHEMIE ASIA PACIFIC PERMAI | C101: KMTCJKT3997741 | D101: EXPORT | E101: KMTC / OF & CC | F101: KMTU7422161 | G101: 1X20GP | H101: 024/QUO-VJL/01-2022 | I101: 031707 | J101: YATSUSHIRO - JAPAN | K101: BIMARUNA - KOJA | L101: 18/01/2022 | M101: 29/01/2022 | N101: NPE 14/01/2022 | O101: STUFF : 14/01/2022 | Q101: PMP | R101: 28/01/2022 | S101: 10086 | T101: 44672 | U101: 2603550 | V101: 840000 | W101: BCA 8421242259 A/N RONAL L TOBING | X101: 44673
V102: 500000 | W102: BCA 5390525798 A/N ASIAH | X102: 44673
A103: 16 | B103: PT. POLYCHEMIE ASIA PACIFIC PERMAI | C103: KMTCJKT3998736 | D103: EXPORT | E103: KMTC / OF & CC | F103: TEMU3904753 | G103: 1X20GP | H103: 025/QUO-VJL/01-2022 | I103: 031706 | J103: CAT LAI - HCM - VN | K103: BIMARUNA - KOJA | L103: 19/01/2022 | M103: 22/01/2022 | N103: NPE 14/01/2022 | O103: STUFF : 14/01/2022 | Q103: PMP | R103: 28/01/2021 | S103: 10088 | T103: 44672 | U103: 1657040 | V103: 640000 | W103: BCA 8421242259 A/N RONAL L TOBING | X103: 44673
...

Sheet CICILAN EMAS 10GR
A1: ANGSURAN EMAS 10GR - 3THN (36 BULAN)
A4: No. | B4: Angsuran ke | C4: Jth Tempo | D4: Nominal | E4: Paid Tgl | F4: Keterangan
A5: 1 | B5: DP/UM | C5: 44585 | D5: 1394100 | E5: 44585 | F5: UPS
A6: 2 | B6: Admin | C6: 44585 | D6: 50000 | E6: 44585 | F6: UPS
A7: 3 | B7: 1 | C7: 44616 | D7: 303547 | E7: 44609 | F7: VIA MANDIRI + 2,5K ADM
A8: 4 | B8: 2 | C8: 44644 | D8: 303547 | E8: 44628 | F8: VIA MANDIRI + 2,5K ADM
A9: 5 | B9: 3 | C9: 44675 | D9: 303547 | E9: 44653 | F9: VIA MANDIRI + 2,5K ADM
A10: 6 | B10: 4 | C10: 44705 | D10: 303547 | E10: 44685 | F10: VIA MANDIRI + 2,5K ADM
A11: 7 | B11: 5 | C11: 44736 | D11: 303547 | E11: 44723 | F11: VIA MANDIRI + 2,5K ADM
A12: 8 | B12: 6 | C12: 44766 | D12: 303547 | E12: 44746 | F12: VIA MANDIRI + 2,5K ADM
A13: 9 | B13: 7 | C13: 44797 | D13: 303547 | E13: 44774 | F13: VIA BCA + 2,5K ADM
A14: 10 | B14: 8 | C14: 44828 | D14: 303547 | E14: 44810 | F14: VIA BCA + 2,5K ADM
A15: 11 | B15: 9 | C15: 44858 | D15: 303547 | E15: 44846 | F15: VIA BCA + 2,5K ADM
A16: 12 | B16: 10 | C16: 44889 | D16: 303547 | E16: 44886 | F16: VIA BCA + 2,5K ADM
A17: 13 | B17: 11 | C17: 44919 | D17: 303547 | E17: 44900 | F17: VIA BCA + 2,5K ADM
A18: 14 | B18: 12 | C18: 44950 | D18: 303547 | E18: 44933 | F18: VIA BCA + 2,5K ADM
... A25: 21 | B25: 19 | C25: 45162 | D25: 303547 | E25: 45140 | F25: VIA BCA + 2,5K ADM
A26: 22 | B26: 20 | C26: 45193 | D26: 303547 | F26: VIA BCA + 2,5K ADM
A27: 23 | B27: 21 | C27: 45223 | D27: 303547 | F27: VIA BCA + 2,5K ADM
A28: 24 | B28: 22 | C28: 45254 | D28: 303547 | F28: VIA BCA + 2,5K ADM
A29: 25 | B29: 23 | C29: 45284 | D29: 303547 | F29: VIA BCA + 2,5K ADM
A30: 26 | B30: 24 | C30: 45315 | D30: 303547 | F30: VIA BCA + 2,5K ADM
A31: 27 | B31: 25 | C31: 45346 | D31: 303547 | F31: VIA BCA + 2,5K ADM
A32: 28 | B32: 26 | C32: 45375 | D32: 303547 | F32: VIA BCA + 2,5K ADM
A33: 29 | B33: 27 | C33: 45406 | D33: 303547 | F33: VIA BCA + 2,5K ADM
A34: 30 | B34: 28 | C34: 45436 | D34: 303547 | F34: VIA BCA + 2,5K ADM
A35: 31 | B35: 29 | C35: 45467 | D35: 303547 | F35: VIA BCA + 2,5K ADM
A36: 32 | B36: 30 | C36: 45497 | D36: 303547 | F36: VIA BCA + 2,5K ADM
A37: 33 | B37: 31 | C37: 45528 | D37: 303547 | F37: VIA BCA + 2,5K ADM
... A42: 38 | B42: 36 | C42: 45650 | D42: 303547 | F42: VIA BCA + 2,5K ADM
A43: Total Keseluruhan | D43: =SUM(D5:D41) -> 12068245 | E43: Note :
A44: Harga Jual Emas
A45: Laba / Rugi

Sheet LISTRIK NENEK
A1: PLN NENEK BULANAN
A4: No. | B4: Jth Tempo | C4: Nominal | D4: Paid Tgl | E4: Keterangan
A5: 1 | B5: 44464 | C5: 169675 | D5: 44458 | E5: Listrik + Adm 3rb
A6: 2 | B6: 44494 | C6: 147745 | D6: 44488 | E6: Listrik + Adm 3rb
A7: 3 | B7: 44525 | C7: 189306 | D7: 44505 | E7: Listrik + Adm 3rb
A8: 4 | B8: 44555 | C8: 136280 | D8: 44535 | E8: Listrik + Adm 3rb
A9: 5 | B9: 44586 | C9: 147745 | D9: 44566 | E9: Listrik + Adm 3rb
A10: 6 | B10: 44617 | C10: 142013 | D10: 44597 | E10: Listrik + Adm 3rb
A11: 7 | B11: 44645 | C11: 134847 | D11: 44625 | E11: Listrik + Adm 3rb
A12: 8 | B12: 44676 | C12: 147611 | D12: 44656 | E12: Listrik + Adm 3rb
A13: 9 | B13: 44706 | C13: 154911 | D13: 44686 | E13: Listrik + Adm 3rb
A14: 10 | B14: 44737 | C14: 188006 | D14: 44733 | E14: Listrik + Adm 3rb
A15: 11 | B15: 44767 | C15: 146312 | D15: 44747 | E15: Listrik + Adm 3rb
A16: 12 | B16: 44798 | C16: 167809 | D16: 44778 | E16: Listrik + Adm 3rb
... A27: 23 | B27: 45132 | C27: 253796 | D27: 44747 | E27: Listrik + Adm 3rb
A28: 24 | B28: 45163 | E28: Listrik + Adm 3rb
A29: 25 | B29: 45194 | E29: Listrik + Adm 3rb
A30: 26 | B30: 45224 | E30: Listrik + Adm 3rb
A31: 27 | B31: 45255 | E31: Listrik + Adm 3rb
A32: 28 | B32: 45285 | E32: Listrik + Adm 3rb
A33: 29 | B33: 45316 | E33: Listrik + Adm 3rb
A34: 30 | B34: 45347 | E34: Listrik + Adm 3rb
A35: 31 | B35: 45376 | E35: Listrik + Adm 3rb
A36: 32 | B36: 45407 | E36: Listrik + Adm 3rb
A37: 33 | B37: 45437 | E37: Listrik + Adm 3rb
A38: 34 | B38: 45468 | E38: Listrik + Adm 3rb
A39: 35 | B39: 45498 | E39: Listrik + Adm 3rb
... A44: 40 | B44: 45651 | E44: Listrik + Adm 3rb
C46: =SUM(C5:C44) -> 3876233

Sheet LISTRIK, IPL & AIR PMA
A1: KEBUTUHAN LISTRIK, IPL, AIR DLL PMA
A4: No. | B4: Jth Tempo | C4: Nominal | D4: Paid Tgl | E4: Keterangan
A5: 1 | B5: - | C5: 55000 | D5: 44391 | E5: Akses Mobil
A6: 2 | B6: - | C6: 60500 | D6: 44391 | E6: Other
A7: 3 | B7: - | C7: 55000 | D7: 44446 | E7: Akses Motor
A8: 4 | B8: 44459 | C8: 347404 | D8: 44446 | E8: Listrik & Air
A9: 5 | B9: 44489 | C9: 701887 | D9: 44477 | E9: Listrik & Air
A10: 6 | B10: 44520 | C10: 649650 | D10: 44505 | E10: Listrik & Air
A11: 7 | B11: 44550 | C11: 477806 | D11: 44539 | E11: Listrik & Air
A12: 8 | B12: 44581 | C12: 568447 | D12: 44567 | E12: Listrik & Air
A13: 9 | B13: 44597 | C13: 385000 | D13: 44597 | E13: Akses Patah
A14: 10 | B14: 44612 | C14: 603896 | D14: 44597 | E14: Listrik & Air
A15: 11 | B15: 44640 | C15: 584992 | D15: 44628 | E15: Listrik & Air
A16: 12 | B16: 44671 | C16: 549804 | D16: 44653 | E16: Listrik & Air
A17: 13 | B17: 44691 | C17: 55000 | D17: 44691 | E17: Other
A18: 14 | B18: 44701 | C18: 531933 | D18: 44691 | E18: Listrik & Air
A19: 15 | B19: 44720 | C19: 99900 | D19: 44704 | E19: Other
... A35: 31 | B35: 45127 | C35: 2188366 | D35: 45140 | E35: Listrik, Air & IPL 3 Bulan
A36: 32 | B36: 45158 | E36: Listrik & Air
A37: 33 | B37: 45189 | E37: Listrik & Air
A38: 34 | B38: 45219 | E38: Listrik, Air & IPL 3 Bulan
A39: 35 | B39: 45250 | E39: Listrik & Air
A40: 36 | B40: 45280 | E40: Listrik & Air
A41: 37 | B41: 45311 | E41: Listrik, Air & IPL 3 Bulan
A42: 38 | B42: 45342 | E42: Listrik & Air
A43: 39 | B43: 45371 | E43: Listrik & Air
A44: 40 | B44: 45402 | E44: Listrik, Air & IPL 3 Bulan
A45: 41 | B45: 45432 | E45: Listrik & Air
A46: 42 | B46: 45463 | E46: Listrik & Air
A47: 43 | B47: 45493 | E47: Listrik, Air & IPL 3 Bulan
... A52: 48 | B52: 45646 | E52: Listrik & Air
B55: Total Sementara | C55: =SUM(C5:C52) -> 23909674

Sheet PMA
A1: CICILAN PMA STUDIO TD31B15 15TH / 180BULAN
A4: Angsuran ke | B4: Jth Tempo | C4: Nominal | D4: Paid Tgl | E4: Nominal | F4: Keterangan
A5: Booking Fee | B5: 44324 | C5: 20000000 | D5: 44324 | E5: =C5 -> 20000000
A6: Akad | B6: 44356 | C6: 11000000 | D6: 44356 | E6: =C6 -> 11000000 | F6: Via Mandiri (Hold dana 3,909,923) Lunas di refund
A7: 1 | B7: 44389 | C7: 3909923 | D7: - | E7: =C7 -> 3909923 | F7: Cek Mutasi Mandiri
A8: 2 | B8: 44420 | C8: 3909922 | D8: - | E8: =C8 -> 3909922 | F8: Cek Mutasi Mandiri
A9: 3 | B9: 44451 | C9: 1888124 | D9: 44482 | E9: =SUM(C9:C11) -> 3909922
B10: 44451 | C10: 384347 | D10: 44483
B11: 44451 | C11: 1637451 | D11: 44483
B12: 44451 | C12: 200000 | D12: 44483 | E12: =C12 -> 200000 | F12: Late Charges
A13: 4 | B13: 44481 | C13: 705240 | D13: 44480 | E13: =SUM(C13:C15) -> 3909923
B14: 44481 | C14: 1561431 | D14: 44480
B15: 44481 | C15: 1643252 | D15: 44480
A16: 5 | B16: 44512 | C16: 2257318 | D16: 44511 | E16: =SUM(C16:C17) -> 3909923
B17: 44512 | C17: 1652605 | D17: 44511
A18: 6 | B18: 44542 | C18: 2249767 | D18: 44543 | E18: =SUM(C18:C19) -> 3909922
B19: 44542 | C19: 1660155 | D19: 44543
A20: 7 | B20: 44573 | C20: 2238370 | D20: 44572 | E20: =SUM(C20:C21) -> 3909922
B21: 44573 | C21: 1671552 | D21: 44572
A22: 8 | B22: 44604 | C22: 2195863 | D22: 44603 | E22: =SUM(C22:C23) -> 3909922
B23: 44604 | C23: 1714059 | D23: 44603
A24: 9 | B24: 44632 | C24: 2209658 | D24: 44631 | E24: =SUM(C24:C25) -> 3909923
B25: 44632 | C25: 1700265 | D25: 44631
A26: 10 | B26: 44663 | C26: 2212307 | D26: 44662 | E26: =SUM(C26:C27) -> 3909923
B27: 44663 | C27: 1697616 | D27: 44662
A28: 11 | B28: 44693 | C28: 2210083 | D28: 44692 | E28: =SUM(C28:C29) -> 3909923
B29: 44693 | C29: 1699840 | D29: 44692
A30: 12 | B30: 44724 | C30: 2202516 | D30: 44725 | E30: =SUM(C30:C31) -> 3909923
B31: 44724 | C31: 1707407 | D31: 44725
A32: 13 | B32: 44754 | C32: 2185030 | D32: 44753 | E32: =SUM(C32:C33) -> 3909923
B33: 44754 | C33: 1724893 | D33: 44753
A34: 14 | B34: 44785 | C34: 2182519 | D34: 44784 | E34: =SUM(C34:C35) -> 3909922
B35: 44785 | C35: 1727403 | D35: 44784
A36: 15 | B36: 44816 | C36: 2142762 | D36: 44816 | E36: =SUM(C36:C37) -> 3909923
B37: 44816 | C37: 1767161 | D37: 44816
A38: 16 | B38: 44846 | C38: 2098793 | D38: 44845 | E38: =SUM(C38:C39) -> 3909923
B39: 44846 | C39: 1811130 | D39: 44845
A40: 17 | B40: 44877 | C40: 1822527 | D40: 44876 | E40: =SUM(C40:C41) -> 3909922
B41: 44877 | C41: 2087395 | D41: 44876
A42: 18 | B42: 44907 | C42: 2098794 | D42: 44907 | E42: =SUM(C42:C43) -> 3909922
B43: 44907 | C43: 1811128 | D43: 44907
A44: 19 | B44: 44938 | C44: 1805002 | D44: 44937 | E44: =SUM(C44:C45) -> 3909922
B45: 44938 | C45: 2104920 | D45: 44937
A46: 20 | B46: 44969 | C46: 1795425 | D46: 44970 | E46: =SUM(C46:C47) -> 3909922
B47: 44969 | C47: 2114497 | D47: 44970
A48: 21 | B48: 44997 | C48: 1787183 | D48: 44998 | E48: =SUM(C48:C49) -> 3909923
B49: 44997 | C49: 2122740 | D49: 44998
A50: 22 | B50: 45028 | C50: 1800120 | D50: 45027 | E50: =SUM(C50:C51) -> 3909923
B51: 45028 | C51: 2109803 | D51: 45027
A52: 23 | B52: 45058 | C52: 1807123 | D52: 45057 | E52: =SUM(C52:C53) -> 3909923
B53: 45058 | C53: 2102800 | D53: 45057
A54: 24 | B54: 45089 | C54: 1784274 | D54: 45089 | E54: =SUM(C54:C55) -> 3877766
B55: 45089 | C55: 2093492 | D55: 45089
B56: 45089 | C56: 200000 | D56: 45096 | E56: =C56 -> 200000 | F56: Late Charges
A57: 25 | B57: 45119 | C57: 1828745 | D57: 45118 | E57: =SUM(C57:C58) -> 3909923
B58: 45119 | C58: 2081178 | D58: 45118
A59: 26 | B59: 45150 | E59: =SUM(C59:C60) -> 0
B60: 45150
A61: 27 | B61: 45181 | E61: =SUM(C61:C62) -> 0
A63: 28 | B63: 45211 | E63: =SUM(C63:C64) -> 0
A65: 29 | B65: 45242 | E65: =SUM(C65:C66) -> 0
A67: 30 | B67: 45272 | E67: =SUM(C67:C68) -> 0
A69: 31 | B69: 45303 | E69: =SUM(C69:C70) -> 0
A71: 32 | B71: 45334 | E71: =SUM(C71:C72) -> 0
A73: 33 | B73: 45363 | E73: =SUM(C73:C74) -> 0
A75: 34 | B75: 45394 | E75: =SUM(C75:C76) -> 0
A77: 35 | B77: 45424 | E77: =SUM(C77:C78) -> 0
E79: =SUM(C79:C80) -> 0
A80: 36 | B80: 45455
E81: =SUM(C81:C82) -> 0
A82: 37 | B82: 45485
E83: =SUM(C83:C84) -> 0
A84: 38 | B84: 45516
E85: =SUM(C85:C86) -> 0
A86: 39 | B86: 45547
E87: =SUM(C87:C88) -> 0
A88: 40 | B88: 45577
E89: =SUM(C89:C90) -> 0
A90: 41 | B90: 45608
E91: =SUM(C91:C92) -> 0
A92: 42 | B92: 45638
E93: =SUM(C93:C94) -> 0
A94: 43 | B94: 45669
E95: =SUM(C95:C96) -> 0
A96: 44 | B96: 45700
E97: =SUM(C97:C98) -> 0
A98: 45 | B98: 45728
E99: =SUM(C99:C100) -> 0
A100: 46 | B100: 45759
E101: =SUM(C101:C102) -> 0
A102: 47 | B102: 45789
E103: =SUM(C103:C104) -> 0
A104: 48 | B104: 45820
E105: =SUM(C105:C106) -> 0
A106: 49 | B106: 45850
E107: =SUM(C107:C108) -> 0
A108: 50 | B108: 45881
E109: =SUM(C109:C110) -> 0
A110: 51 | B110: 45912
E111: =SUM(C111:C112) -> 0
...

Sheet ASURANSI ASTRALIFE
A1: ANGSURAN ASURANSI 10THN / 120BULAN
A4: Angsuran ke | B4: Jth Tempo | C4: Nominal | D4: Paid Tgl | E4: Keterangan
A5: 1 | B5: 44302 | C5: 270000
A6: 2 | B6: 44332 | C6: 270000
A7: 3 | B7: 44363 | C7: 270000
A8: 4 | B8: 44393 | C8: 270000
A9: 5 | B9: 44424 | C9: 270000
A10: 6 | B10: 44455 | C10: 270000 | D10: 44455 | E10: Angsuran Sep 21
A11: 7 | B11: 44485 | C11: 270000 | D11: 44487 | E11: Angsurang Okt 21
A12: 8 | B12: 44516 | C12: 270000 | D12: 44516 | E12: Angsuran Nov 21
A13: 9 | B13: 44546 | C13: 270000 | D13: 44567 | E13: Angsuran Des 21 +Late Charge
A14: 10 | B14: 44577 | C14: 270000 | D14: 44578 | E14: Angsurang Jan 22
A15: 11 | B15: 44608 | C15: 270000 | D15: 44608 | E15: Angsuran Feb 22
A16: 12 | B16: 44636 | C16: 270000 | D16: 44636 | E16: Angsuran Mar 22
A17: 13 | B17: 44667 | C17: 270000 | D17: 44690 | E17: Angsuran Apr 22 + Late Charge
A18: 14 | B18: 44697 | C18: 270000 | D18: 44698 | E18: Angsuran Mei 22
A19: 15 | B19: 44728 | C19: 270000 | D19: 44728 | E19: Angsurang Jun 22
A20: 16 | B20: 44758 | C20: 270000 | D20: 44760 | E20: Angsurang Jul 22
A21: 17 | B21: 44789 | C21: 270000 | D21: 44789 | E21: Angsurang Aug 22
... A32: 28 | B32: 45123 | C32: 270000 | D32: 45124 | E32: Angsuran Jul 23 + Late Charge
A33: 29 | B33: 45154 | C33: 270000
A34: 30 | B34: 45185 | C34: 270000
A35: 31 | B35: 45215 | C35: 270000
A36: 32 | B36: 45246 | C36: 270000
A37: 33 | B37: 45276 | C37: 270000
A38: 34 | B38: 45307 | C38: 270000
A39: 35 | B39: 45338 | C39: 270000
A40: 36 | B40: 45367 | C40: 270000
A41: 37 | B41: 45398 | C41: 270000
A42: 38 | B42: 45428 | C42: 270000
A43: 39 | B43: 45459 | C43: 270000
A44: 40 | B44: 45489 | C44: 270000
... A124: 120 | B124: 47923 | C124: 270000

Sheet MSR JAN 2023 (AAE-ARL)
A1: MSR JANUARI 2023
A2: Marketing : IKA
A3: PERIODR 01-31 JANUARI 2023
A4: IMPORT
A5: NO | B5: REFF NO | C5: DESCRIPTION | D5: CUSTOMER | E5: NO. B/L | F5: ORIGIN | G5: ETA | H5: BUYING | I5: SELLING | J5: PROFIT | K5: PAYMENT DATE | L5: ACCOUNT
A7: 1 | B7: 009/IMP/I/23 | C7: CUSTOM CLEARANCE & TRUCKING 4X40HQ | D7: PT. BERCA MANDIRI PERKASA | E7: 008CX66413 | F7: KOBE | G7: 44936 | H7: 8800000 | I7: 11550000 | J7: =I7-H7 -> 2750000 | K7: 45000 | L7: ANTILLIA
A8: 2 | B8: 010/IMP/I/23 | C8: CUSTOM CLEARANCE & TRUCKING 3X40HQ | D8: PT. BERCA MANDIRI PERKASA | E8: 008CX64787 | F8: KOBE | G8: 44941 | H8: 6600000 | I8: 8750000 | J8: =I8-H8 -> 2150000 | K8: 45000 | L8: ANTILLIA
A9: 3 | B9: 17601/IMP/I/23 | C9: OF EXW, CUSTOM CLEARANCE & TRUCKING LCL | D9: PT. BERCA MANDIRI PERKASA | E9: X22-10623-JKT-005 | F9: SINGAPORE | G9: 44944 | H9: 7279790.5 | I9: 15223868 | J9: =I9-H9 -> 7944078 | K9: 45000 | L9: ATLANTIK
A10: 4 | B10: 3022/IMP/I/23 | C10: CUSTOM CLEARANCE & TRUCKING 1X40HQ | D10: PT. ARYASATYA MAKMUR LESTARI | E10: SNKO101230100179 | F10: HO CHI MINH | G10: 44940 | H10: 2750000 | I10: 3650000 | J10: =I10-H10 -> 900000 | K10: 44964 | L10: ATLANTIK
A11: 5 | B11: 00002/IMP/I/23 | C11: OF EXWORK IMPORT NEW DELHI TO JAKARTA | D11: PT. TRUELOGS GEO ENERGI | E11: 320113000037 | F11: NEW DELHI | G11: 44961 | H11: 12809512 | I11: 29145905 | J11: =I11-H11 -> 16336393 | K11: 45016 | L11: ANTILLIA
A12: 6 | B12: 012/IMP/I/23 | C12: TRUCKING ONLY | D12: PT. TRACLINEOO UTAMA INDONESIA | E12: COAU7884525680 | F12: TIANJIN | G12: 44956 | H12: 18241664 | I12: 25479164 | J12: =I12-H12 -> 7237500 | K12: 45026 | L12: ANTILLIA
F13: Total Profit Import | J13: =SUM(J7:J12) -> 37317971
A14: EXPORT
A15: NO | B15: REFF NO | C15: DESCRIPTION | D15: CUSTOMER | E15: NO. B/L | F15: DESTINASI | G15: ETA | H15: BUYING | I15: SELLING | J15: PROFIT | K15: PAYMENT DATE | L15: ACCOUNT
A17: 7 | B17: 001/CX/I/2023 | C17: CUSTOM EXPORT & TRUCKING | D17: PT. BINA NIAGA MULTIUSAHA | E17: KMTCJKT4362976 | F17: HAIPHONG - VIETNAM | G17: 44967 | H17: 2718021 | I17: 3468021 | J17: =I17-H17 -> 750000 | K17: 45022 | L17: ANTILLIA
A18: 8 | B18: 002/CX/I/2023 | C18: CUSTOM EXPORT & TRUCKING | D18: PT. BINA NIAGA MULTIUSAHA | E18: PGBG0109099472 | F18: NEW YORK | G18: 45002 | H18: 1750000 | I18: 2500000 | J18: =I18-H18 -> 750000 | K18: 45022 | L18: ANTILLIA
F19: Total Profit Export | J19: =SUM(J17:J17) -> 750000
F20: Total Export Import | J20: =J13+J19 -> 38067971
F21: Target Marketing | J21: 36000000
F23: Total Komisi 12,5% | J23: =J20*12.5/100 -> 4758496.4
F25: Total Komisi IKA | J25: =SUM(J23:J23) -> 4758496.4

Sheet MSR FEB 2023 (AAE-ARL)
A1: MSR FEBRUARI 2023
A2: Marketing : IKA
A3: PERIODR 01-28 FEBRUARI 2023
A4: IMPORT
A5: NO | B5: REFF NO | C5: DESCRIPTION | D5: CUSTOMER | E5: NO. B/L | F5: ORIGIN | G5: ETA | H5: BUYING | I5: SELLING | J5: PROFIT | L5: ACCOUNT
A7: 1 | B7: 013/IMP/II/23 | C7: IMPORT TRUCKING ONLY | D7: PT. ELANG CAKRAWALA INDONESIA - PT. MITRA ANTARA KARGO | E7: COAU8029546880 | F7: XIAOLAN | G7: 44965 | H7: 4510000 | I7: 5310000 | J7: =I7-H7 -> 800000 | L7: ANTILLIA
A8: 2 | B8: 3026/IMP/23 | C8: IMPORT CC | D8: PT. ARYASATYA MAKMUR LESTARI | E8: SGNCB23001902 | F8: HO CHI MINH | G8: 44970 | H8: 3144660 | I8: 3994660 | J8: =I8-H8 -> 850000 | L8: ATLANTIK
A9: 3 | B9: 3027/IMP/23 | C9: IMPORT CC | D9: PT. ARYASATYA MAKMUR LESTARI | E9: SGNCB23002330 | F9: HO CHI MINH | G9: 44978 | H9: 3844660 | I9: 5994660 | J9: =I9-H9 -> 2150000 | L9: ATLANTIK
A10: 4 | B10: 3029/IMP/23 | C10: IMPORT, TRUCKING & CC | D10: PT. DELISARI NUSANTARA | E10: COAU7243138400 | F10: PASIR GUDANG - MALAYSIA | G10: 44982 | H10: 2232700 | I10: 4197700 | J10: =I10-H10 -> 1965000 | L10: ATLANTIK
A11: 5 | B11: 3030/IMP/23 | C11: IMPORT CC | D11: PT. ARYASATYA MAKMUR LESTARI | E11: HASL21230201182 | F11: HO CHI MINH | G11: 44983 | H11: 2100000 | I11: 2950000 | J11: =I11-H11 -> 850000 | L11: ATLANTIK
F12: Total Profit Import | J12: =SUM(J7:J11) -> 6615000
A13: EXPORT
A14: NO | B14: REFF NO | C14: DESCRIPTION | D14: CUSTOMER | E14: NO. B/L | F14: DESTINASI | G14: ETA | H14: BUYING | I14: SELLING | J14: PROFIT
A16: - | B16: - | C16: - | D16: - | E16: - | F16: - | G16: - | H16: - | I16: - | J16: 0
F17: Total Profit Export | J17: =SUM(J16:J16) -> 0
F18: Total Export Import | J18: =J12+J17 -> 6615000
F19: Target Marketing | J19: 36000000
F20: Selisih Target | J20: =J19-J18 -> 29385000
F21: Total Komisi 12,5% | J21: =J18*12.5/100 -> 826875
F23: Total Komisi IKA | J23: =SUM(J21:J21) -> 826875

Sheet MSR MARCH 2023 (AAE-ARL)
A1: MSR MARET 2023
A2: Marketing : IKA
A3: PERIODR 01-31 MARCH 2023
A4: IMPORT
A5: NO | B5: REFF NO | C5: DESCRIPTION | D5: CUSTOMER | E5: NO. B/L | F5: ORIGIN | G5: ETA | H5: BUYING | I5: SELLING | J5: PROFIT | L5: ACCOUNT
A7: 1 | B7: 3033/IMP/23 | C7: CUSTOM & TRUCKING | D7: PT. BERCA MANDIRI PERKASA | E7: SISS23086732 | F7: SINGAPORE | G7: 44986 | H7: 1025000 | I7: 2750000 | J7: =I7-H7 -> 1725000 | L7: ATLANTIK
A8: 2 | B8: 014/IMP/III/23 | C8: CUSTOM & TRUCKING | D8: PT. BERCA MANDIRI PERKASA | E8: SISS23087487 | F8: SINGAPORE | G8: 44998 | H8: 875000 | I8: 2750000 | J8: =I8-H8 -> 1875000 | L8: ANTILLIA
A9: 3 | B9: 01/IMP/III/23 | C9: IMPORT AF BY AIR | D9: PT. PRIMAPLAST STRAW | E9: 235-49892673 | F9: ISTANBUL | G9: 44988 | H9: 13615956 | I9: 18877000 | J9: 5261044 | L9: ANTILLIA
A10: 4 | B10: 3039/IMP/23 | C10: IMPORT OF, CC & TRUCKING | D10: PT. BERCA MANDIRI PERKASA | E10: X23-01649-JKT-003 | F10: SINGAPORE | G10: 44992 | H10: 12639066 | I10: 15944465 | J10: =I10-H10 -> 3305399 | L10: ATLANTIK
A11: 5 | B11: 3034/IMP/23 | C11: CUSTOM & TRUCKING | D11: PT. ARYASATYA MAKMUR LESTARI | E11: SGNCB23003578 | F11: HO CHI MINH | G11: 44993 | H11: 5000160 | I11: 6850160 | J11: =I11-H11 -> 1850000 | L11: ATLANTIK
A12: 6 | B12: 3038/IMP/23 | C12: CUSTOM & TRUCKING | D12: PT. FECALINDO DINAMIKA INTIPRIMA | E12: PRG0166247 | F12: HAMBURG | G12: 44998 | H12: 5750000 | I12: 9325000 | J12: =I12-H12 -> 3575000 | L12: ATLANTIK
A13: 7 | B13: 3036/IMP/24 | C13: CUSTOM & TRUCKING | D13: PT. ARYASATYA MAKMUR LESTARI | E13: MUN331654JKR | F13: MUNDRA | G13: 44999 | H13: 1850000 | I13: 2900000 | J13: =I13-H13 -> 1050000 | L13: ATLANTIK
A14: 8 | B14: 017/IMP/III/23 | C14: CUSTOM & TRUCKING | D14: PT. BERCA MANDIRI PERKASA | E14: TAOJKTN20004 | F14: QINGDAO | G14: 45000 | H14: 1025000 | I14: 2750000 | J14: =I14-H14 -> 1725000 | L14: ANTILLIA
A15: 9 | B15: 018/IMP/III/23 | C15: TALANGAN INV ONLY | D15: PT. BERCA MANDIRI PERKASA | E15: 914876507 | F15: SHANGHAI | G15: 45001 | H15: 81307350 | I15: 84419500 | J15: =I15-H15 -> 3112150 | L15: ANTILLIA
A16: 10 | B16: 015/IMP/III/23 | C16: CUSTOM & TRUCKING | D16: PT. DELISARI NUSANTARA | E16: ONEYJHBD02568500 | F16: PASIR GUDANG | G16: 45009 | H16: 1750000 | I16: 3565000 | J16: =I16-H16 -> 1815000 | L16: ANTILLIA
A17: 11 | B17: 016/IMP/III/23 | C17: CUSTOM & TRUCKING | D17: PT. BERCA MANDIRI PERKASA | E17: LGZJKT2322344 | F17: GUANGZHOU | G17: 45010 | H17: 975000 | I17: 2750000 | J17: =I17-H17 -> 1775000 | L17: ANTILLIA
A18: 12 | B18: 3040/IMP/23 | C18: CUSTOM & TRUCKING | D18: PT. DELISARI NUSANTARA | E18: CMZ1055501 | F18: QINZHOU | G18: 45012 | H18: 1950000 | I18: 4815000 | J18: =I18-H18 -> 2865000 | L18: ATLANTIK
F19: Total Profit Import | J19: =SUM(J7:J18) -> 29933593
A20: EXPORT
A21: NO | B21: REFF NO | C21: DESCRIPTION | D21: CUSTOMER | E21: NO. B/L | F21: DESTINASI | G21: ETD | H21: BUYING | I21: SELLING | J21: PROFIT
A23: 13 | B23: 0021/EXP/III/23 | C23: OF, TRUCK & CUSTOM | D23: PT. POLYCHEMIE ASIA PACIFIC PERMAI | E23: MEJKT,10,009292 | F23: HOCHIMINCH | G23: 44999 | H23: 5522160 | I23: 9832500 | J23: =I23-H23 -> 4310340 | L23: ANTILLIA
A24: 14 | B24: 0022/EXP/III/23 | C24: TRUCK & EMKL SBY | D24: SH: PT. GUNTNER INDONESIA / PT. OBOR INDONESIA | E24: COSU6890767100 | F24: APAPA - SURABAYA | G24: 45008 | H24: 6500000 | I24: 12853480 | J24: =I24-H24 -> 6353480 | L24: ANTILLIA
A25: 15 | B25: 0020/EXP/III/23 | C25: OF, TRUCK & CUSTOM | D25: PT. POLYCHEMIE ASIA PACIFIC PERMAI | E25: ARL/JKT/LCL/PKG/0019/23 | F25: PORTKLANG | G25: 45008 | H25: 3538860 | I25: 7003050 | J25: =I25-H25 -> 3464190 | L25: ANTILLIA
F26: Total Profit Export | J26: =SUM(J23:J25) -> 14128010
F28: Total Export Import | J28: =J19+J26 -> 44061603
F29: Target Marketing | J29: 36000000
F31: Total Komisi 12,5% | J31: =J28*12.5/100 -> 5507700.4

Sheet MSR JAN TILL MAR
A1: MSR IKA
A2: PERIODE JANUARI S/D MARET 2023
A3: IMPORT
A4: NO | B4: REFF NO | C4: DESCRIPTION | D4: CUSTOMER | E4: NO. B/L | F4: ORIGIN | G4: ETA | H4: BUYING | I4: SELLING | J4: PROFIT | K4: PAYMENT DATE | L4: ACCOUNT
A6: JANUARI
A7: 1 | B7: 009/IMP/I/23 | C7: CUSTOM CLEARANCE & TRUCKING 4X40HQ | D7: PT. BERCA MANDIRI PERKASA | E7: 008CX66413 | F7: KOBE | G7: 44936 | H7: 8800000 | I7: 11550000 | J7: =I7-H7 -> 2750000 | K7: 45000 | L7: ANTILLIA
A8: 2 | B8: 010/IMP/I/23 | C8: CUSTOM CLEARANCE & TRUCKING 3X40HQ | D8: PT. BERCA MANDIRI PERKASA | E8: 008CX64787 | F8: KOBE | G8: 44941 | H8: 6600000 | I8: 8750000 | J8: =I8-H8 -> 2150000 | K8: 45000 | L8: ANTILLIA
A9: 3 | B9: 17601/IMP/I/23 | C9: OF EXW, CUSTOM CLEARANCE & TRUCKING LCL | D9: PT. BERCA MANDIRI PERKASA | E9: X22-10623-JKT-005 | F9: SINGAPORE | G9: 44944 | H9: 7279790.5 | I9: 15223868 | J9: =I9-H9 -> 7944078 | K9: 45000 | L9: ATLANTIK
A10: 4 | B10: 3022/IMP/I/23 | C10: CUSTOM CLEARANCE & TRUCKING 1X40HQ | D10: PT. ARYASATYA MAKMUR LESTARI | E10: SNKO101230100179 | F10: HO CHI MINH | G10: 44940 | H10: 2750000 | I10: 3650000 | J10: =I10-H10 -> 900000 | K10: 44964 | L10: ATLANTIK
A11: 5 | B11: 00002/IMP/I/23 | C11: OF EXWORK IMPORT NEW DELHI TO JAKARTA | D11: PT. TRUELOGS GEO ENERGI | E11: 320113000037 | F11: NEW DELHI | G11: 44961 | H11: 12809512 | I11: 29145905 | J11: =I11-H11 -> 16336393 | K11: 45016 | L11: ANTILLIA
A12: 6 | B12: 012/IMP/I/23 | C12: TRUCKING ONLY | D12: PT. TRACLINEOO UTAMA INDONESIA | E12: COAU7884525680 | F12: TIANJIN | G12: 44956 | H12: 18241664 | I12: 25479164 | J12: =I12-H12 -> 7237500 | K12: 45026 | L12: ANTILLIA
A13: FEBRUARI
A14: 1 | B14: 013/IMP/II/23 | C14: IMPORT TRUCKING ONLY | D14: PT. ELANG CAKRAWALA INDONESIA - PT. MITRA ANTARA KARGO | E14: COAU8029546880 | F14: XIAOLAN | G14: 44965 | H14: 4510000 | I14: 5310000 | J14: =I14-H14 -> 800000 | K14: 45000 | L14: ANTILLIA
A15: 2 | B15: 3026/IMP/23 | C15: IMPORT CC | D15: PT. ARYASATYA MAKMUR LESTARI | E15: SGNCB23001902 | F15: HO CHI MINH | G15: 44970 | H15: 3144660 | I15: 3994660 | J15: =I15-H15 -> 850000 | K15: 45000 | L15: ATLANTIK
A16: 3 | B16: 3027/IMP/23 | C16: IMPORT CC | D16: PT. ARYASATYA MAKMUR LESTARI | E16: SGNCB23002330 | F16: HO CHI MINH | G16: 44978 | H16: 3844660 | I16: 5994660 | J16: =I16-H16 -> 2150000 | K16: 45000 | L16: ATLANTIK
A17: 4 | B17: 3029/IMP/23 | C17: IMPORT, TRUCKING & CC | D17: PT. DELISARI NUSANTARA | E17: COAU7243138400 | F17: PASIR GUDANG - MALAYSIA | G17: 44982 | H17: 2232700 | I17: 4197700 | J17: =I17-H17 -> 1965000 | K17: 44964 | L17: ATLANTIK
A18: 5 | B18: 3030/IMP/23 | C18: IMPORT CC | D18: PT. ARYASATYA MAKMUR LESTARI | E18: HASL21230201182 | F18: HO CHI MINH | G18: 44983 | H18: 2100000 | I18: 2950000 | J18: =I18-H18 -> 850000 | K18: 45016 | L18: ATLANTIK
A19: MARET
A20: 1 | B20: 3033/IMP/23 | C20: CUSTOM & TRUCKING | D20: PT. BERCA MANDIRI PERKASA | E20: SISS23086732 | F20: SINGAPORE | G20: 44986 | H20: 1025000 | I20: 2750000 | J20: =I20-H20 -> 1725000 | K20: LUNAS | L20: ATLANTIK
A21: 2 | B21: 014/IMP/III/23 | C21: CUSTOM & TRUCKING | D21: PT. BERCA MANDIRI PERKASA | E21: SISS23087487 | F21: SINGAPORE | G21: 44998 | H21: 875000 | I21: 2750000 | J21: =I21-H21 -> 1875000 | K21: LUNAS | L21: ANTILLIA
A22: 3 | B22: 01/IMP/III/23 | C22: IMPORT AF BY AIR | D22: PT. PRIMAPLAST STRAW | E22: 235-49892673 | F22: ISTANBUL | G22: 44988 | H22: 13615956 | I22: 18877000 | J22: 5261044 | K22: LUNAS | L22: ANTILLIA
A23: 4 | B23: 3039/IMP/23 | C23: IMPORT OF, CC & TRUCKING | D23: PT. BERCA MANDIRI PERKASA | E23: X23-01649-JKT-003 | F23: SINGAPORE | G23: 44992 | H23: 12639066 | I23: 15944465 | J23: =I23-H23 -> 3305399 | K23: 45033 | L23: ATLANTIK
A24: 5 | B24: 3034/IMP/23 | C24: CUSTOM & TRUCKING | D24: PT. ARYASATYA MAKMUR LESTARI | E24: SGNCB23003578 | F24: HO CHI MINH | G24: 44993 | H24: 5000160 | I24: 6850160 | J24: =I24-H24 -> 1850000 | K24: LUNAS | L24: ATLANTIK
A25: 6 | B25: 3038/IMP/23 | C25: CUSTOM & TRUCKING | D25: PT. FECALINDO DINAMIKA INTIPRIMA | E25: PRG0166247 | F25: HAMBURG | G25: 44998 | H25: 5750000 | I25: 9325000 | J25: =I25-H25 -> 3575000 | K25: 45019 | L25: ATLANTIK
A26: 7 | B26: 3036/IMP/24 | C26: CUSTOM & TRUCKING | D26: PT. ARYASATYA MAKMUR LESTARI | E26: MUN331654JKR | F26: MUNDRA | G26: 44999 | H26: 1850000 | I26: 2900000 | J26: =I26-H26 -> 1050000 | K26: LUNAS | L26: ATLANTIK
A27: 8 | B27: 017/IMP/III/23 | C27: CUSTOM & TRUCKING | D27: PT. BERCA MANDIRI PERKASA | E27: TAOJKTN20004 | F27: QINGDAO | G27: 45000 | H27: 1025000 | I27: 2750000 | J27: =I27-H27 -> 1725000 | K27: LUNAS | L27: ANTILLIA
A28: 9 | B28: 018/IMP/III/23 | C28: TALANGAN INV ONLY | D28: PT. BERCA MANDIRI PERKASA | E28: 914876507 | F28: SHANGHAI | G28: 45001 | H28: 81307350 | I28: 84419500 | J28: =I28-H28 -> 3112150 | K28: 45026 | L28: ANTILLIA
A29: 10 | B29: 015/IMP/III/23 | C29: CUSTOM & TRUCKING | D29: PT. DELISARI NUSANTARA | E29: ONEYJHBD02568500 | F29: PASIR GUDANG | G29: 45009 | H29: 1750000 | I29: 3565000 | J29: =I29-H29 -> 1815000 | K29: 45034 | L29: ANTILLIA
A30: 11 | B30: 016/IMP/III/23 | C30: CUSTOM & TRUCKING | D30: PT. BERCA MANDIRI PERKASA | E30: LGZJKT2322344 | F30: GUANGZHOU | G30: 45010 | H30: 975000 | I30: 2750000 | J30: =I30-H30 -> 1775000 | K30: 45016 | L30: ANTILLIA
A31: 12 | B31: 3040/IMP/23 | C31: CUSTOM & TRUCKING | D31: PT. DELISARI NUSANTARA | E31: CMZ1055501 | F31: QINZHOU | G31: 45012 | H31: 1950000 | I31: 4815000 | J31: =I31-H31 -> 2865000 | K31: 45042 | L31: ATLANTIK
F32: Total Profit Import | J32: =SUM(J7:J31) -> 73866564
A33: EXPORT
A34: NO | B34: REFF NO | C34: DESCRIPTION | D34: CUSTOMER | E34: NO. B/L | F34: DESTINASI | G34: ETA | H34: BUYING | I34: SELLING | J34: PROFIT | K34: PAYMENT DATE | L34: ACCOUNT
A36: JANUARI
A37: 1 | B37: 001/CX/I/2023 | C37: CUSTOM EXPORT & TRUCKING | D37: PT. BINA NIAGA MULTIUSAHA | E37: KMTCJKT4362976 | F37: HAIPHONG - VIETNAM | G37: 44967 | H37: 2718021 | I37: 3468021 | J37: =I37-H37 -> 750000 | K37: 45022 | L37: ANTILLIA
A38: 2 | B38: 002/CX/I/2023 | C38: CUSTOM EXPORT & TRUCKING | D38: PT. BINA NIAGA MULTIUSAHA | E38: PGBG0109099472 | F38: NEW YORK | G38: 45002 | H38: 1750000 | I38: 2500000 | J38: =I38-H38 -> 750000 | K38: 45022 | L38: ANTILLIA
A39: FEBRUARI
A40: MARET
B41: 0021/EXP/III/23 | C41: OF, TRUCK & CUSTOM | D41: PT. POLYCHEMIE ASIA PACIFIC PERMAI | E41: MEJKT,10,009292 | F41: HOCHIMINCH | G41: 44999 | H41: 5522160 | I41: 9832500 | J41: =I41-H41 -> 4310340 | K41: 45022 | L41: ANTILLIA
A42: 2 | B42: 0022/EXP/III/23 | C42: TRUCK & EMKL SBY | D42: SH: PT. GUNTNER INDONESIA / PT. OBOR INDONESIA | E42: COSU6890767100 | F42: APAPA - SURABAYA | G42: 45008 | H42: 6500000 | I42: 12853480 | J42: =I42-H42 -> 6353480 | K42: 45022 | L42: ANTILLIA
A43: 3 | B43: 0020/EXP/III/23 | C43: OF, TRUCK & CUSTOM | D43: PT. POLYCHEMIE ASIA PACIFIC PERMAI | E43: ARL/JKT/LCL/PKG/0019/23 | F43: PORTKLANG | G43: 45008 | H43: 3538860 | I43: 7003050 | J43: =I43-H43 -> 3464190 | K43: 45022 | L43: ANTILLIA
F44: Total Profit Import | J44: =J37+J38+J41+J42+J43 -> 15628010
F45: Total Export Import | J45: =SUM(J20:J44) -> 135056177
J46: =J45*12.5/100 -> 16882022

Sheet MSR APRIL 2023
A1: MSR APRIL2023
A2: Marketing : IKA
A3: PERIODE 1-30 APRIL 2023
A4: IMPORT
A5: NO | B5: REFF NO | C5: DESCRIPTION | D5: CUSTOMER | E5: NO. B/L | F5: ORIGIN | G5: ETA | H5: BUYING | I5: SELLING | J5: PROFIT | L5: ACCOUNT
A7: 1 | B7: 00005/IMP/III/23 | C7: IMPORT - OF & CC | D7: PT. BERCA MANDIRI PERKASA | E7: AWSJKT124632 / YMLUI450448655 | F7: SINGAPORE | G7: 45017 | H7: 27833324 | I7: 34353310 | J7: =I7-H7 -> 6519986 | L7: ANTILLIA
A8: 2 | B8: 00003/IMP/III/23 | C8: IMPORT, OF & CC | D8: PT. POLYCHEMIE ASIA PACIFIC PERMAI | E8: S00215842 / COAU8036158210 | F8: SHANGHAI | G8: 45019 | H8: 6307300 | I8: 10225000 | J8: =I8-H8 -> 3917700 | L8: ANTILLIA
A9: 3 | B9: 019/IMP/III/23 | C9: JUST INVOICE | D9: PT. BERCA MANDIRI PERKASA | E9: YMLUI236297936 | F9: SHANGHAI | G9: 45019 | H9: 114836000 | I9: 121763010 | J9: =I9-H9 -> 6927010 | L9: ANTILLIA
A10: 4 | B10: 02/IMP/IV/2023 | C10: IMPORT CC | D10: PT. NATA KIMINDO PRATAMA | E10: 784-38399561 | F10: SHENZEN | G10: 45023 | H10: 140000 | I10: 1400500 | J10: =I10-H10 -> 1260500 | L10: ANTILLIA
A11: 5 | B11: 01/IMP/IV/23 | C11: IMPORT, OF & CC | D11: PT. POLYCHEMIE ASIA PACIFIC PERMAI | E11: WS230400017 / 695-41501456 | F11: XIAMEN | G11: 45025 | H11: 194838000 | I11: 265247000 | J11: =I11-H11 -> 70409000 | L11: ANTILLIA
A12: 6 | B12: 020/IMP/IV/23 | C12: IMPORT CC | D12: PT. ARYASATYA MAKMUR LESTARI | E12: SGNCB23006190 | F12: HOCHIMINCH | G12: 45026 | H12: 1750000 | I12: 2800000 | J12: =I12-H12 -> 1050000 | L12: ANTILLIA
A13: 7 | B13: 021/IMP/IV/23 | C13: IMPORT, TRUCKING & CC | D13: PT. DELISARI NUSANTARA | E13: ONEYJHBD03736300 | F13: PASIR GUDANG | G13: 45026 | H13: 1650000 | I13: 3565000 | J13: =I13-H13 -> 1915000 | L13: ANTILLIA
A14: 8 | B14: 00004/IMP/III/23 | C14: IMPORT, TRUCKING & CC | D14: PT. BERINGIN MITRA GUNA | E14: S00216264 / OOLU2715967310 | F14: SHANTOU | G14: 45028 | H14: 4500000 | I14: 13876250 | J14: =I14-H14 -> 9376250 | L14: ANTILLIA
A15: 9 | B15: 0022/IMP/IV/23 | C15: IMPORT, TRUCKING & CC | D15: PT. CITRA JAYA HOSINDO | E15: WFLQDCJKT23032237 | F15: QINGDAO | G15: 45029 | H15: 5192788 | I15: 6567788 | J15: =I15-H15 -> 1375000 | L15: ANTILLIA
A16: 10 | B16: 024/IMP/IV/23 | C16: IMPORT | D16: PT. BERCA MANDIRI PERKASA | E16: CEM0101191 | F16: DALIAN - CHINA | G16: 45029 | H16: 27800000 | I16: 37700000 | J16: =I16-H16 -> 9900000 | L16: ANTILLIA
A17: 11 | B17: 023/IMP/IV/23 | C17: INVOICE ALISPED & CUSTOM | D17: PT. BERCA MANDIRI PERKASA | E17: 226222927 | F17: SHANGHAI | G17: 45029 | H17: 23400000 | I17: 28075900 | J17: =I17-H17 -> 4675900 | L17: ANTILLIA
A18: 12 | B18: 025/IMP/IV/23 | C18: IMPORT, CC & TRUCK | D18: PT. BERCA MANDIRI PERKASA | E18: COAU8034361490 | F18: DALIAN - CHINA | G18: 45036 | H18: 5800000 | I18: 8650000 | J18: =I18-H18 -> 2850000 | L18: ANTILLIA
A19: 13 | B19: 026/IMP/IV /23 | C19: IMPORT, CC & TRUCK | D19: PT. BERCA MANDIRI PERKASA | E19: COAU7243633300 | F19: DALIAN - CHINA | G19: 45036 | H19: 11600000 | I19: 16900000 | J19: =I19-H19 -> 5300000 | L19: ANTILLIA
A20: 14 | B20: 032/IMP/IV/23 | C20: IMPORT CC | D20: PT. ARYASATYA MAKMUR LESTARI | E20: 144DX03316 | F20: CHENNAI - INDIA | G20: 45044 | H20: 4500000 | I20: 6450000 | J20: =I20-H20 -> 1950000 | L20: ANTILLIA
A21: 15 | B21: 029/IMP/IV/23 | C21: INVOICE ALISPED & CUSTOM | D21: PT. BERCA MANDIRI PERKASA | E21: 226376719 | F21: SHANGHAI | G21: 45044 | H21: 59750000 | I21: 66381500 | J21: =I21-H21 -> 6631500 | L21: ANTILLIA
A22: 16 | B22: 028/IMP/IV/23 | C22: INVOICE ALISPED & CUSTOM | D22: PT. BERCA MANDIRI PERKASA | E22: 226373665 | F22: SHANGHAI | G22: 45044 | H22: 47800000 | I22: 56785200 | J22: =I22-H22 -> 8985200 | L22: ANTILLIA
A23: 17 | B23: 030/IMP/IV/23 | C23: INVOICE ALISPED & CUSTOM | D23: PT. BERCA MANDIRI PERKASA | E23: 226373780 | F23: SHANGHAI | G23: 45044 | H23: 35950000 | I23: 39988900 | J23: =I23-H23 -> 4038900 | L23: ANTILLIA
A24: 18 | B24: 031/IMP/IV/23 | C24: INVOICE ALISPED & CUSTOM | D24: PT. BERCA MANDIRI PERKASA | E24: 226373746 | F24: SHANGHAI | G24: 45044 | H24: 119500000 | I24: 132363000 | J24: =I24-H24 -> 12863000 | L24: ANTILLIA
F25: Total Profit Import | J25: =SUM(J7:K24) -> 159944946
A26: EXPORT
A27: NO | B27: REFF NO | C27: DESCRIPTION | D27: CUSTOMER | E27: NO. B/L | F27: DESTINASI | G27: ETD | H27: BUYING | I27: SELLING | J27: PROFIT
A29: 19 | B29: 003/CX/23 | C29: TRUCKING ONLY | D29: PT. Belva Transtama Abadi / Sh: PT. Diza Aishwarya Global | E29: ARM0293828 | F29: LIANHUSHAN-CHINA | G29: 45029 | H29: 1600000 | I29: 2100000 | J29: =I29-H29 -> 500000 | L29: ANTILLIA
F30: Total Profit Export | J30: =SUM(J29) -> 500000
A31: LOKAL / DOMESTIK
A32: NO | B32: REFF NO | C32: DESCRIPTION | D32: CUSTOMER | E32: NO. B/L | F32: DESTINASI | G32: ETD | H32: BUYING | I32: SELLING | J32: PROFIT
A34: 20 | B34: 003/OTH/23 | C34: LOKAL TRUCK ONLY | D34: PT. CITRA NIAGA LOGISTIK / RADHIKA CARGO SERVICE | E34: BJKTC23012281 | F34: JKT-MAKASSAR | G34: - | H34: 3600000 | I34: 4300000 | J34: =I34-H34 -> 700000 | L34: ANTILLIA
A35: 21 | B35: 0001/DOM/IV/23 | C35: DOMESTIK | D35: PT. BERCA MANDIRI PERKASA | E35: SPK NO 048/SKPB-MSD-HE/IV/2023 | F35: JKT-BANJARMASIN | G35: 45029 | H35: 64200000 | I35: 81000000 | J35: =I35-H35 -> 16800000 | L35: ANTILLIA
F36: Total Profit Domestik | J36: =SUM(J34:J35) -> 17500000
F38: Total Export Import & Domestik | J38: =J25+J30+J36 -> 177944946
F39: Target Marketing | J39: 36000000
F40: Deduct Berca | J40: 5000000
J41: =J38-J40 -> 172944946
F43: Total Komisi 12,5% | J43: =J38*12.5/100 -> 22243118
J44: =J41*12.5/100 -> 21618118 | L44: lunas 27/07/2023

Sheet MSR MEI 2023
A1: MSR MAY 2023
A2: Marketing : IKA
A3: PERIODE 1-31 MAY 2023
A4: IMPORT
A5: NO | B5: REFF NO | C5: DESCRIPTION | D5: CUSTOMER | E5: NO. B/L | F5: ORIGIN | G5: ETA | H5: PAYMENT DATE | I5: BUYING | J5: SELLING | K5: PROFIT
A7: 1 | B7: 033/IMP/IV/23 | C7: IMPORT, CC & TRUCK | D7: PT. ARYASATYA MAKMUR LESTARI | E7: KMTCSGN4661962 | F7: HOCHIMINCH | G7: 45048 | H7: 45128 | I7: 2710450 | J7: 3560450 | K7: =J7-I7 -> 850000
A8: 2 | B8: 034/IMP/IV/23 | C8: IMPORT INV, CC & TRUCK | D8: PT. BERCA MANDIRI PERKASA | E8: 914906633 | F8: SHANGHAI | G8: 45050 | H8: 31/05/2023 OF & 17/07/2023 CC | I8: 58150000 | J8: 64510000 | K8: =J8-I8 -> 6360000
A9: 3 | B9: 011/IMP/IV/23 | C9: IMPORT, OF & CUSTOM | D9: PT. BERCA MANDIRI PERKASA | E9: WS23040084/CMZ1081293 | F9: SHEKOU | G9: 45053 | H9: 45140 | I9: 34535000 | J9: 51300830 | K9: =J9-I9 -> 16765830
A10: 4 | B10: 001/IMP/V/23 | C10: IMPORT CC | D10: PT. BERCA MANDIRI PERKASA | E10: GTD0776598 | F10: LAEM CHABANG - THAILAND | G10: 45054 | H10: 45134 | I10: 4200000 | J10: 6200000 | K10: =J10-I10 -> 2000000
A11: 5 | B11: 035/IMP/IV/23 | C11: IMPORT INV, CC & TRUCK | D11: PT. BERCA MANDIRI PERKASA | E11: 226906048 | F11: SHANGHAI | G11: 45057 | H11: 31/05/2023 OF & 17/07/2023 CC | I11: 34950000 | J11: 39988900 | K11: =J11-I11 -> 5038900
A12: 6 | B12: 027/IMP/IV/23 | C12: IMPORT, TRUCKING & CC | D12: PT. DELISARI NUSANTARA | E12: OOLU2139437570 | F12: ANTWERPEN | G12: 45060 | H12: 45113 | I12: 4050000 | J12: 6190000 | K12: =J12-I12 -> 2140000
A13: 7 | B13: 002/IMP/V/23 | C13: IMPORT, CC & TRUCK | D13: PT. ARYASATYA MAKMUR LESTARI | E13: CNICB23006450001 | F13: CHENAI | G13: 45061 | H13: 45128 | I13: 1950000 | J13: 3200000 | K13: =J13-I13 -> 1250000
A14: 8 | B14: 006/IMP/V/23 | C14: IMPORT CUSTOM AND TRUCK | D14: PT. CITRA PERDANA PUTRA | E14: TSNA59929200 | F14: XINGGANG | G14: 45064 | H14: 45162 | I14: 3350000 | J14: 4150000 | K14: =J14-I14 -> 800000
A15: 9 | B15: 036/IMP/IV/23 | C15: IMPORT, TRUCKING & CC | D15: PT. DELISARI NUSANTARA | E15: DELJAK210530 | F15: ICD TKD NEW DELHI | G15: 45066 | H15: 45128 | I15: 975000 | J15: 3825000 | K15: =J15-I15 -> 2850000
A16: 10 | B16: 008/IMP/V/23 | C16: IMPORT, CC & TRUCK | D16: PT. ARYASATYA MAKMUR LESTARI | E16: HASLS21230500344 | F16: HOCHIMINCH | G16: 45067 | H16: 45128 | I16: 1750000 | J16: 2800000 | K16: =J16-I16 -> 1050000
A17: 11 | B17: 010/IMP/V/23 | C17: IMPORT INV, CC & TRUCK | D17: PT. BERCA MANDIRI PERKASA | E17: SNKO190230403352 | F17: LAEM CHABANG - THAILAND | G17: 45069 | H17: 45145 | I17: 8900000 | J17: 17800000 | K17: =J17-I17 -> 8900000
A18: 12 | B18: 003/IMP/V/23 | C18: IMPORT INV, CC & TRUCK | D18: PT. BERCA MANDIRI PERKASA | E18: 227090974 | F18: SHANGHAI | G18: 45071 | H18: 45145 | I18: 88400000 | J18: 102399840 | K18: =J18-I18 -> 13999840
A19: 13 | B19: 009/IMP/V/23 | C19: IMPORT, CC & TRUCK | D19: PT. ARYASATYA MAKMUR LESTARI | E19: CNICB2300694402 | F19: CHENAI | G19: 45074 | H19: 45129 | I19: 1700000 | J19: 2800000 | K19: =J19-I19 -> 1100000
A20: 14 | B20: 012/IMP/V/23 | C20: IMPORT INV, CC & TRUCK | D20: PT. BERCA MANDIRI PERKASA | E20: GTD0782596 | F20: LAEM CHABANG - THAILAND | G20: 45075 | H20: 45145 | I20: 8100000 | J20: 11600000 | K20: =J20-I20 -> 3500000
A21: 15 | B21: 03/IMP/V/23 | C21: IMPORT CC | D21: PT. NATA KIMINDO PRATAMA | E21: 205-20968356 | F21: SHANGHAI | G21: 45076 | H21: 19/07/2023 | I21: 260000 | J21: 1371000 | K21: =J21-I21 -> 1111000
A22: 16 | B22: 005/IMP/V/23 | C22: IMPORT JASA EDIT & STAMP ONLY | D22: PT. SINERGI MANDIRI SELARAS | E22: H700204875 / GEN102157 | F22: GENOA | G22: - | H22: 45072 | I22: 180000 | J22: 1050000 | K22: =J22-I22 -> 870000
A23: 17 | B23: 004/IMP/V/23 | C23: IMPORT JASA EDIT & STAMP ONLY | D23: PT. SINERGI MANDIRI SELARAS | E23: MX/19/802568 / ONEYGOAV38152500 | F23: GENOVA | G23: - | H23: 45072 | I23: 180000 | J23: 1050000 | K23: =J23-I23 -> 870000
A24: 18 | B24: 006/IMP/23 | C24: TRUCK ONLY NON PPN | D24: PT. KARUNIA MAS SEWATAMA / TUNAS SUMBER | E24: 226484187 | F24: SHANGHAI | G24: - | H24: 45065 | I24: 1700000 | J24: 1900000 | K24: =J24-I24 -> 200000
F25: Total Profit Import | K25: =SUM(K7:K24) -> 69655570
A26: EXPORT
A27: NO | B27: REFF NO | C27: DESCRIPTION | D27: CUSTOMER | E27: NO. B/L | F27: DESTINASI | G27: ETD | H27: PAYMENT DATE | I27: BUYING | J27: SELLING | K27: PROFIT
A29: 19 | B29: 002A/EXP/V/23 | C29: EXPORT, COO ONLY | D29: SH: PT. TUNAS SUMBER IDEAKREASI KIMIA FW: TRACLINEOO | E29: SHJK230028PK | F29: PORT KELANG NORTH | G29: 45047 | H29: 14/06/2023 | I29: 200000 | J29: 550000 | K29: =J29-I29 -> 350000
A30: 20 | B30: 006/OTH/23 | C30: EXPORT CUSTOM | D30: PT. OBOR INDONESIA PRATAMA | E30: 049DX03763 | F30: XIAMEN | G30: 45060 | H30: 45163 | I30: 2000000 | J30: 5500000 | K30: =J30-I30 -> 3500000
A31: 21 | B31: 009/OTH/23 | C31: EXPORT CUSTOM | D31: PT. OBOR INDONESIA PRATAMA | E31: 049DX03975 | F31: SHANGHAI | G31: 45067 | H31: 45163 | I31: 900000 | J31: 3100000 | K31: =J31-I31 -> 2200000
A32: 22 | B32: 008/OTH/23 | C32: EXPORT CUSTOM | D32: PT. OBOR INDONESIA PRATAMA | E32: 049DX03974 | F32: XIAMEN | G32: 45067 | H32: 45163 | I32: 1550000 | J32: 4600000 | K32: =J32-I32 -> 3050000
A33: 23 | B33: 010/OTH/23 | C33: EXPORT CUSTOM & TRUCK | D33: PT. BINA NIAGA MULTIUSAHA | E33: OERT110702M00610 | F33: NEW YORK | G33: 45074 | H33: 45145 | I33: 1650000 | J33: 2600000 | K33: =J33-I33 -> 950000
F34: Total Profit Export | K34: =SUM(K29:K33) -> 10050000
A35: LOKAL / DOMESTIK
A36: NO | B36: REFF NO | C36: DESCRIPTION | D36: CUSTOMER | E36: NO. B/L | F36: DESTINASI | G36: ETD | H36: PAYMENT DATE | I36: BUYING | J36: SELLING | K36: PROFIT
A38: 24 | B38: 002/DOM/IV/23 | C38: DOMESTIK | D38: PT. BERCA MANDIRI PERKASA | E38: SPK NO 052/SKPB-MSD-HE/IV/2023 | F38: JKT-BALI | G38: 45048 | H38: 45090 | I38: 12000000 | J38: 16000000 | K38: =J38-I38 -> 4000000
A39: 25 | B39: 00003/DOM/V/23 | C39: DOMESTIK | D39: PT. BERCA MANDIRI PERKASA | E39: SPK NO 110/SKPB-MSD-MH/V/2023 | F39: JATAKE-JAMBI | G39: 45072 | H39: 45090 | I39: 12000000 | J39: 14000000 | K39: =J39-I39 -> 2000000
A40: 26 | B40: 005/OTH/23 | C40: DOMESTIK | D40: PT. OBOR INDONESIA PRATAMA | E40: BIT1023042000001 | F40: BITUNG-JKT | G40: 45035 | H40: 45163 | I40: 2850000 | J40: 4950000 | K40: =J40-I40 -> 2100000
A41: 27 | B41: 007/OTH/23 | C41: DOMESTIK | D41: PT. OBOR INDONESIA PRATAMA | E41: BIT1023050600005 | F41: BITUNG-JKT | G41: 45052 | H41: 45163 | I41: 2800000 | J41: 4950000 | K41: =J41-I41 -> 2150000
F42: Total Profit Domestik | K42: =SUM(K38:K41) -> 10250000
F44: Sisa Potongan Berca | K44: 5000000
F45: Total Export Import & Domestik | K45: =K25+K34+K42 -> 89955570
F46: Total Keseluruhan | K46: =K45-K44 -> 84955570
F48: Total Komisi 12,5% | K48: =K46*12.5/100 -> 10619446 | L48: 45187 | M48: Lunas

Sheet MSR JUNI 2023
A1: MSR JUNI 2023
A2: Marketing : IKA
A3: PERIODE 01-30 JUNI 2023
A4: IMPORT
A5: NO | B5: REFF NO | C5: DESCRIPTION | D5: CUSTOMER | E5: NO. B/L | F5: ORIGIN | G5: ETA | H5: PAYMENT DATE | I5: BUYING | J5: SELLING | K5: PROFIT
A7: 1 | B7: 037/IMP/IV/23 | C7: IMPORT OF ONLY | D7: PT. AGRAPRANA EKSPRESS | E7: 33044547 | F7: ROTTERDAM | G7: 45080 | H7: 45083 | I7: 4131087 | J7: 8587462 | K7: =J7-I7 -> 4456375
A8: 2 | B8: 011/IMP/V/23 | C8: IMPORT CC | D8: PT. CITRA PERDANA PUTRA | E8: COAU8038084470 | F8: DALIAN | G8: 45078 | H8: 45162 | I8: 3250000 | J8: 4150000 | K8: =J8-I8 -> 900000
A9: 3 | B9: 007/IMP/V/23 | C9: IMPORT CC | D9: PT. FECALINDO DINAMIKA INTIPRIMA | E9: 52302489 | F9: HAMBURG | G9: 45080 | H9: 45103 | I9: 2500000 | J9: 4675000 | K9: =J9-I9 -> 2175000
A10: 4 | B10: 013/IMP/V/23 | C10: IMPORT CC | D10: PT. CITRA PERDANA PUTRA | E10: 292084067 | F10: XINGANG | G10: 45084 | H10: 45162 | I10: 1700000 | J10: 2275000 | K10: =J10-I10 -> 575000
A11: 5 | B11: 014/IMP/V/23 | C11: IMPORT INV ONLY | D11: PT. BERCA MANDIRI PERKASA | E11: SITGSHSRQ116404 | F11: SHANGHAI | G11: 45088 | H11: 45021 | I11: 85900000 | J11: 89814000 | K11: =J11-I11 -> 3914000
A12: 6 | B12: 002/IMP/VI/23 | C12: IMPORT, CC & TRUCK | D12: PT. ARYASATYA MAKMUR LESTARI | E12: EGLV235300605401 | F12: HO CHI MINH | G12: 45089 | I12: 2050000 | J12: 2900000 | K12: =J12-I12 -> 850000
A13: 7 | B13: 015/IMP/V/23 | C13: IMPORT CC | D13: PT. OBOR INDONESIA PRATAMA | E13: JJCSHSYA337408 | F13: SHANGHAI | G13: 45090 | I13: 9307129 | J13: 11598129 | K13: =J13-I13 -> 2291000
A14: 8 | B14: 004/IMP/VI/23 | C14: IMPORT CC | D14: PT. CITRA PERDANA PUTRA | E14: COAU8038243870 | F14: DALIAN | G14: 45092 | I14: 5150000 | J14: 6225000 | K14: =J14-I14 -> 1075000
A15: 9 | B15: 001/IMP/VI/23 | C15: IMPORT CC | D15: PT. BERCA MANDIRI PERKASA | E15: AXI0240929 | F15: XIAMEN | G15: 45093 | H15: 03/07/2023 OF & 17/07/2023 CC | I15: 41800000 | J15: 47863200 | K15: =J15-I15 -> 6063200
A16: 10 | B16: 007/IMP/V/23 | C16: IMPORT CC | D16: PT. OBOR INDONESIA PRATAMA | E16: 228113399 | F16: XIAMEN/JKT | G16: 45097 | I16: 2050000 | J16: 5300000 | K16: =J16-I16 -> 3250000
A17: 11 | B17: 006/IMP/VI/23 | C17: IMPORT CC | D17: PT. OBOR INDONESIA PRATAMA | E17: 227916291 | F17: SHANGHAI | G17: 45097 | I17: 845000 | J17: 4095000 | K17: =J17-I17 -> 3250000
A18: 12 | B18: 003/IMP/VI/23 | C18: IMPORT CC | D18: PT. BERCA MANDIRI PERKASA | E18: 227760389 | F18: SHANGHAI | G18: 45099 | H18: 02/08/2023 & 22/08/2023 | I18: 30900000 | J18: 36089000 | K18: =J18-I18 -> 5189000
A19: 13 | B19: 005/IMP/VI/23 | C19: IMPORT, TRUCKING & CC | D19: PT. DELISARI NUSANTARA | E19: OOLU8894095020 | F19: QINZHOU | G19: 45105 | H19: 45148 | I19: 1900000 | J19: 4515000 | K19: =J19-I19 -> 2615000
F20: Total Profit Import | K20: =SUM(K7:K19) -> 36603575
A21: EXPORT
A22: NO | B22: REFF NO | C22: DESCRIPTION | D22: CUSTOMER | E22: NO. B/L | F22: DESTINASI | G22: ETD | H22: PAYMENT DATE | I22: BUYING | J22: SELLING | K22: PROFIT
A24: 14 | B24: 011/OTH/23 | C24: EXPORT CC | D24: PT. BINA NIAGA MULTIUSAHA | E24: JKT300310800 | F24: LAEMCHABANG | G24: 45089 | H24: 45175 | I24: 3400000 | J24: 4650000 | K24: =J24-I24 -> 1250000
A25: 15 | B25: 013/OTH/23 | C25: EXPORT CUSTOM | D25: PT. OBOR INDONESIA PRATAMA | E25: 049DX04730 | F25: XIAMEN | G25: 45091 | H25: 45163 | I25: 1500000 | J25: 3100000 | K25: =J25-I25 -> 1600000
A26: 16 | B26: 014/OTH/23 | C26: EXPORT CUSTOM | D26: PT. OBOR INDONESIA PRATAMA | E26: 049DX04731 | F26: XIAMEN | G26: 45091 | H26: 45163 | I26: 1500000 | J26: 3100000 | K26: =J26-I26 -> 1600000
F27: Total Profit Export | K27: =SUM(K24:K26) -> 4450000
A28: LOKAL / DOMESTIK
A29: NO | B29: REFF NO | C29: DESCRIPTION | D29: CUSTOMER | E29: NO. B/L | F29: DESTINASI | G29: ETD | H29: PAYMENT DATE | I29: BUYING | J29: SELLING | K29: PROFIT
A31: 17 | B31: 004/DOM/VI/23 | C31: DOMESTIK | D31: PT. RAMADYA CAKRA SEMESTA | E31: 0106/SKPB-ARL/VI/DOM/2023 | F31: CIKARANG - KENDARI | G31: 06/06/2023 JKT 15/06/2023 SUB | H31: 45135 | I31: 20000000 | J31: 22500000 | K31: =J31-I31 -> 2500000
A32: 18 | B32: 012/OTH/23 | C32: DOMESTIK | D32: PT. OBOR INDONESIA PRATAMA | E32: BIT1023060300002 | F32: BITUNG-JKT | G32: 45079 | I32: 4200000 | J32: 7350000 | K32: =J32-I32 -> 3150000
F33: Total Profit Domestik | K33: =SUM(K31:K32) -> 5650000
F35: Total Export Import & Domestik | K35: =K20+K27+K33 -> 46703575
F36: Target Marketing | K36: 36000000
F38: Total Komisi 12,5% | K38: =K35*12.5/100 -> 5837946.9

Sheet MSR JULI 2023
A1: MSR JULY 2023
A2: Marketing : IKA
A3: PERIODE JULI 01-31 JULY 2023
A4: IMPORT
A5: NO | B5: REFF NO | C5: DESCRIPTION | D5: CUSTOMER | E5: NO. B/L | F5: ORIGIN | G5: ETA | H5: PAYMENT DATE | I5: BUYING | J5: SELLING | K5: PROFIT
A7: 1 | B7: 008/IMP/VI/23 | C7: IMPORT CC | D7: PT. CITRA PERDANA PUTRA | E7: COAU8038801920 | F7: DALIAN | G7: 45108 | H7: 24/08/2023 -REIMBURS BLM DI BYAR | I7: 5150000 | J7: 6025000 | K7: =J7-I7 -> 875000
A8: 2 | B8: 011/IMP/VI/23 | C8: IMPORT CC | D8: PT. CITRA PERDANA PUTRA | E8: KMTCTAO6894383 | F8: QINGDAO | G8: 45109 | H8: 45162 | I8: 1650000 | J8: 2275000 | K8: =J8-I8 -> 625000
A9: 3 | B9: 009/IMP/VI/23 | C9: IMPORT OF ONLY | D9: PT. BERCA MANDIRI PERKASA | E9: SITGSHJTQ118116 | F9: SHANGHAI | G9: - | H9: 17/07/2023 | I9: 187125000 | J9: 194224100 | K9: =J9-I9 -> 7099100
A10: 4 | B10: 010/IMP/VI/23 | C10: IMPORT CC & OF | D10: PT. BERCA MANDIRI PERKASA | E10: SITGSHJTQ118120 | F10: SHANGHAI | G10: 45111 | H10: 27/07/2023 OF - 11/09/2023 CC | I10: 50750000 | J10: 58095600 | K10: =J10-I10 -> 7345600
A11: 5 | B11: 008/IMP/VII/23 | C11: IMPORT - OF & CC | D11: PT. BERCA MANDIRI PERKASA | E11: WS230700039 / CPL0113847 | F11: SHANGHAI | G11: 45138 | H11: 04/09/2023 OF | I11: 71020000 | J11: 89015480 | K11: =J11-I11 -> 17995480
A12: 6 | B12: 003/IMP/VII/23 | C12: IMPORT CC & OF | D12: PT. BERCA MANDIRI PERKASA | E12: WS230700008 / MEDUQC689674 | F12: QINGDAO | G12: 45137 | H12: 14/08/2023 OF | I12: 9450000 | J12: 12154560 | K12: =J12-I12 -> 2704560
A13: 7 | B13: 007/IMP/VII/23 | C13: IMPORT CC & OF | D13: PT. BERCA MANDIRI PERKASA | E13: WS230700028 / 025D642007 | F13: SHANGHAI | G13: 45129 | H13: 04/09/2023 OF | I13: 59000000 | J13: 93404800 | K13: =J13-I13 -> 34404800
A14: 8 | B14: 012/IMP/VI/23 | C14: IMPORT, CC & TRUCK | D14: PT. ARYASATYA MAKMUR LESTARI | E14: HCS344717JKR | F14: HO CHI MINH | G14: 45089 | H14: 45163 | I14: 1800000 | J14: 2900000 | K14: =J14-I14 -> 1100000
A15: 9 | B15: 013/IMP/VI/23 | C15: IMPORT CC & TRUCK | D15: PT. CITRA PERDANA PUTRA | E15: 2703040501 | F15: XINGANG | G15: 45117 | H15: 45198 | I15: 3630000 | J15: 4505000 | K15: =J15-I15 -> 875000
A16: 10 | B16: 001/IMP/VII/23 | C16: IMPORT CC & TRUCK | D16: PT. CITRA PERDANA PUTRA | E16: NSA-JKTG119834 | F16: NANSHA | G16: 45124 | H16: 45196 | I16: 3150000 | J16: 4700000 | K16: =J16-I16 -> 1550000
A17: 11 | B17: 003/IMP/VII/23 | C17: IMPORT CC & TRUCK | D17: PT. CITRA PERDANA PUTRA | E17: COAU8039648240 | F17: DALIAN | G17: 45137 | H17: 45209 | I17: 3250000 | J17: 4150000 | K17: =J17-I17 -> 900000
A18: 12 | B18: 002/IMP/VII/23 | C18: IMPORT CC & TRUCK | D18: PT. CITRA PERDANA PUTRA | E18: OOLU2721618793 | F18: SHEKOU | G18: 45138 | H18: 45209 | I18: 3450000 | J18: 4700000 | K18: =J18-I18 -> 1250000
F19: Total Profit Import | K19: =SUM(K7:K18) -> 76724540
A20: EXPORT
A21: NO | B21: REFF NO | C21: DESCRIPTION | D21: CUSTOMER | E21: NO. B/L | F21: DESTINASI | G21: ETD | H21: PAYMENT DATE | I21: BUYING | J21: SELLING | K21: PROFIT
A23: 13 | B23: 015/OTH/23 | C23: EXPORT CUSTOM & TRUCKING | D23: PT. DOLPHIN FOOD & BEVERAGES INDUSTRY | E23: 1KT888751 / WB854625 | F23: JKT-FIJI ISLAND | G23: 45118 | H23: 45135 | I23: 2810500 | J23: 3700000 | K23: =J23-I23 -> 889500
A24: 14 | B24: 016/OTH/23 | C24: EXPORT CC | D24: PT. BINA NIAGA MULTIUSAHA | E24: JKT300380300 | F24: JKT-FELIXSTOWE | G24: 45135 | H24: 45177 | I24: 3200000 | J24: 4650000 | K24: =J24-I24 -> 1450000
F25: Total Profit Export | K25: =SUM(K23:K24) -> 2339500
A26: LOKAL / DOMESTIK
A27: NO | B27: REFF NO | C27: DESCRIPTION | D27: CUSTOMER | E27: NO. B/L | F27: DESTINASI | G27: ETD | H27: PAYMENT DATE | I27: BUYING | J27: SELLING | K27: PROFIT
A29: 15 | B29: 005/DOM/VII/23 | C29: DOMESTIK AF | D29: PT. POLYCHEMIE ASIA PACIFIC PERMAI | E29: 938-36176361 | F29: CGK TO PADANG | G29: 45115 | H29: 45187 | I29: 3198000 | J29: 5502500 | K29: =J29-I29 -> 2304500
A30: 16 | B30: 006/DOM/VII/23 | C30: DOMESTIK AF | D30: PT. POLYCHEMIE ASIA PACIFIC PERMAI | E30: 237-00130130 | F30: CGK TO PANGKEP | G30: 45115 | H30: 45187 | I30: 4437000 | J30: 6815000 | K30: =J30-I30 -> 2378000
A31: 17 | B31: 007/DOM/VII/23 | C31: DOMESTIK | D31: PT. BERCA MANDIRI PERKASA | E31: 182/SKPB-MSD-MH/VII/23 | F31: JATAKE - CAKUNG | G31: 45048 | H31: 45180 | I31: 5500000 | J31: 6500000 | K31: =J31-I31 -> 1000000
F32: Total Profit Domestik | K32: =SUM(K29:K31) -> 5682500
F34: Total Export Import & Domestik | K34: =K19+K25+K32 -> 84746540
F35: Target Marketing | K35: 36000000
F37: Total Komisi 12,5% | K37: =K34*12.5/100 -> 10593318

Sheet MSR AGUSTUS 2023
A1: MSR AGUSTUS 2023
A2: Marketing : IKA
A3: PERIODE 01-31 AGUSTUS 2023
A4: IMPORT
A5: NO | B5: REFF NO | C5: DESCRIPTION | D5: CUSTOMER | E5: NO. B/L | F5: ORIGIN | G5: ETA | H5: PAYMENT DATE | I5: BUYING | J5: SELLING | K5: PROFIT
A7: 1 | B7: 018/IMP/VII/23 | C7: IMPORT OF & CC | D7: PT. BERCA MANDIRI PERKASA | E7: WS230700119 / JJCSHJKA389416 | F7: SHANGHAI | G7: 45147 | H7: 45180 | I7: 33750000 | J7: 42020080 | K7: =J7-I7 -> 8270080
A8: 2 | B8: 0014/IMP/VIII/23 | C8: IMPORTAF | D8: PT. AGRAPRANA JAYA EXPRESS / PT. POLYCHEMIE | E8: WS23080062 / 112-14098173 | F8: PUDONG - CGK | G8: 45151 | H8: 45152 | I8: 11565000 | J8: 21056020 | K8: =J8-I8 -> 9491020
A9: 3 | B9: 004/IMP/VII/23 | C9: IMPORT CC | D9: PT. CITRA PERDANA PUTRA | E9: MEDUDI737468 | F9: DALIAN | G9: 45153 | I9: 15820000 | J9: 18650000 | K9: =J9-I9 -> 2830000
A10: 4 | B10: 001/IMP/VIII/23 | C10: IMPORT CC | D10: PT. ALADDIN INDONESIA | E10: CENJKT23088503 | F10: QINGDAO | G10: 45157 | I10: 700000 | J10: 2300000 | K10: =J10-I10 -> 1600000
A11: 5 | B11: 009/IMP/VIII/23 | C11: IMPORT OF & CC | D11: PT. BERCA MANDIRI PERKASA | E11: WS230800054 / KMTCSHAL013520D | F11: SHANGHAI JKT | G11: 45165 | H11: 45187 | I11: 16890000 | J11: 21306140 | K11: =J11-I11 -> 4416140
A12: 6 | B12: 010/IMP/VIII/23 | C12: IMPORT OF & CC | D12: PT. BERCA MANDIRI PERKASA | E12: WS230800080 / YMLUI236318560 | F12: SHANGHAI TO BATAM | G12: 45165 | H12: 45187 | I12: 29200000 | J12: 37573800 | K12: =J12-I12 -> 8373800
A13: 7 | B13: 006/IMP/VIII/23 | C13: IMPORT OF ONLY | D13: PT. TRUELOGS GEO ENERGI | E13: S3PL/23-24/00/ FBLDJKT0823/00724 | F13: NEW DELHI | G13: 45167 | H13: 45170 | I13: 9029800 | J13: 14500000 | K13: =J13-I13 -> 5470200
A14: 8 | B14: 004/IMP/VIII/23 | C14: IMPORT OF & CC | D14: PT. BERCA MANDIRI PERKASA | E14: SITGSHJTQ116945 | F14: SHANGHAI - JKT | G14: 45167 | H14: 45187 | I14: 214400000 | J14: 256426000 | K14: =J14-I14 -> 42026000
A15: 9 | B15: 016/IMP/VIII/23 | C15: IMPORT OF & CC | D15: PT. BERCA MANDIRI PERKASA | E15: S00245344 /MEDUQK124541 | F15: NINGBO JKT | G15: 45169 | H15: 45187 | I15: 5975000 | J15: 10744435 | K15: =J15-I15 -> 4769435
A16: 10 | B16: 002/IMP/VIII/23 | C16: IMPORT CC | D16: PT. CITRA PERDANA PUTRA | E16: H2300749423 | F16: QINGDAO JKT | G16: 45169 | I16: 3550000 | J16: 4700000 | K16: =J16-I16 -> 1150000
A17: 11 | B17: 003/IMP/VIII/23 | C17: IMPORT CC | D17: PT. CITRA PERDANA PUTRA | E17: 273187656 | F17: XINGGANG JKT | G17: 45169 | I17: 2825000 | J17: 3362500 | K17: =J17-I17 -> 537500
A18: 12 | B18: 017/IMP/VIII/23 | C18: IMPORT OF & CC | D18: PT. BERCA MANDIRI PERKASA | E18: WS230800089 / 177IETETS03757UWS | F18: SHANGHAI TO JKT | G18: 45173 | H18: 45187 | I18: 35700000 | J18: 54139600 | K18: =J18-I18 -> 18439600
A19: 13 | B19: 018/IMP/VIII/23 | C19: IMPORT OF & CC | D19: PT. BERCA MANDIRI PERKASA | E19: WS230800091 / 177IETETS03756UWS | F19: SHANGHAI TO JKT | G19: 45173 | H19: 45187 | I19: 35700000 | J19: 54139600 | K19: =J19-I19 -> 18439600
F20: Total Profit Import | K20: =SUM(K7:K19) -> 125813375
F22: Total Export Import & Domestik | K22: =K20 -> 125813375
F23: Target Marketing | K23: 100000000
F25: Total Komisi 15% | K25: =K22*15/100 -> 18872006

Sheet MSR SEPTEMBER 2023
A1: MSR SEPTEMBER 2023
A2: Marketing : IKA
A3: PERIODE 01-30 SEPTEMBER 2023
A4: IMPORT
A5: NO | B5: REFF NO | C5: DESCRIPTION | D5: CUSTOMER | E5: NO. B/L | F5: ORIGIN | G5: ETA | H5: TGL PAYMENT | I5: BUYING | J5: SELLING | K5: PROFIT
A7: 1 | B7: 005/IMP/VIII/23 | C7: IMPORT - OF & CC | D7: PT. BERCA MANDIRI PERKASA | E7: GTD0798916 | F7: LAEM CHABANG - JKT | G7: 45174 | H7: 20/11/23 | I7: 8200000 | J7: 11700000 | K7: =J7-I7 -> 3500000
A8: 2 | B8: 007/IMP/VIII/23 | C8: IMPORT, CC & TRUCK | D8: PT. ARYASATYA MAKMUR LESTARI | E8: MCLMAA2301259 | F8: CHENNAI, INDIA | G8: 45175 | H8: 45210 | I8: 1800000 | J8: 3000000 | K8: =J8-I8 -> 1200000
A9: 3 | B9: 006/IMP/VIII/23 | C9: IMPORT CC | D9: PT. CITRA PERDANA PUTRA | E9: 273187646 | F9: XINGGANG JKT | G9: 45176 | H9: 24/10/2023 | I9: 3550000 | J9: 4750000 | K9: =J9-I9 -> 1200000
A10: 4 | B10: 10/IMP/IX/23 | C10: IMPORT CC & TRUCK | D10: PT. BERCA MANDIRI PERKASA | E10: GUA23090001 / 784-02585730 | F10: GUANGZHOU - CGK | G10: 45181 | H10: 20/11/23 | I10: 850000 | J10: 1637600 | K10: =J10-I10 -> 787600
A11: 5 | B11: 003/IMP/IX/23 | C11: IMPORT CC | D11: PT. CITRA PERDANA PUTRA | E11: OOLU2724496600 | F11: DA CHAN BAY - CHINA JKT | G11: 45184 | H11: 24/10/2023 | I11: 5390000 | J11: 6990000 | K11: =J11-I11 -> 1600000
A12: 6 | B12: 001/IMP/IX/23 | C12: IMPORT CC | D12: PT. BERCA MANDIRI PERKASA | E12: ONEYLCBD20617600 | F12: LAEM CHABANG - MEDAN | G12: 45185 | H12: LUNAS | I12: 2300000 | J12: 3200000 | K12: =J12-I12 -> 900000
A13: 7 | B13: 008/IMP/VIII/23 | C13: IMPORT, CC & TRUCK | D13: PT. ARYASATYA MAKMUR LESTARI | E13: MDACB23003881 | F13: MUNDRA INDIA | G13: 45188 | H13: 45210 | I13: 1900000 | J13: 3000000 | K13: =J13-I13 -> 1100000
A14: 8 | B14: 012/IMP/IX/23 | C14: IMPORT OF ONLY | D14: PT. BERCA MANDIRI PERKASA | E14: WS230800146 / 177IETETS03875 | F14: SHANGHAI - JKT | G14: 45189 | H14: 45088 | I14: 88000000 | J14: 118700000 | K14: =J14-I14 -> 30700000
A15: 9 | B15: 013/IMP/IX/23 | C15: IMPORT CC | D15: PT. BERCA MANDIRI PERKASA | E15: WS230800145 / 177IETETS03874 | F15: SHANGHAI - JKT | G15: 45189 | H15: 45088 | I15: 26950000 | J15: 37825300 | K15: =J15-I15 -> 10875300
A16: 10 | B16: 008/IMP/IX/23 | C16: IMPORT OF & CC | D16: PT. BERCA MANDIRI PERKASA | E16: S00247795 / MEDUQK463998 | F16: NINGBO - JKT | G16: 45190 | H16: 45088 | I16: 5275000 | J16: 11521760 | K16: =J16-I16 -> 6246760
A17: 11 | B17: 002/IMP/IX/23 | C17: IMPORT CC | D17: PT. BERCA MANDIRI PERKASA | E17: ONEYLCBD20518600 | F17: LAEM CHABANG - SURABAYA | G17: 45191 | H17: LUNAS | I17: 2300000 | J17: 3200000 | K17: =J17-I17 -> 900000
A18: 12 | B18: 009/IMP/IX/23 | C18: IMPORT OF & CC | D18: PT. BERCA MANDIRI PERKASA | E18: S00248869 / COAU8034728910 | F18: QINGDAO - JKT | G18: 45191 | H18: 45088 | I18: 8275000 | J18: 13215320 | K18: =J18-I18 -> 4940320
A19: 13 | B19: 004/IMP/IX/23 OUTSIDE | C19: IMPORT OF & CC | D19: PT. BERCA MANDIRI PERKASA | E19: GTD0801181 | F19: BANGKOK - JKT | G19: 45191 | H19: 20/11/23 | I19: 14350000 | J19: 20225000 | K19: =J19-I19 -> 5875000
A20: 14 | B20: 010/IMP/IX/23 | C20: IMPORT - OF & CC | D20: PT. BERCA MANDIRI PERKASA | E20: WS230800147 / OOLU2724058700 | F20: SHANGHAI - JKT EXW | G20: 45193 | H20: 20/11/23 | I20: 67640000 | J20: 95504240 | K20: =J20-I20 -> 27864240
A21: 15 | B21: 004/IMP/IX/24 | C21: IMPORT OF & CC | D21: PT. BERCA MANDIRI PERKASA | E21: S00248604 / MEDUQK452777 | F21: NINGBO - SBY | G21: 45194 | H21: 45088 | I21: 5375000 | J21: 11671760 | K21: =J21-I21 -> 6296760
A22: 16 | B22: 12/IMP/IX/23 | C22: IMPORT CC | D22: PT. NATA KIMINDO PRATAMA | E22: 112-70755624 | F22: SHANGHAI | G22: 45194 | H22: 45088 | I22: 943000 | J22: 2251000 | K22: =J22-I22 -> 1308000
A23: 17 | B23: 019/IMP/IX/23 | C23: IMPORT CC | D23: PT. BERCA MANDIRI PERKASA | E23: WS230900045 / KMTCSHAL196059 | F23: SHANGHAI - JKT EXW | G23: 45196 | H23: 44968 | I23: 64425000 | J23: 87445600 | K23: =J23-I23 -> 23020600
A24: 18 | B24: 005/IMP/IX/23 | C24: IMPORT OF ONLY | D24: PT. AGRAPRANA / PT. POLYCHEMIE | E24: TLC230927075 / EGLV020300333388 | F24: YOKOHAMA - JKT | G24: 45198 | H24: 45088 | I24: 3024872 | J24: 7219482 | K24: =J24-I24 -> 4194610
A25: 19 | B25: 006/IMP/IX/23 | C25: IMPORT, CC & TRUCK | D25: PT. ARYASATYA MAKMUR LESTARI | E25: SSLKAJKTCAA0885 | F25: KATTUPALI - JKT | G25: 45201 | H25: 45198 | I25: 1800000 | J25: 2800000 | K25: =J25-I25 -> 1000000
A26: 20 | B26: 005/IMP/IX/23 | C26: IMPORT, CC & TRUCK | D26: PT. ARYASATYA MAKMUR LESTARI | E26: CNICB23014321 | F26: CHENNAI, INDIA - JKT | G26: 45206 | H26: LUNAS | I26: 1800000 | J26: 2800000 | K26: =J26-I26 -> 1000000
A27: 21 | B27: NULL | C27: IMPORT OF & CC | D27: PT. BERCA MANDIRI PERKASA | E27: ORD1048610 / NAM6442929 | F27: HOUSTON JKT | G27: 45245 | H27: LUNAS | I27: 31970000 | J27: 42270000 | K27: =J27-I27 -> 10300000
A28: 22 | B28: 001/DOM/IX/23 | C28: DOMESTIK | D28: PT. BERCA MANDIRI PERKASA | E28: 215/SKPB-MSD-MH/IX/23 | F28: JATAKE - JAMBI | G28: 45172 | H28: LUNAS | I28: 11500000 | J28: 12500000 | K28: =J28-I28 -> 1000000
A29: 23 | B29: NULL | C29: IMPORT OF & CC | D29: PT. BERCA MANDIRI PERKASA | E29: ORD1048628 / NAM6458612 | F29: HOUSTON JKT | G29: 45245 | H29: 13/11/23 | I29: 31970000 | J29: 42270000 | K29: =J29-I29 -> 10300000
F30: Total Profit Import | K30: =SUM(K7:K29) -> 156109190
F32: Total Export Import & Domestik | K32: =K30 -> 156109190
F33: Target Marketing | K33: 100000000
F35: Total Komisi 15% | K35: =K32*15/100 -> 23416378 | M35: lunas 19/1/24

Sheet MSR OKT 2023
A1: MSR OKTOBER 2023
A2: Marketing : IKA
A3: PERIODE 01 - 30 OKTOBER2023
A4: IMPORT
A5: NO | B5: SO NUMBER | C5: DESCRIPTION | D5: CUSTOMER | E5: NO. B/L | F5: ORIGIN | G5: ETA | H5: TGL PAYMENT | I5: BUYING | J5: SELLING | K5: PROFIT
A7: 1 | B7: 2310-001 | C7: IMPORT CC | D7: PT CITRA JAYA HOSINDO | E7: ONEYTA3DK7430300 | F7: QINGDAO | G7: 30/10/23 | H7: 15/11/23 | I7: 4766816 | J7: 6054616 | K7: =J7-I7 -> 1287800
A8: 2 | B8: 2310-002 | C8: IMPORT CC | D8: PT CITRA PERDANA PUTRA | E8: MAEU273487610 | F8: XINGGANG | G8: 14/10/23 | I8: 25141601 | J8: 28836601 | K8: =J8-I8 -> 3695000
A9: 3 | B9: 2310-003 | C9: IMPORT AF | D9: PT BEPAHKUPI GLOBAL EKSPOR | E9: WS23100088 / 126-88894481 | F9: SHANGHAI | G9: 19/10/23 | H9: 16/110/23 | I9: 7128145 | J9: 17839800 | K9: =J9-I9 -> 10711655
A10: 4 | B10: 2310-004 | C10: IMPORT CC | D10: PT CITRA PERDANA PUTRA | E10: MAEU273487613 | F10: XINGGANG | G10: 17/10/23 | I10: 7419698 | J10: 8302698 | K10: =J10-I10 -> 883000
A11: 5 | B11: 2310-005 | C11: IMPORT CC | D11: PT CITRA PERDANA PUTRA | E11: MAEU273487791 | F11: XINGGANG | G11: 30/10/23 | I11: 5136712 | J11: 5809712 | K11: =J11-I11 -> 673000
F12: Total Profit Import | K12: =SUM(K7:K11) -> 17250455
F14: Total Export Import & Domestik | K14: =K12 -> 17250455
F15: Target Marketing | K15: 105000000
F17: Total Komisi 10% | K17: =K14*10/100 -> 1725045.5

Sheet MSR NOV 2023 
A1: MSR NOVEMBER 2023
A2: Marketing : IKA
A3: PERIODE 01 - 30 NOVEMBER 2023
A4: IMPORT
A5: NO | B5: SO NUMBER | C5: DESCRIPTION | D5: CUSTOMER | E5: NO. B/L | F5: ORIGIN | G5: ETA | H5: TGL PAYMENT | I5: BUYING | J5: SELLING | K5: PROFIT
A7: 1 | B7: S02311-001 | C7: IMPORT OF & CUSTOM | D7: PT AGATA PROMAR | E7: OOLU2300926930 | F7: DA CHAN BAY CHINA | G7: 22/11/23 | I7: 15826747 | J7: 22259472 | K7: =J7-I7 -> 6432725
A8: 2 | B8: SO2311-002 | C8: CUSTOM EXPORT | D8: PT DOLPHIN FOOD & BEVERAGES | E8: MEDUIE724659 | F8: JAKARTA - SIN | G8: 23/11/23 | I8: 3354238 | J8: 3700000 | K8: =J8-I8 -> 345762
A9: 3 | B9: S02311-003 | C9: TRUCKING 1X20GP | D9: PT EXODUS INTERNATIONAL | E9: OOLU2143333180 | F9: USA | G9: 17/11/23 | H9: 23-30/11/23 | I9: 2337100 | J9: 2627100 | K9: =J9-I9 -> 290000
F10: Total Profit Import | K10: =SUM(K7:K9) -> 7068487
F12: Total Export Import & Domestik | K12: =K10 -> 7068487
F13: Target Marketing | K13: 70000000
F15: Total Komisi 10% | K15: =K12*10/100 -> 706848.7 | M15: GAJIAN TGL 30/11 IDR 2.100

Sheet MSR DES 2023
A1: MSR DESEMBER 2023
A2: Marketing : IKA
A3: PERIODE 01 - 31 DESEMBER 2023
A4: NO | B4: SO NUMBER | C4: DESCRIPTION | D4: CUSTOMER | E4: NO. B/L | F4: ORIGIN | G4: TGL PAYMENT | H4: PROFIT
A6: IMPORT
A7: 1 | B7: SO2311-004 | C7: IMPORT - CC ONLY | D7: PT CITRA PERDANA PUTRA | E7: SITGTXDR451950 | F7: XINGANG - SEMARANG | H7: 4420000
A8: 2 | B8: SO2311-005 | C8: IMPORT - CC ONLY | D8: PT CITRA PERDANA PUTRA | E8: MAEU273769814 | F8: XINGANG - JAKARTA | H8: 973000
A9: 3 | B9: SO2311-006 | C9: IMPORT - CC ONLY | D9: PT CITRA PERDANA PUTRA | E9: SITGTXDR451692 | F9: XINGANG - SEMARANG | H9: 4930000
A10: 4 | B10: SO2312-001 | C10: IMPORT - CC ONLY | D10: PT FECALINDO DINAMIKA INTIPRIMA | E10: CTLTDD0000223979 | F10: NZ - JKT | H10: 8830000
A11: 5 | B11: SO2312-002 | C11: IMPORT CC | D11: PT. CITRA PERDANA PUTRA | E11: MAEU273769710 | F11: XINGANG - JAKARTA | H11: 1425000
A12: 6 | B12: SO2312-003 | C12: IMPORT - CC ONLY | D12: PT CITRA PERDANA PUTRA | E12: MAEU232500561 | F12: XINGANG - SEMARANG | H12: 4198000
A13: 7 | B13: SO2312-004 | C13: IMPORT - CC ONLY | D13: PT CITRA PERDANA PUTRA | E13: HLCUTS12310AVTM1 | F13: XINGANG - BELAWAN | H13: 4869450
A14: 8 | B14: SO2312-008 | C14: IMPORT - CC ONLY | D14: PT CITRA PERDANA PUTRA | E14: MAEU273769960 | F14: XINGANG - SEMARANG | H14: 18275000
A15: 9 | B15: SO2312-009 | C15: IMPORT - CC ONLY | D15: PT CITRA PERDANA PUTRA | E15: MAEU273769961 | F15: XINGANG - SEMARANG | H15: 8015000
A16: EXPORT
A17: 10 | B17: SO2312-005 | C17: TRUCKING ONLY | D17: PT QUANTERM LOGISTINDO | E17: JKTD89721500 | F17: JKT-SONGHKLA | H17: 4620000
A18: 11 | B18: SO2312-006 | C18: Export CC & Truck | D18: PT Dolphin Food & Beverages | E18: JKT2312288 | F18: JKT - HONOIRA | H18: 281552
A19: 12 | B19: SO2312-007 | C19: EXPORT AF & CUSTOM | D19: PT PRIMAPLAST INDONESIA | E19: AA23120517 | F19: JKT - NGO JAPAN | H19: 17162500
A20: DOMESTIK
A21: 13 | B21: SO2312-010 | C21: TRUCKING ONLY | D21: PT OBOR INDONESIA PRATAMA | E21: BTG2302127200012 | F21: BITUNG-JKT | H21: 250000
F22: Total Profit Import | H22: =SUM(H7:H21) -> 78249502
F24: Total Export Import & Domestik | H24: =H22 -> 78249502
F25: Target Marketing | H25: 100000000
F27: Total Komisi 10% | H27: =H24*10/100 -> 7824950.2 | J27: lunas 05/01/24

Sheet MSR JAN 24
A1: MSR DESEMBER 2023
A2: Marketing : IKA
A3: PERIODE 01 - 31 DESEMBER 2023
A4: NO | B4: SO NUMBER | C4: DESCRIPTION | D4: CUSTOMER | E4: NO. B/L | F4: ORIGIN | G4: TGL PAYMENT | H4: PROFIT
A6: IMPORT
A7: 1 | B7: SO2311-004 | C7: IMPORT - CC ONLY | D7: PT CITRA PERDANA PUTRA | E7: SITGTXDR451950 | F7: XINGANG - SEMARANG | H7: 4420000
A8: 2 | B8: SO2311-005 | C8: IMPORT - CC ONLY | D8: PT CITRA PERDANA PUTRA | E8: MAEU273769814 | F8: XINGANG - JAKARTA | H8: 973000
A9: 3 | B9: SO2311-006 | C9: IMPORT - CC ONLY | D9: PT CITRA PERDANA PUTRA | E9: SITGTXDR451692 | F9: XINGANG - SEMARANG | H9: 4930000
A10: 4 | B10: SO2312-001 | C10: IMPORT - CC ONLY | D10: PT FECALINDO DINAMIKA INTIPRIMA | E10: CTLTDD0000223979 | F10: NZ - JKT | H10: 8830000
A11: 5 | B11: SO2312-002 | C11: IMPORT CC | D11: PT. CITRA PERDANA PUTRA | E11: MAEU273769710 | F11: XINGANG - JAKARTA | H11: 1425000
A12: 6 | B12: SO2312-003 | C12: IMPORT - CC ONLY | D12: PT CITRA PERDANA PUTRA | E12: MAEU232500561 | F12: XINGANG - SEMARANG | H12: 4198000
A13: 7 | B13: SO2312-004 | C13: IMPORT - CC ONLY | D13: PT CITRA PERDANA PUTRA | E13: HLCUTS12310AVTM1 | F13: XINGANG - BELAWAN | H13: 4869450
A14: 8 | B14: SO2312-008 | C14: IMPORT - CC ONLY | D14: PT CITRA PERDANA PUTRA | E14: MAEU273769960 | F14: XINGANG - SEMARANG | H14: 18275000
A15: 9 | B15: SO2312-009 | C15: IMPORT - CC ONLY | D15: PT CITRA PERDANA PUTRA | E15: MAEU273769961 | F15: XINGANG - SEMARANG | H15: 8015000
A16: EXPORT
A17: 10 | B17: SO2312-005 | C17: TRUCKING ONLY | D17: PT QUANTERM LOGISTINDO | E17: JKTD89721500 | F17: JKT-SONGHKLA | H17: 4620000
A18: 11 | B18: SO2312-006 | C18: Export CC & Truck | D18: PT Dolphin Food & Beverages | E18: JKT2312288 | F18: JKT - HONOIRA | H18: 281552
A19: 12 | B19: SO2312-007 | C19: EXPORT AF & CUSTOM | D19: PT PRIMAPLAST INDONESIA | E19: AA23120517 | F19: JKT - NGO JAPAN | H19: 17162500
A20: DOMESTIK
A21: 13 | B21: SO2312-010 | C21: TRUCKING ONLY | D21: PT OBOR INDONESIA PRATAMA | E21: BTG2302127200012 | F21: BITUNG-JKT | H21: 250000
F22: Total Profit Import | H22: =SUM(H7:H21) -> 78249502
F24: Total Export Import & Domestik | H24: =H22 -> 78249502
F25: Target Marketing | H25: 100000000
F27: Total Komisi 10% | H27: =H24*10/100 -> 7824950.2 | J27: lunas 05/01/24

Sheet MSR FEB 24
A1: MSR DESEMBER 2023
A2: Marketing : IKA
A3: PERIODE 01 - 31 DESEMBER 2023
A4: NO | B4: SO NUMBER | C4: DESCRIPTION | D4: CUSTOMER | E4: NO. B/L | F4: ORIGIN | G4: TGL PAYMENT | H4: PROFIT
A6: IMPORT
A7: 1 | B7: SO2311-004 | C7: IMPORT - CC ONLY | D7: PT CITRA PERDANA PUTRA | E7: SITGTXDR451950 | F7: XINGANG - SEMARANG | H7: 4420000
A8: 2 | B8: SO2311-005 | C8: IMPORT - CC ONLY | D8: PT CITRA PERDANA PUTRA | E8: MAEU273769814 | F8: XINGANG - JAKARTA | H8: 973000
A9: 3 | B9: SO2311-006 | C9: IMPORT - CC ONLY | D9: PT CITRA PERDANA PUTRA | E9: SITGTXDR451692 | F9: XINGANG - SEMARANG | H9: 4930000
A10: 4 | B10: SO2312-001 | C10: IMPORT - CC ONLY | D10: PT FECALINDO DINAMIKA INTIPRIMA | E10: CTLTDD0000223979 | F10: NZ - JKT | H10: 8830000
A11: 5 | B11: SO2312-002 | C11: IMPORT CC | D11: PT. CITRA PERDANA PUTRA | E11: MAEU273769710 | F11: XINGANG - JAKARTA | H11: 1425000
A12: 6 | B12: SO2312-003 | C12: IMPORT - CC ONLY | D12: PT CITRA PERDANA PUTRA | E12: MAEU232500561 | F12: XINGANG - SEMARANG | H12: 4198000
A13: 7 | B13: SO2312-004 | C13: IMPORT - CC ONLY | D13: PT CITRA PERDANA PUTRA | E13: HLCUTS12310AVTM1 | F13: XINGANG - BELAWAN | H13: 4869450
A14: 8 | B14: SO2312-008 | C14: IMPORT - CC ONLY | D14: PT CITRA PERDANA PUTRA | E14: MAEU273769960 | F14: XINGANG - SEMARANG | H14: 18275000
A15: 9 | B15: SO2312-009 | C15: IMPORT - CC ONLY | D15: PT CITRA PERDANA PUTRA | E15: MAEU273769961 | F15: XINGANG - SEMARANG | H15: 8015000
A16: EXPORT
A17: 10 | B17: SO2312-005 | C17: TRUCKING ONLY | D17: PT QUANTERM LOGISTINDO | E17: JKTD89721500 | F17: JKT-SONGHKLA | H17: 4620000
A18: 11 | B18: SO2312-006 | C18: Export CC & Truck | D18: PT Dolphin Food & Beverages | E18: JKT2312288 | F18: JKT - HONOIRA | H18: 281552
A19: 12 | B19: SO2312-007 | C19: EXPORT AF & CUSTOM | D19: PT PRIMAPLAST INDONESIA | E19: AA23120517 | F19: JKT - NGO JAPAN | H19: 17162500
A20: DOMESTIK
A21: 13 | B21: SO2312-010 | C21: TRUCKING ONLY | D21: PT OBOR INDONESIA PRATAMA | E21: BTG2302127200012 | F21: BITUNG-JKT | H21: 250000
F22: Total Profit Import | H22: =SUM(H7:H21) -> 78249502
F24: Total Export Import & Domestik | H24: =H22 -> 78249502
F25: Target Marketing | H25: 100000000
F27: Total Komisi 10% | H27: =H24*10/100 -> 7824950.2 | J27: lunas 05/01/24

Sheet MSR MAR 24
A1: MSR MARET 2024
A2: Marketing : IKA
A3: PERIODE 01-31 MARET 2024
A4: NO | B4: SO NUMBER | C4: DESCRIPTION | D4: CUSTOMER | E4: NO. B/L | F4: ORIGIN | G4: TGL PAYMENT | H4: PROFIT
A6: IMPORT
A7: 1
A8: 2
A9: 3
A10: 4
A11: 5
A12: 6
A13: 7
A14: 8
A15: 9
A16: EXPORT
A17: 10
A18: 11
A19: 12
A20: DOMESTIK
F22: Total Profit Import | H22: =SUM(H7:H21) -> 0
F24: Total Export Import & Domestik | H24: =H22 -> 0
F25: Target Marketing | H25: 105000000
H26: 6
F27: Total Komisi 10% | H27: =H24*10/100 -> 0

Sheet PIUTANG TEST
B4: {=SHIPMENT!#REF!} -> #REF!

Sheet Format Trucking List
A3: No | B3: Muat | C3: Tujuan | D3: Trucking Rate | F3: Keterangan
D4: 20" | E4: 40"
A5: Priok Area
A6: 1 | B6: Tg. Priok | C6: Cakung | D6: 1750000 | E6: 1850000
A7: 2 | B7: Tg. Priok | C7: Marunda | D7: 1750000 | E7: 1850000
A8: 3 | B8: Tg. Priok | C8: Pulo Gadung | D8: 1750000 | E8: 1850000
A9: 4 | B9: Tg. Priok | C9: Ancol - Mangga Dua | D9: 1750000 | E9: 1850000
A10: 5 | B10: Tg. Priok | C10: Sunter - Plumpang | D10: 1750000 | E10: 1850000
A11: 6 | B11: Tg. Priok | C11: Sunda Kelapa | D11: 1850000 | E11: 1950000
A12: 7 | B12: Tg. Priok | C12: Pluit Bandengan | D12: 2050000 | E12: 2150000
A13: Lintas Cikampek
A14: 1 | B14: Tg. Priok | C14: Pondok Ungu | D14: 2250000 | E14: 2350000
A15: 2 | B15: Tg. Priok | C15: Bekasi, Tambun | D15: 2250000 | E15: 2350000
A16: 3 | B16: Tg. Priok | C16: Cibitung | D16: 2350000 | E16: 2450000
A17: 4 | B17: Tg. Priok | C17: Cikarang/Jababeka | D17: 2450000 | E17: 2550000
A18: 5 | B18: Tg. Priok | C18: Cikarang Pusat | D18: 2650000 | E18: 2750000
A19: 6 | B19: Tg. Priok | C19: Karawang Barat | D19: 2750000 | E19: 2850000
A20: 7 | B20: Tg. Priok | C20: Karawang Timur | D20: 2850000 | E20: 2950000
A21: 8 | B21: Tg. Priok | C21: Cikampek / Klari | D21: 2950000 | E21: 3050000
A22: 9 | B22: Tg. Priok | C22: Subang | D22: 4950000 | E22: 5150000
A23: 10 | B23: Tg. Priok | C23: Indramayu | D23: 5250000 | E23: 5450000
A24: 11 | B24: Tg. Priok | C24: Cirebon | D24: 5750000 | E24: 5950000
A25: Lintas Jagorawi
A26: 1 | B26: Tg. Priok | C26: Ciracas, Ps. Rebo, Kr. Jati | D26: 2750000 | E26: 2850000
A27: 2 | B27: Tg. Priok | C27: Cimanggis, Cileungsi, Gn. Putri | D27: 2850000 | E27: 2950000
A28: 3 | B28: Tg. Priok | C28: Citeureup, Cibinong, Jonggol | D28: 2950000 | E28: 3100000
A29: 4 | B29: Tg. Priok | C29: Bogor | D29: 3150000 | E29: 3250000
A30: 5 | B30: Tg. Priok | C30: Ciawi | D30: 3250000 | E30: 3450000
A31: 6 | B31: Tg. Priok | C31: Cicurug, Pr. Kuda, Sukabumi | D31: 5350000 | E31: 5500000
A32: Lintas Tol Merak
A33: 1 | B33: Tg. Priok | C33: BSD, Legok | D33: 2750000 | E33: 2850000
A34: 2 | B34: Tg. Priok | C34: Curug, Karawaci, Bitung | D34: 2750000 | E34: 2850000
A35: 3 | B35: Tg. Priok | C35: Jatake, Cikupa, Tigaraksa | D35: 2750000 | E35: 2850000
A36: 4 | B36: Tg. Priok | C36: Tangerang, Mauk, Ps. Kemis | D36: 2750000 | E36: 2850000
A37: 5 | B37: Tg. Priok | C37: Cikande | D37: 3750000 | E37: 3850000
A38: 6 | B38: Tg. Priok | C38: Kapuk, Dadap, Kembangan | D38: 2750000 | E38: 2850000
A39: 7 | B39: Tg. Priok | C39: Serang, Rks Bitung | D39: 5150000 | E39: 5250000
A40: 8 | B40: Tg. Priok | C40: Cilegon, Bojonegoro, Merak | D40: 5750000 | E40: 5950000
A41: 9 | B41: Tg. Priok | C41: Daan Mogot, X-Deres, Batuceper | D41: 2550000 | E41: 2650000
A42: Lintas Bandung
A43: 1 | B43: Tg. Priok | C43: Padalarang | D43: 5300000 | E43: 5550000
A44: 2 | B44: Tg. Priok | C44: Kopo | D44: 5150000 | E44: 5250000
A45: 3 | B45: Tg. Priok | C45: Rancaekek | D45: 5450000 | E45: 5750000
A46: 4 | B46: Tg. Priok | C46: Cianjur | D46: 5450000 | E46: 5750000
A47: 5 | B47: Tg. Priok | C47: Garut | D47: 5950000 | E47: 6250000
A48: 6 | B48: Tg. Priok | C48: Sumedang | D48: 5650000 | E48: 5750000
A49: 7 | B49: Tg. Priok | C49: Tasikmalaya | D49: 7950000 | E49: 8200000
A50: 8 | B50: Tg. Priok | C50: Ciamis, Banjar | D50: 9250000 | E50: 9750000
A51: 9 | B51: Tg. Priok | C51: Pangandaran | D51: 13500000 | E51: 1400000
A52: Lintas Sumatera
A53: 1 | B53: Tg. Priok | C53: Palembang | D53: 29500000 | E53: 30800000
A54: 2 | B54: Tg. Priok | C54: Medan | D54: 31250000 | E54: 35450000
B87: 0

Sheet TABUNGAN EMAS
A1: ANGSURAN EMAS 10GR - 3THN (36 BULAN)
A4: Angsuran ke | B4: Jth Tempo | C4: Nominal | D4: Paid Tgl | E4: Keterangan
B6: 44585
B7: 44616
B8: 44644
B9: 44675
B10: 44705
B11: 44736
B12: 44766
B13: 44797
B14: 44828
B15: 44858
B16: 44889
B17: 44919
... B41: 45650

Sheet PEMBUKUAN
A1: PEMBUKUAN PT ESHAKA WIJAYA LOGISTICS TAHUN 2023
A2: Periode : Oktober 2023
A3: NO | B3: Order Number | C3: Customer Name | D3: Shipper Name | E3: BL Number | F3: Type | G3: Kontainer No. | H3: Commodity | I3: POL - POD | J3: ETD | K3: ETA | L3: SPPB | M3: Delivery Date | N3: Liner / Airliner | O3: Description | P3: Vendor | Q3: Buying | R3: Selling | S3: Pot PPh 2% | T3: Margin / Revenue | U3: Remark
A4: 1 | B4: SO2310-001 | C4: PT Citra Jaya Hosindo | D4: Henan Huvlone Hydraulic Technology | E4: ONEYTA3DK7430300 | F4: 1X20GP | G4: TRHU1993143 | H4: Hydraulic Hose | I4: Qingdao - Jakarta | J4: 45220 | K4: 45230 | L4: 31/10/23 | M4: 31/10/23 | N4: ONE | O4: Invoice Jasa
O5: Handling | P5: Kaka Trans | Q5: 125000 | R5: 350000 | T5: =R5-Q5 -> 225000 | U5: AJU : 004943
O6: PIB EDI | Q6: 100000 | R6: 250000 | T6: =R6-Q6 -> 150000 | U6: EWL2310-001/R
O7: JNE Tagihan | P7: Ewil | Q7: 10000 | R7: 0 | T7: =R7-Q7 -> -10000 | U7: LUNAS 15 /11/2023
O8: Pot Adm Bank | P8: CJH | Q8: 2500 | R8: 0 | T8: =R8-Q8 -> -2500
O9: Trucking | P9: Hanabi | Q9: 1450000 | R9: 2375000 | T9: =R9-Q9 -> 925000
O10: Debit Note
O11: Lift Of / Lift On | P11: Hanabi | Q11: 765900 | R11: 765900 | T11: =R11-Q11 -> 0 | U11: As Per Receipt
O12: Storage Pelindo | P12: Ewil | Q12: 371396 | R12: 371396 | T12: =R12-Q12 -> 0
O13: Do Charges | Q13: 1606320 | R13: 1606320 | T13: =R13-Q13 -> 0
O14: Parkir | P14: Hanabi | Q14: 36000 | R14: 36000 | T14: =R14-Q14 -> 0
O15: Biaya Bongkar | P15: Hanabi | Q15: 300000 | R15: 300000 | T15: =R15-Q15 -> 0
O16: Total | Q16: =SUM(Q5:Q15) -> 4767116 | R16: =SUM(R5:R15) -> 6054616 | S16: 0 | T16: =SUM(T5:T9) -> 1287500 | U16: TF 15/11/23
R17: =R16-S16 -> 6054616 | U17: 6052116
A18: 2 | B18: SO2310-002 | C18: PT Citra Perdana Putra | D18: Inner Mongolia Epen Biotech | E18: MAEU273487610 | F18: 1X20GP | G18: MSKU3869267 | H18: Monosodium Glutamate | I18: Xinggang - Semarang | J18: 45223 | K18: 45213 | L18: 45223 | M18: 26-10-2023 TITIP DEPO PENITIPAN | N18: MAERSK | O18: Invoice Jasa
O19: Handling Green | P19: SPS | Q19: 200000 | R19: 450000 | S19: =R19*2/100 -> 9000 | T19: =R19-Q19 -> 250000 | U19: AJU : 003957
O20: Materai 4 Pcs | Q20: 0 | R20: 60000 | S20: =R20*2/100 -> 1200 | T20: =R20-Q20 -> 60000 | U20: EWL2310-002/R
O21: PIB EDI | Q21: 200000 | R21: 350000 | S21: =R21*2/100 -> 7000 | T21: =R21-Q21 -> 150000 | U21: 17/11/23
O22: Trucking SMG -Yogya | Q22: 2500000 | R22: 3550000 | S22: =R22*2/100 -> 71000 | T22: =R22-Q22 -> 1050000
O23: Trucking Repo Penitipan | Q23: 0 | R23: 950000 | S23: =R23*2/100 -> 19000 | T23: =R23-Q23 -> 950000
O24: Storage Penitipan | Q24: 660000 | R24: 1575000 | S24: =R24*2/100 -> 31500 | T24: =R24-Q24 -> 915000
O25: Lolo Penitipan | Q25: 550000 | R25: 850000 | S25: =R25*2/100 -> 17000 | T25: =R25-Q25 -> 300000
O26: Admin Penitipan | Q26: 30000 | R26: 250000 | S26: =R26*2/100 -> 5000 | T26: =R26-Q26 -> 220000
O27: Refund Dewi | P27: Ewil | Q27: 100000 | R27: 0 | S27: =R27*2/100 -> 0 | T27: =R27-Q27 -> -100000
O28: Debit Note
O29: Do Charges | P29: SPS | Q29: 2544051 | R29: 2544051 | S29: 0 | T29: =R29-Q29 -> 0 | U29: As Per Receipt
O30: Lift Of / Lift On | Q30: 466200 | R30: 466200 | S30: 0 | T30: =R30-Q30 -> 0
O31: Storage | Q31: 1995780 | R31: 1995780 | S31: 0 | T31: =R31-Q31 -> 0
O32: Detention | Q32: 15857820 | R32: 15857820 | S32: 0 | T32: =R32-Q32 -> 0
O33: Adm Det | Q33: 27750 | R33: 27750 | S33: 0 | T33: =R33-Q33 -> 0
O34: Biaya Materai | Q34: 10000 | R34: 10000 | S34: 0 | T34: =R34-Q34 -> 0
O35: Total | Q35: =SUM(Q19:Q34) -> 25141601 | R35: =SUM(R19:R34) -> 28936601 | S35: =SUM(S19:S34) -> 160700 | T35: =SUM(T19:T34) -> 3795000
R36: 6319040 | T36: =T35-S35 -> 3634300
A37: 3 | B37: SO2310-003 | C37: PT Bepahkupi Global Ekspor | D37: Beijing Guixia Legend Trading | E37: 126-88894481 | F37: Import LCL By Air | G37: 4 Pallet / 853 Kg / 8 Cbm | H37: Coffee Sparepart | I37: Shanghai - CGK | J37: 45218 | K37: 19/10/23 at 16:00 | L37: - | M37: - | N37: GA | O37: Doc Fee | P37: Win Share | Q37: 7048145 | R37: 1065300 | T37: =R37-Q37 -> -5982845 | U37: Cancel Pick up & Delivery back Cargo
O38: Custom at Origin | Q38: 80000 | R38: 1431000 | T38: =R38-Q38 -> 1351000 | U38: Adm BCA Tf Valas
O39: Handling at Origin | R39: 874500 | T39: =R39-Q39 -> 874500 | U39: Invoice No : SO2310-003 - 16/10/23
O40: Pick Up Charge | R40: 7234500 | T40: =R40-Q40 -> 7234500
O41: Delivery Charge | R41: 7234500 | T41: =R41-Q41 -> 7234500
O42: Total | Q42: 7128145 | R42: 17839800 | T42: 10711655 | U42: LUNAS 19 /10/2023
A43: 4 | B43: SO2310-004 | C43: PT Citra Perdana Putra | D43: Inner Mongolia Epen Biotech | E43: MAEU273487613 | F43: 1X20GP | G43: MSKU3869267 | H43: Monosodium Glutamate | I43: Xinggang - Jakarta | J43: 45229 | K43: 45215 | L43: 45223 | M43: 45225 | N43: MAERSK | O43: Invoice Jasa
O44: Handling Green | P44: Kaka Trans | Q44: 125000 | R44: 350000 | S44: =R44*2/100 -> 7000 | T44: =R44-Q44 -> 225000 | U44: AJU : 004952
O45: Biaya DO | Q45: 150000 | R45: 0 | S45: =R45*2/100 -> 0 | T45: =R45-Q45 -> -150000 | U45: EWL2310-004/R
O46: Materai 4 Pcs | Q46: 0 | R46: 48000 | S46: =R46*2/100 -> 960 | T46: =R46-Q46 -> 48000 | U46: 24/10/23
O47: PIB EDI | Q47: 100000 | R47: 300000 | S47: =R47*2/100 -> 6000 | T47: =R47-Q47 -> 200000
O48: Trucking Dadap | P48: Hanabi | Q48: 1500000 | R48: 1900000 | S48: =R48*2/100 -> 38000 | T48: =R48-Q48 -> 400000
O49: Stempel 2 Pcs | P49: S. Kembangan | Q49: 80000 | R49: 250000 | S49: =R49*2/100 -> 5000 | T49: =R49-Q49 -> 170000
O50: Refund Dewi | P50: BCA Dewi | Q50: 150000 | R50: 0 | S50: =R50*2/100 -> 0 | T50: =R50-Q50 -> -150000
O51: Debit Note
O52: Lift Of / Lift On | P52: Seacon / Hanabi | Q52: 699500 | R52: 699500 | S52: 0 | T52: =R52-Q52 -> 0 | U52: As Per Receipt
O53: Storage NPCT1 | P53: Ewilog | Q53: 2777321 | R53: 2777321 | S53: 0 | T53: =R53-Q53 -> 0
O54: Do Charges | P54: Ewilog | Q54: 1827877 | R54: 1827877 | S54: 0 | T54: =R54-Q54 -> 0
O55: Biaya Bongkar | P55: Hanabi | Q55: 150000 | R55: 150000 | S55: 0 | T55: =R55-Q55 -> 0
O56: Total | Q56: =SUM(Q44:Q55) -> 7559698 | R56: =SUM(R44:R55) -> 8302698 | S56: =SUM(S44:S55) -> 56960 | T56: =SUM(T44:T55) -> 743000
R57: =R56-S56 -> 8245738 | T57: =T56-S56 -> 686040
A58: 5 | B58: SO2310-005 | C58: PT Citra Perdana Putra | D58: Inner Mongolia Epen Biotech | E58: MAEU273487791 | F58: 1X20GP | G58: TEMU0698643 | H58: Monosodium Glutamate | I58: Xinggang - Jakarta | J58: 45215 | K58: 45230 | L58: 44937 | M58: 44937 | N58: MAERSK | O58: Invoice Jasa
O59: Handling Green | P59: Kaka Trans | Q59: 125000 | R59: 350000 | S59: =R59*2/100 -> 7000 | T59: =R59-Q59 -> 225000 | U59: AJU : 004961
O60: Materai 4 Pcs | Q60: 0 | R60: 48000 | S60: =R60*2/100 -> 960 | T60: =R60-Q60 -> 48000
O61: PIB EDI | Q61: 100000 | R61: 300000 | S61: =R61*2/100 -> 6000 | T61: =R61-Q61 -> 200000
O62: Trucking Dadap | P62: Hanabi | Q62: 1500000 | R62: 1900000 | S62: =R62*2/100 -> 38000 | T62: =R62-Q62 -> 400000
O63: Refund Dewi | P63: BCA Dewi | Q63: 150000 | R63: 0 | S63: =R63*2/100 -> 0 | T63: =R63-Q63 -> -150000
O64: Debit Note
O65: Lift Of / Lift On | P65: Hanabi | Q65: 699500 | R65: 699500 | S65: 0 | T65: =R65-Q65 -> 0
O66: Storage NPCT1 | P66: Ewilog | Q66: 512921 | R66: 512921 | S66: 0 | T66: =R66-Q66 -> 0
O67: Do Charges | P67: Ewilog | Q67: 1849291 | R67: 1849291 | S67: 0 | T67: =R67-Q67 -> 0
O68: Biaya Bongkar | P68: Hanabi | Q68: 150000 | R68: 150000 | S68: 0 | T68: =R68-Q68 -> 0
O69: Total | Q69: =SUM(Q59:Q68) -> 5086712 | R69: =SUM(R59:R68) -> 5809712 | S69: =SUM(S59:S68) -> 51960 | T69: =SUM(T59:T68) -> 723000
R70: =R69-S69 -> 5757752 | T70: =T69-S69 -> 671040
R72: Total Buying
R73: Total Selling
R74: Total Pph 2%
R75: Total Profit Sementara

Sheet PIUTANG LIST
A1: PIUTANG LIST CUSTOMER EWILOG
A2: No. | B2: Customer | C2: SO Order Number | D2: BL No | E2: Shipment | F2: Invoice / DN No | G2: Buying | H2: Nominal INV | I2: Nominal DN | J2: Pot PPH | K2: Total Transfer | L2: Profit | M2: Tgl Jth Tempo | N2: Tgl Payment
A3: Bulan : OKTOBER 2023
A4: 1 | B4: PT Citra Jaya Hosindo | C4: SO2310-001 | D4: ONEYTA3DK7430300 | E4: Import CC & Truck | F4: EWL2310-001/R | G4: 4766816 | H4: 2975000 | I4: 3079616 | J4: 0 | K4: =H4+I4 -> 6054616 | L4: =H4+I4-J4-G4 -> 1287800 | M4: 45611 | N4: 45611 | O4: Lunas | P4: -
A5: 2 | B5: PT Citra Perdana Putra | C5: SO2310-002 | D5: MAEU273487610 | E5: Import CC & Truck | F5: EWL2311-002/R | G5: 25141601 | H5: 7935000 | I5: 20901601 | J5: 0 | K5: =H5+I5 -> 28836601 | L5: =H5+I5-J5-G5 -> 3695000 | M5: 45643 | N5: 45295 | O5: Lunas | P5: Total Transfer IDR 31.380.652
E6: Over Payment | F6: EWL2311-002/R/1 | G6: 2544051 | H6: 0 | I6: 2544051 | J6: 0 | K6: =H6+I6 -> 2544051 | L6: =H6+I6-J6-G6 -> 0 | M6: 45643 | N6: 45295 | O6: Lunas | P6: Total Transfer IDR 31.380.652
A7: 3 | B7: PT Bepahkupi Global Ekspor | C7: SO2310-003 | D7: 126-88894481 | E7: Import AF Exw | F7: EWL2310-003 | G7: 7128145 | H7: 17839800 | I7: 0 | J7: 0 | K7: =H7+I7 -> 17839800 | L7: =H7+I7-J7-G7 -> 10711655 | M7: 45581 | N7: 45581 | O7: Lunas | P7: -
A8: 4 | B8: PT Citra Perdana Putra | C8: SO2310-004 | D8: MAEU273487613 | E8: Import CC & Truck | F8: EWL2310-004/R | G8: 7559698 | H8: 2860000 | I8: 5455698 | J8: 0 | K8: =H8+I8 -> 8315698 | L8: =H8+I8-J8-G8 -> 756000 | M8: 45620 | N8: 45306 | O8: Lunas | P8: Total Transfer IDR 14.125.410
A9: 5 | B9: PT Citra Perdana Putra | C9: SO2310-005 | D9: MAEU273487791 | E9: Import CC & Truck | F9: EWL2310-005/R | G9: 5136712 | H9: 2598000 | I9: 3211712 | J9: 0 | K9: =H9+I9 -> 5809712 | L9: =H9+I9-J9-G9 -> 673000 | M9: 45303 | N9: 45306 | O9: Lunas | P9: Total Transfer IDR 14.125.410
A10: SUBTOTAL | H10: =SUM(H4:H9) -> 34207800 | L10: =SUM(L4:L9) -> 17123455
A11: Bulan : NOVEMBER 2023
A12: 1 | B12: PT Agata Promar | C12: SO2311-001 | D12: OOLU2300926930 | E12: Import OF, CC & Truck | F12: EWL2311-007/R | G12: 15765647 | H12: 16410575 | I12: 5849472 | J12: 0 | K12: =H12+I12 -> 22260047 | L12: =H12+I12-J12-G12 -> 6494400 | M12: 45653 | N12: 45627 | O12: Lunas | P12: -
A13: 2 | B13: PT Dolphin Food & Beverages | C13: SO2311-002 | D13: MEDUIE724659 | E13: Export CC & Truck | F13: EWL2311-001 | G13: 3354238 | H13: 3700000 | I13: 0 | J13: =H13*2/100 -> 74000 | K13: =H13+I13 -> 3700000 | L13: =H13+I13-J13-G13 -> 271762 | M13: 45623 | N13: 45625 | O13: Lunas | P13: -
A14: 3 | B14: PT Exodus International | C14: SO2311-003 | D14: OOLU2143333180 | E14: Import Truck Only | F14: EWL2311-003 | G14: 2337100 | H14: 2627100 | I14: 0 | J14: 0 | K14: =H14+I14 -> 2627100 | L14: =H14+I14-J14-G14 -> 290000 | M14: 45623 | N14: 45623 | O14: Lunas | P14: -
A15: SUBTOTAL | H15: =SUM(H12:H14) -> 22737675 | J15: =SUM(J12:J14) -> 74000 | L15: =SUM(L12:L14) -> 7056162
A16: Bulan : DESEMBER 2023
A17: 1 | B17: PT Citra Perdana Putra | C17: SO2311-004 | D17: SITGTXDR451950 | E17: Import CC & Truck | F17: EWL2311-004/R | G17: 37077496 | H17: 14010000 | I17: 27497496 | J17: 0 | K17: =H17+I17 -> 41507496 | L17: =H17+I17-J17-G17 -> 4430000 | M17: 45309 | N17: 45351 | O17: Lunas | P17: Total Transfer IDR 165,873,825
A18: 2 | B18: PT Citra Perdana Putra | C18: SO2311-005 | D18: MAEU273769814 | E18: Import CC & Truck | F18: EWL2311-005/R | G18: 5416900 | H18: 2798000 | I18: 3741910 | J18: 0 | K18: =H18+I18 -> 6539910 | L18: =H18+I18-J18-G18 -> 1123010 | M18: 45309 | N18: 45370 | O18: Lunas | P18: Total Transfer IDR 111.277.296
A19: 3 | B19: PT Citra Perdana Putra | C19: SO2311-006 | D19: SITGTXDR451692 | E19: Import CC & Truck | F19: EWL2311-006/R | G19: 39270634 | H19: 14010000 | I19: 29690634 | J19: 0 | K19: =H19+I19 -> 43700634 | L19: =H19+I19-J19-G19 -> 4430000 | M19: 45309 | N19: 45351 | O19: Lunas | P19: Total Transfer IDR 165,873,825
A20: 4 | B20: PT Fecalindo Dinamika Intiprima | C20: SO2312-001 | D20: CTLTDD0000223979 | E20: Import CC & Truck | F20: EWL2312001/R | G20: 17533812 | H20: 15900000 | I20: 10428953 | J20: 0 | K20: =H20+I20 -> 26328953 | L20: =H20+I20-J20-G20 -> 8795141 | M20: 45301 | N20: 45308 | O20: Lunas | P20: -
A21: 5 | B21: PT Citra Perdana Putra | C21: SO2312-002 | D21: MAEU273769710 | E21: Import CC & Truck | F21: EWL2312-002/R | G21: 9555011 | H21: 4960000 | I21: 6020011 | J21: 0 | K21: =H21+I21 -> 10980011 | L21: =H21+I21-J21-G21 -> 1425000 | M21: 45309 | N21: 45335 | O21: Lunas | P21: Total Transfer IDR 48.527.501
A22: 6 | B22: PT Citra Perdana Putra | C22: SO2312-003 | D22: MAEU232500561 | E22: Import CC & Truck | F22: EWL2312003/R | G22: 3395940 | H22: 11298000 | I22: 26249490 | J22: 0 | K22: =H22+I22 -> 37547490 | L22: =H22+I22-J22-G22 -> 34151550 | M22: 45332 | N22: 45335 | O22: Lunas | P22: Total Transfer IDR 48.527.501
A23: 7 | B23: PT Citra Perdana Putra | C23: SO2312-004 | D23: HLCUTS12310AVTM1 | E23: Import CC & Truck | F23: EWL2312004/R | G23: 10162087 | H23: 8155000 | I23: 6918537 | J23: 0 | K23: =H23+I23 -> 15073537 | L23: =H23+I23-J23-G23 -> 4911450 | M23: 45319 | N23: 45370 | O23: Lunas | P23: Total Transfer IDR 111.277.296
A24: 8 | B24: PT Quanterm Logistindo | C24: SO2312-005 | D24: JKTD89721500 | E24: Export Truck Only | F24: EWL2312-005/A | G24: 12500000 | H24: 17120000 | I24: 0 | J24: 0 | K24: =H24+I24 -> 17120000 | L24: =H24+I24-J24-G24 -> 4620000 | M24: 45631 | N24: 45631 | O24: Lunas | P24: -
A25: 9 | B25: PT Dolphin Food & Beverages | C25: SO2312-006 | D25: JKT2312288 | E25: Export CC & Truck | F25: EWL2312-006 | G25: 3344448 | H25: 3700000 | I25: 0 | J25: =H25*2/100 -> 74000 | K25: =H25+I25 -> 3700000 | L25: =H25+I25-J25-G25 -> 281552 | M25: 45292 | N25: 45293 | O25: Lunas | P25: -
A26: 10 | B26: PT Primaplast Indonesia | C26: SO2312-007 | D26: AA23120517 | E26: Export AF & Custom | F26: EWL2312-007/R | G26: 18349549 | H26: 35380500 | I26: 2176524 | J26: =H26*2/100 -> 707610 | K26: =H26+I26 -> 37557024 | L26: =H26+I26-J26-G26 -> 18499865 | M26: 45313 | N26: 45366 | O26: Lunas | P26: Dibayar Tg 15 Mar 24 INV Only 34.673.890 Sisa DN 2.176.524 4/4/24
A27: 11 | B27: PT Citra Perdana Putra | C27: SO2312-008 | D27: MAEU273769960 | E27: Import CC & Truck | F27: EWL2312-008/R | G27: 64433695 | H27: 35497000 | I27: 45168695 | J27: 0 | K27: =H27+I27 -> 80665695 | L27: =H27+I27-J27-G27 -> 16232000 | M27: 45315 | N27: 45351 | O27: Lunas | P27: Total Transfer IDR 165,873,825
A28: 12 | B28: PT Citra Perdana Putra | C28: SO2312-009 | D28: MAEU273769961 | E28: Import CC & Truck | F28: EWL2312-009/R | G28: 30709348 | H28: 18397000 | I28: 22739348 | J28: 0 | K28: =H28+I28 -> 41136348 | L28: =H28+I28-J28-G28 -> 10427000 | M28: 45315 | N28: 45370 | O28: Lunas | P28: Total Transfer IDR 111.277.296
A29: 13 | B29: PT Obor Indonesia Pratama | C29: SO2312-010 | D29: BTG2302127200012 | E29: Import CC & Truck | F29: EWL2312-010 | G29: 1100000 | H29: 1350000 | I29: 0 | J29: 0 | K29: =H29+I29 -> 1350000 | L29: =H29+I29-J29-G29 -> 250000 | M29: 45334 | N29: lunas | O29: Lunas | P29: -
A30: SUBTOTAL | H30: =SUM(H17:H29) -> 182575500 | I30: =SUM(I17:I29) -> 180631598 | J30: =SUM(J17:J29) -> 781610 | L30: =SUM(L17:L29) -> 109576568
A31: Bulan : JANUARI 2024
A32: 1 | B32: PT Kay Ocean Indonesia | C32: SO2401-001 | D32: KMTCTAO7183485013 | E32: Trucking Only | F32: EWL2401-001 | G32: 810000 | H32: 1250000 | I32: 0 | J32: 0 | K32: =H32+I32 -> 1250000 | L32: =H32+I32-J32-G32 -> 440000 | M32: 45296 | N32: 45310 | O32: Lunas | P32: -
A33: 2 | B33: PT Citra Perdana Putra | C33: SO2401-002 | D33: MAEU273770258 | E33: Import CC & Truck | F33: EWL2401-002/R | G33: 19991656 | H33: 8360000 | I33: 14921656 | J33: 0 | K33: =H33+I33 -> 23281656 | L33: =H33+I33-J33-G33 -> 3290000 | M33: 45348 | N33: 45370 | O33: Lunas | P33: Total Transfer IDR 111.277.296
A34: 3 | B34: PT Citra Perdana Putra | C34: SO2401-003 | D34: MAEU273770257 | E34: Import CC & Truck | F34: EWL2401003/R | G34: 10028528 | H34: 4610000 | I34: 6978528 | J34: 0 | K34: =H34+I34 -> 11588528 | L34: =H34+I34-J34-G34 -> 1560000 | M34: 45348 | N34: 45370 | O34: Lunas | P34: Total Transfer IDR 111.277.296
A35: 4 | B35: PT Citra Perdana Putra | C35: SO2401-004 | D35: MAEU273770361 | E35: Import CC & Truck | F35: EWL2401004/R | G35: 5419044 | H35: 2710000 | I35: 3619044 | J35: 0 | K35: =H35+I35 -> 6329044 | L35: =H35+I35-J35-G35 -> 910000 | M35: 45348 | N35: 45370 | O35: Lunas | P35: Total Transfer IDR 111.277.296
A36: 5 | B36: PT Citra Perdana Putra | C36: SO2401-005 | D36: MAEU273770260 | E36: Import CC & Truck | F36: EWL2401005/R | G36: 12926250 | H36: 9860000 | I36: 7325788 | J36: 0 | K36: =H36+I36 -> 17185788 | L36: =H36+I36-J36-G36 -> 4259538 | M36: 45339 | N36: 45378 | O36: Lunas | P36: Total Transfer IDR 85.842.894
A37: 6 | B37: PT Citra Perdana Putra | C37: SO2401-006 | D37: MAEU273770259 | E37: Import CC & Truck | F37: EWL2401006/R | G37: 6491750 | H37: 6160000 | I37: 2876679 | J37: 0 | K37: =H37+I37 -> 9036679 | L37: =H37+I37-J37-G37 -> 2544929 | M37: 45338 | N37: 19-27/Mar/2024 | P37: Total Transfer IDR 111.277.296 (6.160.000 + 1.168.273) Total 7.328.273 Sisa 1.708.406 di tf Tgl 27/3/24 Total Transfer 85.842.894
A38: 7 | B38: PT Citra Perdana Putra | C38: SO2401-007 | D38: MAEU273770256 | E38: Import CC & Truck | F38: EWL2401007/R | G38: 10561015 | H38: 12210000 | I38: 7446060 | J38: 0 | K38: =H38+I38 -> 19656060 | L38: =H38+I38-J38-G38 -> 9095045 | M38: 45337 | N38: 45378 | O38: Lunas | P38: Total Transfer IDR 85.842.894
A39: 8 | B39: PT Dolphin Food & Beverages | C39: SO2401-008 | D39: 235172273 | E39: Export CC & Truck | F39: EWL2401008 | G39: 3573000 | H39: 3700000 | I39: 0 | J39: =H39*2/100 -> 74000 | K39: =H39+I39 -> 3700000 | L39: =H39+I39-J39-G39 -> 53000 | M39: 45302 | N39: 45317 | O39: Lunas | P39: -
A40: 9 | B40: PT Cahaya Nuansa Samudera | C40: SO2401-009 | D40: EGLV148300368978 | E40: Import CC & Truck | F40: EWL2401-009 | G40: 9610000 | H40: 17038000 | I40: 0 | J40: 0 | K40: =H40+I40 -> 17038000 | L40: =H40+I40-J40-G40 -> 7428000 | M40: 45316 | N40: 45317 | O40: Lunas | P40: -
A41: 10 | B41: PT Quanterm Logistindo | C41: SO2401-010 | D41: EBKG07727040 | E41: Trucking Only | F41: EWL2401010/R | G41: 3200000 | H41: 4150000 | I41: 50000 | J41: =H41*2/100 -> 83000 | K41: =H41+I41 -> 4200000 | L41: =H41+I41-J41-G41 -> 917000 | M41: 45330 | N41: 45364 | O41: Lunas | P41: -
A42: 11 | B42: PT Quanterm Logistindo | C42: SO2401-011 | D42: EBKG07781117 | E42: Export CC & Truck | F42: EWL2401011/R | G42: 9041314 | H42: 5256000 | I42: 5231314 | J42: =H42*2/100 -> 105120 | K42: =H42+I42 -> 10487314 | L42: =H42+I42-J42-G42 -> 1340880 | M42: 45330 | N42: 45364 | O42: Lunas | P42: -
A43: 12 | B43: PT Obor Indonesia Pratama | C43: SO2401-012 | D43: BTG2405121200029 | E43: Domestik Truck Only | F43: EWL2401012 | G43: 1050000 | H43: 1250000 | I43: 0 | J43: 0 | K43: =H43+I43 -> 1250000 | L43: =H43+I43-J43-G43 -> 200000 | M43: 45316 | N43: 45352 | O43: Lunas | P43: -
A44: 13 | B44: CV Elmaro | C44: SO2401-013 | D44: COAU7247361710 | E44: Import OF, CC & Truck | F44: EWL2401013/R | G44: 25723089 | H44: 20174000 | I44: 12565089 | J44: =H44*2/100 -> 403480 | K44: =H44+I44 -> 32739089 | L44: =H44+I44-J44-G44 -> 6612520 | M44: 45323 | N44: 45357 | O44: Lunas | P44: -
A45: SUBTOTAL | H45: =SUM(H32:H42) -> 75304000 | J45: =SUM(J40:J42) -> 188120 | L45: =SUM(L32:L44) -> 38650912
A46: Bulan : FEBRUARI 2024
A47: 1 | B47: PT Citra Perdana Putra | C47: SO2402-001 | D47: 999-04122403 | E47: Import CC & Truck | F47: EWL2402001 | G47: 6268188 | H47: 5132500 | I47: 5445188 | J47: 0 | K47: =H47+I47 -> 10577688 | L47: =H47+I47-J47-G47 -> 4309500 | M47: 45356 | N47: 45432 | O47: Lunas | P47: Total Transfer IDR 58.185.303
A48: 2 | B48: PT Obor Indonesia Pratama | C48: SO2402-002 | D48: 049EX01294 | E48: Trucking Only | F48: EWL2402002 | G48: 1100000 | H48: 1250000 | I48: 0 | J48: 0 | K48: =H48+I48 -> 1250000 | L48: =H48+I48-J48-G48 -> 150000 | M48: 45342 | N48: 45352 | O48: Lunas | P48: -
A49: 3 | B49: PT Obor Indonesia Pratama | C49: SO2402-003 | D49: 049EX01293 | E49: Trucking Only | F49: EWL2402003 | G49: 3300000 | H49: 3750000 | I49: 0 | J49: 0 | K49: =H49+I49 -> 3750000 | L49: =H49+I49-J49-G49 -> 450000 | M49: 45342 | N49: 45352 | O49: Lunas | P49: -
A50: 4 | B50: PT Citra Perdana Putra | C50: SO2402-004 | D50: MAEU273770653 | E50: Import CC & Truck | F50: EWL2402004 | G50: 14683350 | H50: 6136000 | I50: 13877452 | J50: 0 | K50: =H50+I50 -> 20013452 | L50: =H50+I50-J50-G50 -> 5330102 | M50: 45357 | N50: 45378 | O50: Lunas | P50: Total Transfer IDR 85.842.894
A51: 5 | B51: PT Obor Indonesia Pratama | C51: SO2402-005 | D51: BTG2402127400021 | E51: Trucking Only | F51: EWL2402005 | G51: 1100000 | H51: 1250000 | I51: 0 | J51: 0 | K51: =H51+K46 -> 1250000 | L51: =H51+I51-J51-G51 -> 150000 | M51: 45343 | N51: 45352 | O51: Lunas | P51: -
A52: 6 | B52: PT Masaji Kargosentra Tama | C52: SO2402-006 | D52: 1 Unit Wingsbox | E52: Trucking Only | F52: EWL2402006 | G52: 2210000 | H52: 2856000 | I52: 0 | J52: 0 | K52: =H52+I52 -> 2856000 | L52: =H52+I52-J52-G52 -> 646000 | M52: 45343 | N52: 45400 | O52: Lunas | P52: -
A53: 7 | B53: PT Citra Perdana Putra | C53: SO2402-007 | D53: MAEU273770886 | E53: Import CC & Truck | F53: EWL2402007 | G53: 10457023 | H53: 8298000 | I53: 8277023 | J53: 0 | K53: =H53+I53 -> 16575023 | L53: =H53+I53-J53-G53 -> 6118000 | M53: 45396 | N53: 45432 | O53: Lunas | P53: Total Transfer IDR 58.185.303
A54: 8 | B54: PT Citra Perdana Putra | C54: SO2402-008 | D54: MAEU273770887 | E54: Import CC & Truck | F54: EWL2402008 | G54: 2844600 | H54: 2586000 | I54: 1255188 | J54: 0 | K54: =H54+I54 -> 3841188 | L54: =H54+I54-J54-G54 -> 996588 | M54: 45367 | N54: 45378 | O54: Lunas | P54: Total Transfer IDR 85.842.894
A55: 9 | B55: PT Citra Perdana Putra | C55: SO2402-009 | D55: MAEU273770814 | E55: Import CC & Truck | F55: EWL2402009 | G55: 5721100 | H55: 4786000 | I55: 2559216 | J55: 0 | K55: =H55+I55 -> 7345216 | L55: =H55+I55-J55-G55 -> 1624116 | M55: 45364 | N55: 45378 | O55: Lunas | P55: Total Transfer IDR 85.842.894
A56: 10 | B56: PT Citra Perdana Putra | C56: SO2402-010 | D56: MAEU273770821 | E56: Import CC & Truck | F56: EWL2402010 | G56: 12427200 | H56: 7986000 | I56: 8106784 | J56: 0 | K56: =H56+I56 -> 16092784 | L56: =H56+I56-J56-G56 -> 3665584 | M56: 45366 | N56: 45378 | O56: Lunas | P56: Total Transfer IDR 85.842.894
A57: 11 | B57: PT Abadi Jaya Unggul Logistik | C57: SO2402-011 | D57: SJ2402050/BO/101/ATU | E57: Trucking Only | F57: EWL2402011 | G57: 2510000 | H57: 3550000 | I57: 0 | J57: 0 | K57: =H57+I57 -> 3550000 | L57: =H57+I57-J57-G57 -> 1040000 | M57: 45338 | N57: 45339 | O57: Lunas | P57: -
A58: 12 | B58: PT Logisklik Gemilang Indonesia | C58: SO2402-012 | D58: HLCUDM2231212602 | E58: Trucking Only | F58: EWL2402012 | G58: 2455300 | H58: 3055300 | I58: 0 | J58: 0 | K58: =H58+I58 -> 3055300 | L58: =H58+I58-J58-G58 -> 600000 | M58: 45344 | N58: 45347 | O58: Lunas | P58: -
A59: 13 | B59: PT Logisklik Gemilang Indonesia | C59: SO2402-013 | D59: HLCUDM2231212584 | E59: Trucking Only | F59: EWL2402013 | G59: 4920600 | H59: 6110600 | I59: 0 | J59: 0 | K59: =H59+I59 -> 6110600 | L59: =H59+I59-J59-G59 -> 1190000 | M59: 45344 | N59: 45347 | O59: Lunas | P59: -
A60: 14 | B60: PT Satya Liprindo | C60: SO2402-014 | D60: MEJKT.10.01030800 | E60: Export AF | F60: EWL2402014 | G60: 1029300 | H60: 2663188 | I60: 1254226 | J60: 0 | K60: =H60+I60 -> 3917414 | L60: =H60+I60-J88-G60 -> 2888114 | M60: 45373 | N60: 45369 | O60: Lunas | P60: -
A61: 15 | B61: PT Citra Perdana Putra | C61: SO2402-015 | D61: MAEU273770977 | E61: Import CC & Truck | F61: EWL2402015/R | G61: 4248700 | H61: 4298000 | I61: 1744032 | J61: 0 | K61: =H61+I61 -> 6042032 | L61: =H61+I61-J61-G61 -> 1793332 | M61: 45383 | N61: 45432 | O61: Lunas | P61: Total Transfer IDR 58.185.303
A62: 16 | B62: PT Citra Perdana Putra | C62: SO2402-016 | D62: MAEU273770973 | E62: Import CC & Truck | F62: EWL2402016/R | G62: 21022750 | H62: 6448000 | I62: 18542560 | J62: 0 | K62: =H62+I62 -> 24990560 | L62: =H62+I62-J62-G62 -> 3967810 | M62: 45383 | N62: 45432 | O62: Lunas | P62: Total Transfer IDR 58.185.303
A63: 17 | B63: PT Dolphin Food & Beverages | C63: SO2402-017 | D63: ONEYJKTE14727700 | E63: Trucking Only | F63: EWL2402017 | G63: 3262258 | H63: 3700000 | I63: 0 | J63: 74000 | K63: =H63+I63 -> 3700000 | L63: =H63+I63-J63-G63 -> 363742 | M63: 45358 | N63: 45365 | O63: Lunas | P63: -
A64: SUBTOTAL | H64: =SUM(H47:H57) -> 47580500 | J64: =SUM(J55:J57) -> 0 | L64: =SUM(L47:L63) -> 35282888
A66: Bulan : MARET 2024
B67: PT Obor Indonesia Pratama | C67: SO2403-001 | D67: 049EX02306 | E67: Trucking Only | F67: EWL2403001 | G67: 2100000 | H67: 2500000 | I67: 0 | J67: 0 | K67: =H67+I67 -> 2500000 | L67: =H67+I67-J67-G67 -> 400000 | M67: 45379 | N67: 41724 | O67: Lunas | P67: Total Transfer IDR 5.900.000
B68: PT Obor Indonesia Pratama | C68: SO2403-002 | D68: KMTCSHAL839484 | E68: Trucking Only | F68: EWL2403002 | G68: 1600000 | H68: 3400000 | I68: 0 | J68: 0 | K68: =H68+I68 -> 3400000 | L68: =H68+I68-J68-G68 -> 1800000 | M68: 45379 | N68: 41724 | O68: Lunas | P68: Total Transfer IDR 5.900.000
B69: PT Obor Indonesia Pratama | C69: SO2403-003 | D69: 049EX02376 | E69: Trucking Only | F69: EWL2403003 | G69: 2100000 | H69: 2500000 | I69: 0 | J69: 0 | K69: =H69+I69 -> 2500000 | L69: =H69+I69-J69-G69 -> 400000 | M69: 45391 | N69: 45387 | O69: Lunas
B70: PT Citra Jaya Hosindo | C70: SO2403-004 | D70: WFLQDCJKT24037941 | E70: Import CC & Truck | F70: EWL2402004/R | G70: 6451616 | H70: 3275000 | I70: 4650116 | J70: 0 | K70: =H70+I70 -> 7925116 | L70: =H70+I70-J70-G70 -> 1473500 | M70: 45387 | N70: 45400 | O70: Lunas
B71: PT Satya Liprindo | C71: SO2403-005 | D71: 2024JTYK0063010 | E71: OF LCL | F71: EWL2403005 | G71: 1403879 | H71: 3016465.1 | I71: 1133721 | J71: 0 | K71: =H71+I71 -> 4150186.1 | L71: =H71+I71-J71-G71 -> 2746307.1 | M71: 45396 | N71: 45408 | O71: Lunas | P71: TITIP TAGIH DI DN
B72: PT Kay Ocean Indonesia | C72: SO2403-006 | D72: MAEU236742164 | E72: Trucking Only | F72: EWL2403006 | G72: 21200000 | H72: 27000000 | I72: 0 | J72: 0 | K72: =H72+I72 -> 27000000 | L72: =H72+I72-J72-G72 -> 5800000 | M72: 45391 | N72: 45387 | O72: Lunas
A73: SUBTOTAL | H73: =SUM(H67:H72) -> 41691465 | J73: =SUM(J67:J72) -> 0 | L73: =SUM(L67:L72) -> 12619807
A74: Bulan : APRIL 2024
B75: PT Quanterm Logistindo | C75: SO2404-001 | D75: EBKG08437598 | E75: Export CC & Truck | F75: EWL2404001 | G75: 3349938 | H75: 5987500 | I75: 0 | J75: 0 | K75: =H75+I75 -> 5987500 | L75: =H75+I75-J75-G75 -> 2637562 | M75: 45416 | N75: 45425 | O75: Lunas | P75: -
B76: PT Cimc Wetrans Indonesia | C76: SO2404-002 | D76: SNKO079240400022 | E76: Trucking Export Sby | F76: EWL2402002/R | G76: 3163610 | H76: 3900000 | I76: 1003610 | J76: 78000 | K76: =H76+I76 -> 4903610 | L76: =H76+I76-J76-G76 -> 1662000 | M76: 45384 | N76: 45387 | O76: Lunas
B77: PT Citra Perdana Putra | C77: SO2404-003 | D77: SITGTXDR473120 | E77: Import CC & Truck | F77: EWL2404003/R | G77: 5209006 | H77: 4410000 | I77: 3974006 | J77: 0 | K77: =H77+I77 -> 8384006 | L77: =H77+I77-J77-G77 -> 3175000 | M77: 45502 | N77: 45516 | O77: Lunas
B78: PT Citra Perdana Putra | C78: SO2404-004 | D78: SITGTXDR443121 | E78: Import CC & Truck | F78: EWL2404004 | G78: 14697028 | H78: 8310000 | I78: 12537028 | J78: 0 | K78: =H78+I78 -> 20847028 | L78: =H78+I78-J78-G78 -> 6150000 | M78: 45502 | N78: 45516 | O78: Lunas
B79: PT Citra Perdana Putra | C79: SO2404-005 | D79: SITGTXDR473123 | E79: Import CC & Truck | F79: EWL2404005 | G79: 10952766 | H79: 8310000 | I79: 8792766 | J79: 0 | K79: =H79+I79 -> 17102766 | L79: =H79+I79-J79-G79 -> 6150000 | M79: 45502 | N79: 45516 | O79: Lunas
B80: PT Kay Ocean Indonesia | C80: SO2404-006 | D80: MAEU237217560 | E80: Trucking Only | F80: EWL2404006 | G80: 13180000 | H80: 16750000 | I80: 0 | J80: 0 | K80: =H80+I80 -> 16750000 | L80: =H80+I80-J80-G80 -> 3570000 | M80: 45414 | N80: 45423 | O80: Lunas
A81: SUBTOTAL | H81: =SUM(H76:H80) -> 41680000 | J81: =SUM(J78:J79) -> 0 | L81: =SUM(L75:L80) -> 23344562
A82: Bulan : May 2024
B83: PT Obor Indonesia Pratama | C83: SO2405-001 | D83: CXCOSHA2067665 | E83: Import Trucking & Storage PMP | F83: EWL2405001 | G83: 5960990 | H83: 10730000 | I83: 675990 | J83: 0 | K83: =H83+I83 -> 11405990 | L83: =H83+I83-J83-G83 -> 5445000 | M83: 45436 | N83: 45468 | O83: Lunas | P83: TF TGL 25/6/24 IDR 11.405.990 KURANG BAYAR SEWA HARIAN
B84: PT Alvio Victori | C84: SO2405-002 | D84: DOMESTIK | E84: Trucking Only | F84: EWL2405002 | G84: 2419000 | H84: 3000000 | I84: 0 | J84: 0 | K84: =H84+I84 -> 3000000 | L84: =H84+I84-J84-G84 -> 581000 | M84: 45414 | N84: 45416 | O84: Lunas
B85: PT Citra Perdana Putra | C85: SO2405-003 | D85: COAU7244244850 | E85: Import CC & Truck | F85: EWL2405003 | G85: 16730296 | H85: 4710000 | I85: 13746196 | J85: 0 | K85: =H85+I85 -> 18456196 | L85: =H85+I85-J85-G85 -> 1725900 | M85: 45476 | N85: 45516 | O85: Lunas
B86: PT Citra Perdana Putra | C86: SO2405-004 | D86: SITGTXJT479446 | E86: Import CC & Truck | F86: EWL2405004 | G86: 12572997 | H86: 3010000 | I86: 10430497 | J86: 0 | K86: =H86+I86 -> 13440497 | L86: =H86+I86-J86-G86 -> 867500 | M86: 46558 | N86: 45516 | O86: Lunas
B87: PT Inside Development Group | C87: SO2405-005 | D87: 71241021018042 | E87: Handling Custom | F87: EWL2405005/A | G87: 69653860 | H87: 106313860 | I87: 0 | J87: 0 | K87: =H87+I87 -> 106313860 | L87: =H87+I87-J87-G87 -> 36660000 | M87: 45417 | N87: 45428 | O87: Lunas
B88: PT Mas Mewah / Traclineoo | C88: SO2405-006 | D88: MCLPKG24002370 | E88: Trucking & SP2 | F88: EWL2405006 | G88: 3735000 | H88: 7100000 | I88: 0 | J88: 0 | K88: =H88+I88-J88 -> 7100000 | L88: =H88+I88-J88-G88 -> 3365000 | M88: 45433 | N88: 45470 | O88: Lunas
B89: CV Persada Indah Mandiri | C89: SO2405-007 | D89: DOMESTIK | E89: Trucking Only | F89: EWL2405007 | G89: 2900000 | H89: 4400000 | I89: 0 | J89: 0 | K89: =H89+I89-J89 -> 4400000 | L89: =H89+I89-J89-G89 -> 1500000 | M89: 45434 | N89: 45434 | O89: Lunas
B90: PT Dolphin Food & Beverages | C90: SO2405-008 | D90: JKT400199200 | E90: Tucking & Export Custome | F90: EWL2405008 | G90: 3144819 | H90: 3400000 | I90: 0 | J90: 0 | K90: =H90+I90-J90 -> 3400000 | L90: =H90+I90-J90-G90 -> 255181 | M90: 45440 | N90: 45462 | O90: Lunas
A91: SUBTOTAL | J91: =SUM(J86:J87) -> 0 | K91: =K77+K78+K79+K83+K85+K86+K88+K90 -> 100136483 | L91: =SUM(L83:L90) -> 50399581
A92: Bulan : Juni 2024
B93: PT GPI Logistics TBK | C93: SO2406-001 | D93: 160-78464794 | E93: Import Trucking Udara | F93: EWL2406001 | G93: 5558000 | H93: 7600000 | I93: 0 | J93: 0 | K93: =H93+I93 -> 7600000 | L93: =H93+I93-J93-G93 -> 2042000 | M93: 45469 | N93: 45478 | O93: Lunas
B94: PT Obor Indonesia Pratama | C94: SO2406-002 | D94: COAU7249231570 | E94: Import Trucking Cileungsi | F94: EWL2406002 | G94: 2360450 | H94: 3100000 | I94: 660450 | J94: 0 | K94: =H94+I94 -> 3760450 | L94: =H94+I94-J94-G94 -> 1400000 | M94: 45464 | N94: 45481 | O94: Lunas
B95: PT Dolphin Food & Beverages | C95: SO2406-003 | D95: JKTE64277500 | E95: Tucking & Export Custome | F95: EWL2406003 | G95: 3180755 | H95: 3700000 | I95: 0 | J95: 0 | K95: =H95+I95-J95 -> 3700000 | L95: =H95+I95-J95-G95 -> 519245 | M95: 45483 | N95: 45481 | O95: Lunas
B96: PT GPI Logistics TBK | C96: SO2406-004 | D96: HASLC01240511230 | E96: Import Trucking 3X20 Karawang | F96: EWL2406004 | G96: 8887720 | H96: 6150000 | I96: 3456970 | J96: 0 | K96: =H96+I96 -> 9606970 | L96: =H96+I96-J96-G96 -> 719250 | M96: 45464 | N96: 45478 | O96: Lunas
B97: PT Efata Tekhnik | C97: SO2406-005 | D97: 06/SJP/SS-PJM/V/2024 | E97: Domestik Truck Only | F97: EWL2406005 | G97: 1000000 | H97: 15500000 | I97: 0 | J97: 0 | K97: =H97+I97-J97 -> 15500000 | L97: =H97+I97-J97-G97 -> 14500000 | M97: 45472 | N97: 45472 | O97: Lunas
A98: SUBTOTAL | H98: =SUM(H94:H97) -> 28450000 | J98: =SUM(J96:J97) -> 0 | K98: =SUM(K93:K97) -> 40167420 | L98: =SUM(L93:L97) -> 19180495
A99: Bulan : Juli 2024
A100: No. | B100: Customer | C100: SO Order Number | D100: BL No | E100: Shipment | F100: Invoice / DN No | G100: Buying | H100: Nominal INV | I100: Nominal DN | J100: Pot PPH | K100: Total Transfer | L100: Profit | M100: Tgl Jth Tempo | N100: Tgl Payment
B101: PT Obor Indonesia Pratama | C101: SO2405-001 | D101: CXCOSHA2067665 | E101: Penitipan Gudang | F101: EWL2405001 | G101: 7504091 | H101: 14481410 | I101: 0 | J101: 0 | K101: =H101+I101 -> 14481410 | L101: =H101+I101-J101-G101 -> 6977319 | M101: 45509 | N101: 45516 | O101: Profit July | P101: Lunas
...

Sheet TEST
B5: {=SHIPMENT!#REF!} -> #REF!

Sheet HUTANG LIST
A1: HUTANG LIST VENDOR
A2: No. | B2: Vendor Name | C2: Deskripsi | D2: No Rekening | E2: Atas Nama | F2: SO Number | G2: Adm TF bank | H2: Nominal Inv | I2: Tgl Terima Inv | J2: Tgl Jth Tempo | K2: Tgl Payment | L2: Remark
A3: Bulan : OKTOBER 2023
A4: Bulan : NOVEMBER 2023
A5: 1 | B5: PT Hanabi Shigara Niapi | C5: Trucking CPP Dadap 1x20GP | D5: BTN 001601560012451 | E5: Julia Purba | F5: SO2310-004 | G5: 0 | H5: 2349500 | I5: 45233 | J5: 45247 | K5: 45247 | L5: Lunas
A6: 2 | B6: PT Kaka Translink International | C6: PIB, Handling & DO fee | D6: BCA 1640677763 | E6: Sugeng Prihanto | F6: SO2310-001/004/005 | G6: 2500 | H6: 925000 | I6: 45235 | J6: 45249 | K6: 45246 | L6: Lunas
A7: 3 | B7: PT Patogar Jaya Trans | C7: Trucking CPP & CJH 2x20Gp | D7: BCA 5212057339 | E7: Nurlela Siagian | F7: SO2310-001/005 | G7: 0 | H7: 4901400 | I7: 45235 | J7: 45249 | K7: 45246 | L7: Lunas
A8: 4 | B8: Mustika Rohmah | C8: Talangan Tf Pak Udi, Paket Data Eshaka, Pak Budi | D8: Mandiri 1180011240776 | E8: Mustika Rohmah | F8: SO2311-001 | G8: 0 | H8: 2515800 | I8: 45259 | J8: 45260 | K8: 45260 | L8: Lunas | M8: Tf Via Mustika
A9: 5 | B9: PT Maju Jaya Transport | C9: Trucking Exodus 1x20gp Legok | D9: BCA 6300158089 | E9: Tuti Hendayani | F9: SO2311-003 | G9: 0 | H9: 2327100 | I9: 45259 | J9: 45260 | K9: 45260 | L9: Lunas
A10: Bulan : DESEMBER 2023
A11: 1 | B11: PT Hanabi Shigara Niapi | C11: Trucking 1x40HQ Dolphin Cikupa | D11: BCA 4142299368 | E11: Kopindo Siregar | F11: SO2311-002 | G11: 0 | H11: 1600000 | I11: 45251 | J11: 45266 | K11: 45266 | L11: Lunas
A12: 2 | B12: Win Share Supply Chain | C12: OF Agata 1X40HQ Shenzhen | D12: HSBC 149352445838 | E12: Win Share Supply Chain (HK) Co., Limited | F12: SO2311-001 | G12: 60000 | H12: 7946175 | I12: 45246 | J12: 45276 | K12: 45273 | L12: Lunas
A13: 3 | B13: PT Samudera Perdana Selaras | C13: PIB, Handling, Trucking & DO fee CPP SO2310-002 | D13: BCA 8035008566 | E13: PT Samudera Perdana Selaras | F13: SO2310-002 | G13: 0 | H13: 25051601 | I13: 45247 | J13: 45277 | K13: 45277 | L13: Lunas
A14: 4 | B14: Mustika Rohmah | C14: Talangan Byr DO Maerskline CPP SO2310-002/2311-005 | D14: Mandiri 1180011240776 | E14: Mustika Rohmah | F14: SO2311-005 | G14: 0 | H14: 4357379 | I14: 45264 | J14: 45264 | K14: 45089 | L14: Lunas
A15: 5 | B15: PT Prasetya Mitra Persada | C15: Trucking 3X40RF PT Quanterm SO2313-005 | D15: Mandiri 1250013602719 | E15: PT Prasetya Mitra Persada | F15: SO2312-005 | G15: 0 | H15: 12500000 | I15: 45274 | J15: 45282 | K15: 22/12/2023 | L15: Lunas
A16: 6 | B16: PT Kaka Translink International | C16: PIB, Handling & DO fee CPP | D16: BCA 5510185091 | E16: Adam Iskandar | F16: SO2311-005/2312-002 | G16: 0 | H16: 550000 | I16: 45273 | J16: 45280 | K16: 20/12/2023 | L16: Lunas
A17: 7 | B17: PT Patogar Jaya Trans | C17: Trucking & Lolo CPP SO2311-005/ 2312-002 | D17: BCA 4142299368 | E17: Kopindo Siregar | F17: SO2311-005/2312-002 | G17: 0 | H17: 6798500 | I17: 45242 | J17: 45280 | K17: 22/12/2023 | L17: Lunas
A18: 8 | B18: Mustika Rohmah | C18: Talangan Dolphin Handling & Lolo SO2312-006 | D18: Mandiri 1180011240776 | E18: Mustika Rohmah | F18: SO2312-006 | G18: 0 | H18: 951500 | I18: 45280 | J18: 45282 | K18: 45295 | L18: Lunas
A19: 9 | B19: PT Samudera Perdana Selaras | C19: Handling, PIb & Trucking CPP | D19: BCA 8035008566 | E19: PT Samudera Perdana Selaras | F19: SO2312-003 | G19: 0 | H19: 33509490 | I19: 44935 | J19: 45331 | K19: 45342 | L19: Lunas
A20: Bulan : JANUARI 2024
A21: 1 | B21: Mustika Rohmah | C21: Talangan Dolphin Handling & Lolo SO2401-008 | D21: Mandiri 1180011240776 | E21: Mustika Rohmah | F21: SO2401-008 | G21: 0 | H21: 1060500 | I21: - | J21: - | K21: 45322 | L21: Lunas
A22: 2 | B22: PT Turangga Cahya Sinergi | C22: Tagihan Trucking Dolphin | D22: BCA 1662995724 | E22: David Budi Prasetyo | F22: SO2410-008 | G22: 0 | H22: 1750000 | I22: 45309 | J22: 45309 | K22: 45309 | L22: Lunas
A23: Bulan : FEBRUARI 2024
A24: 1 | B24: PT Prasetya Mitra Persada | C24: Trucking Quanterm Export 1X40RF | D24: Mandiri 1250013602719 | E24: PT Prasetya Mitra Persada | F24: SO2401-011 | G24: 0 | H24: 1800000 | I24: 45315 | J24: 45331 | K24: 45334 | L24: Lunas
A25: 2 | B25: PT Prasetya Mitra Persada | C25: Lolo Quanterm Export 1X40RF | D25: Mandiri 1250013602719 | E25: PT Prasetya Mitra Persada | F25: SO2401-011 | G25: 0 | H25: 999000 | I25: 45315 | J25: 45331 | K25: 45334 | L25: Lunas
A26: 3 | B26: PT Prasetya Mitra Persada | C26: Storage dan Handling Quanterm Export 1X40RF | D26: Mandiri 1250013602719 | E26: PT Prasetya Mitra Persada | F26: SO2401-011 | G26: 0 | H26: 4332314 | I26: 45315 | J26: 45331 | K26: 45334 | L26: Lunas
A27: 4 | B27: PT Prasetya Mitra Persada | C27: Trucking Quanterm Export 1X40RF | D27: Mandiri 1250013602719 | E27: PT Prasetya Mitra Persada | F27: SO2401-010 | G27: 0 | H27: 1800000 | I27: 45313 | J27: 45329 | K27: 45334 | L27: Lunas
A28: 5 | B28: John Najoan | C28: Trucking CPP Udara & Gate Pass Gapura | D28: Mandiri 1170006917017 | E28: John Najoan | F28: SO2402-001 | G28: 0 | H28: 480000 | I28: 45328 | J28: 45328 | K28: 45329 | L28: Lunas
A29: 6 | B29: John Najoan | C29: Trucking WB MKT Cikampek - Penjaringan | D29: Mandiri 1170006917017 | E29: John Najoan | F29: SO2402-006 | G29: 0 | H29: 2200000 | I29: 45328 | J29: 45328 | K29: 45329 | L29: Lunas
A30: 7 | B30: PT Patogar Jaya Trans | C30: Trucking Cakung Obor Domestik | D30: BCA 4142299368 | E30: Kopindo Siregar | F30: SO2401-012 | G30: 0 | H30: 1050000 | I30: 45322 | J30: 45331 | K30: 45342 | L30: Lunas
A31: 8 | B31: PT Samudera Perdana Selaras | C31: Handling PIB Trucking dan Custom | D31: BCA 8035008566 | E31: PT Samudera Perdana Selaras | F31: SO2401-007 | G31: 0 | H31: 10331060 | I31: 45324 | J31: 45353 | K31: 45363 | L31: Lunas
A32: 9 | B32: Mustika Rohmah | C32: Talangan Handling, DO, Refund Dewi, Ambil Tunai, Kuota Ewilog & Lolo Dolphin | D32: Mandiri 1180011240776 | E32: Mustika Rohmah | F32: SO2402-001/017/2401-2/3/4/5/6/7 | G32: 0 | H32: 4669000 | I32: 45323 | J32: 45352 | K32: 45353 | L32: Lunas
A33: 10 | B33: Win Share Supply Chain | C33: OF Elmaro Qingdao to JKT | D33: HSBC 149352445838 | E33: Win Share Supply Chain (HK) Co., Limited | F33: SO2401-013 | G33: 0 | H33: 8745500 | I33: 45316 | J33: 45347 | K33: 45358 | L33: Lunas
A34: 11 | B34: PT SAP Logistik | C34: Trucking PT Obor | D34: BCA 0070577321 | E34: Triwira Jaya Selaras | F34: SO2402-005 | G34: 0 | H34: 1100000 | I34: 45334 | J34: 45355 | K34: 45353 | L34: Lunas
A35: 12 | B35: PT Prasetya Mitra Persada | C35: Trucking Obor Export | D35: Mandiri 1250013602719 | E35: PT Prasetya Mitra Persada | F35: SO2402-002/003 | G35: 0 | H35: 4400000 | I35: 45334 | J35: 45355 | K35: 45358 | L35: Lunas
... A51: 28 | B51: PT Anugerah Tangkas Transportindo | C51: AF Export CGK to NGO Japan Primaplast | D51: Mandiri 1180011555553 | E51: PT Anugerah Tangkas Transportindo | F51: SO2312-007 | G51: 0 | H51: 17629545 | I51: 45299 | J51: 45330 | K51: 45353 | L51: Lunas
H52: =SUM(H32:H51) -> 282833171
A53: Bulan : MARCH 2024
A54: 1 | B54: PT Turangga Cahya Sinergi | C54: Trucking PT Dolphin | D54: BCA 1662995724 | E54: David Budi Prasetyo | F54: SO2402-017 | G54: 0 | H54: 1750000 | I54: 45356 | J54: 45370 | K54: 45365 | L54: Lunas
A55: 2 | B55: PT Abe Transindo Perkasa | C55: Handling, PIB & Trucking CPP SBY | D55: Mandiri 1400066028888 | E55: PT Abe Transindo Perkasa | F55: SO2402-009 | G55: 0 | H55: 2811100 | I55: 45356 | J55: 45387 | K55: 45387 | L55: Lunas
A56: 3 | B56: PT Abe Transindo Perkasa | C56: Handling PIB Trucking dan Custom CPP SBY | D56: Mandiri 1400066028888 | E56: PT Abe Transindo Perkasa | F56: SO2402-010 | G56: 0 | H56: 12157200 | I56: 45356 | J56: 45387 | K56: 45387 | L56: Lunas
A57: 4 | B57: PT Abe Transindo Perkasa | C57: Handling, PIB & Trucking CPP SBY | D57: Mandiri 1400066028888 | E57: PT Abe Transindo Perkasa | F57: SO2402-004 | G57: 0 | H57: 16384750 | I57: 45356 | J57: 45387 | K57: 45387 | L57: Lunas
A58: 5 | B58: PT Abe Transindo Perkasa | C58: Handling, PIB & Trucking CPP SBY | D58: Mandiri 1400066028888 | E58: PT Abe Transindo Perkasa | F58: SO2402-008 | G58: 0 | H58: 2762750 | I58: 45356 | J58: 45387 | K58: 45387 | L58: Lunas
A59: 6 | B59: PT Abe Transindo Perkasa | C59: Handling PIB Trucking dan Custom | D59: Mandiri 1400066028888 | E59: PT Abe Transindo Perkasa | F59: SO2402-015 | G59: 0 | H59: 4098700 | I59: 45359 | J59: 45390 | K59: 45387 | L59: Lunas
A60: 7 | B60: Mustika Rohmah | C60: Talangan Bayar Win Share Elmaro & Talangan | D60: Mandiri 1180011240776 | E60: Mustika Rohmah | F60: SO2401-013 | G60: 0 | H60: 1045500 | I60: 45381 | J60: 45382 | K60: 45387 | L60: Lunas
A61: 8 | B61: Asiah | C61: Talangan Bayar Win Share Elmaro & Talangan | D61: BCA | E61: Asiah | F61: SO2401-013 | G61: 0 | H61: 10750000 | I61: 45381 | J61: 45382 | K61: 45387 | L61: Lunas
A62: 9 | B62: PT Patogar Jaya Trans | C62: Trucking PT Obor | D62: BCA 4142299368 | E62: Kopindo Siregar | F62: SO2403-001 | G62: 0 | H62: 2100000 | I62: 45359 | J62: 45373 | K62: 45387 | L62: Lunas
A63: 10 | B63: PT Patogar Jaya Trans | C63: Trucking PT Obor | D63: BCA 4142299368 | E63: Kopindo Siregar | F63: SO2403-003 | G63: 0 | H63: 2100000 | I63: 45376 | J63: 45390
A64: 11 | B64: PT Samudera Perdana Selaras | C64: Handling PIB & Trucking Semarang CPP | D64: BCA 8035008566 | E64: PT Samudera Perdana Selaras | F64: SO2402-007 | G64: 0 | H64: 10287023 | I64: 45383 | J64: 45413 | K64: 45436 | L64: Lunas
A65: 12 | B65: PT Abe Transindo Perkasa | C65: Handling, PIB & Trucking CPP SBY | D65: Mandiri 1400066028888 | E65: PT Abe Transindo Perkasa | F65: SO2402-016 | G65: 0 | H65: 20802750 | I65: 45383 | J65: 45413 | K65: 45436 | L65: Lunas
A66: 13 | B66: PT Alia Duta Pertiwi | C66: Trucking Lowbed & Rework | D66: Mandiri 1350015102690 | E66: PT Alia Duta Pertiwi | F66: SO2403-006 | G66: 0 | H66: 20450000 | I66: 45383 | J66: 45389 | K66: 45387 | L66: Lunas
A67: 10 | B67: PT Patogar Jaya Trans | C67: Trucking PT CJH | D67: BCA 4142299368 | E67: Kopindo Siregar | F67: SO2403-004 | G67: 0 | H67: 1750000 | I67: 45384 | J67: 45398 | K67: 45387 | L67: Lunas
A68: Bulan : APRIL 2024
A69: 1 | B69: PT Swan Utama Logisik | C69: Trucking 1X20GP Rembang Pasuruan Export PT CIMC Wetrans | D69: BCA 4681433079 | E69: Suyin Andayani | F69: SO2404-002 | G69: 0 | H69: 1600000 | I69: 45403 | J69: 45413 | K69: 45415 | L69: Lunas
A70: 2 | B70: PT Patogar Jaya Trans | C70: Trucking PT Quanterm Logistindo | D70: BCA 4142299368 | E70: Kopindo Siregar | F70: SO2404-001 | G70: 0 | H70: 1900000 | I70: 45403 | J70: 45413 | K70: 45415 | L70: Lunas
A71: 3 | B71: PT Smart Genset Transcold | C71: Sewa Genset PT Quanterm Logistindo | D71: BCA 5681533835 | E71: Smart Genset Transcold | F71: SO2404-001 | G71: 0 | H71: 1400000 | I71: 45403 | J71: 45413 | K71: 45415 | L71: Lunas
A72: 4 | B72: PT Alia Duta Pertiwi | C72: Trucking Lowbed & Rework | D72: Mandiri 1350015102690 | E72: PT Alia Duta Pertiwi | F72: SO2404-006 | G72: 0 | H72: 11500000 | I72: 45403 | J72: 45414 | K72: 45415 | L72: Lunas
A73: Bulan : MAY 2024
B74: PT Rafindo Trans Mandiri | C74: Handling & PEB Export PT CIMC Wetrans | D74: Mandiri 1420099888579 | E74: PT Rafindo Trans Mandiri | F74: SO2404-002 | G74: 0 | H74: 1330110 | I74: 45421 | J74: 45428 | K74: 45436 | L74: Lunas
B75: PT Prasetya Mitra Persada | C75: Lift Off PT Obor Pratama Indonesia | D75: Mandiri 1250013602719 | E75: PT Prasetya Mitra Persada | F75: SO2405-001 | G75: 0 | H75: 675990 | I75: 45424 | J75: 45438 | K75: 45436 | L75: Lunas
B76: PT Prasetya Mitra Persada | C76: Trucking PT Obor Pratama Indonesia | D76: Mandiri 1250013602719 | E76: PT Prasetya Mitra Persada | F76: SO2405-001 | G76: 0 | H76: 1100000 | I76: 45424 | J76: 45438 | K76: 45436 | L76: Lunas
B77: PT Prasetya Mitra Persada | C77: Trucking PT Mas Mewah / Traclineoo | D77: Mandiri 1250013602719 | E77: PT Prasetya Mitra Persada | F77: SO2405-006 | G77: 0 | H77: 3400000 | I77: 45424 | J77: 45438 | K77: 45436 | L77: Lunas
B78: PT Prasetya Mitra Persada | C78: Lolo Adm PT Mas Mewah / Traclineoo | D78: Mandiri 1250013602719 | E78: PT Prasetya Mitra Persada | F78: SO2405-006 | G78: 0 | H78: 50000 | I78: 45424 | J78: 45438 | K78: 45436 | L78: Lunas
B79: PT Prasetya Mitra Persada | C79: Penitipan Gudang PT Obor Pratama Indonesia | D79: Mandiri 1250013602719 | E79: PT Prasetya Mitra Persada | F79: SO2405-001 | G79: 0 | H79: 3885000 | I79: 45424 | J79: 45438 | K79: 45436 | L79: Lunas
B80: PT Prasetya Mitra Persada | C80: TKBM Klasifikasi Gudang PT Obor Pratama Indonesia | D80: Mandiri 1250013602719 | E80: PT Prasetya Mitra Persada | F80: SO2405-001 | G80: 0 | H80: 300000 | I80: 45424 | J80: 45438 | K80: 45436 | L80: Lunas
B81: PT Widarta Pratama Mandiri | C81: Handling & PIB Custom PT Inside | D81: Panin 4132002742 | E81: PT Widarta Pratama Mandiri | F81: SO2405-005 | G81: 0 | H81: 2500000 | I81: 45434 | J81: 45436 | K81: 45436 | L81: Lunas
A82: Bulan : JUNI 2024
B83: PT SAP Logistik | C83: Trucking Dolphin | D83: BCA 0070577321 | E83: PT Triwira Jaya Selaras | F83: SO2405-008 | G83: 0 | H83: 1800000 | I83: 45467 | J83: 45470 | K83: 45483 | L83: Lunas
B84: PT Eksporindo Mitra Logistic | C84: Trucking dan Handling CPP Jakarta | D84: Mandiri 1200011577595 | E84: PT Eksporindo Mitra Logistic | F84: SO2405-004 | G84: 0 | H84: 891497 | I84: 45457 | J84: 45471 | K84: 45483 | L84: Lunas
B85: PT Maju Jaya Transport | C85: Trucking PT GPI 3x20 Karawang | D85: BCA 6300158089 | E85: Tuti Hendayani | F85: SO2406-004 | G85: 0 | H85: 8856970 | I85: 45468 | J85: 46577 | K85: 45483 | L85: Lunas
B86: PT Abe Transindo Perkasa | C86: Trucking dan Handling CPP Surabaya | D86: Mandiri 1400066028888 | E86: PT Abe Transindo Perkasa | F86: SO2405-003 | G86: 0 | H86: 16590296 | I86: 45467 | J86: 45497 | K86: 45520 | L86: Lunas
B87: PT Samudera Perdana Selaras | C87: Trucking dan Handling CPP Semarang | D87: BCA 8035008566 | E87: PT Samudera Perdana Selaras | F87: SO2404-004 | G87: 0 | H87: 14547028 | I87: 45467 | J87: 45497 | K87: 45520 | L87: Lunas
B88: PT Samudera Perdana Selaras | C88: Trucking dan Handling CPP Semarang | D88: BCA 8035008566 | E88: PT Samudera Perdana Selaras | F88: SO2404-003 | G88: 0 | H88: 5109006 | I88: 45467 | J88: 45497 | K88: 45520 | L88: Lunas
B89: PT Samudera Perdana Selaras | C89: Trucking dan Handling CPP Semarang | D89: BCA 8035008566 | E89: PT Samudera Perdana Selaras | F89: SO2404-005 | G89: 0 | H89: 10802766 | I89: 45467 | J89: 45497 | K89: 45520 | L89: Lunas
B90: PT Patogar Jaya Trans | C90: Trucking PT Dolphin & PT Obor | D90: BCA 4142299368 | E90: Kopindo Siregar | G90: 0 | H90: 4010450 | I90: 45470 | J90: 45481 | K90: 45483 | L90: Lunas
A91: Bulan : JULY 2024
B92: PT Eksporindo Mitra Logistic | C92: Handling & Trucking CPP Jakarta | D92: Mandiri 1200011577595 | E92: PT Eksporindo Mitra Logistic | F92: SO2407-007 | G92: 0 | H92: 3245404 | I92: 45489 | J92: 45502 | K92: 45502 | L92: Lunas
B93: PT Grha Saba Permana | C93: Handling & PIB Jakarana Tama | D93: BCA 5213888322 | E93: PT Grha Saba Permana | F93: SO2407-001 | G93: 0 | H93: 295000 | I93: 45488 | J93: 45502 | K93: 45502 | L93: Lunas
B94: PT Maju Jaya Transport | C94: Trucking PT GPI 1x20 Karawang | D94: BCA 6300158089 | E94: Tuti Hendayani | F94: SO2407-005 | G94: 0 | H94: 2554800 | I94: 46586 | J94: 45502 | K94: 45502 | L94: Lunas
B95: PT Patogar Jaya Trans | C95: Trucking PT Jakarana Tama | D95: BCA 4142299368 | E95: Kopindo Siregar | F95: SO2407-001 | G95: 0 | H95: 2725050 | I95: 45484 | J95: 45502 | K95: 45502 | L95: Lunas
B96: PT Saipan Prima Global | C96: PIB dan DO Fecalindo + JNE | D96: BCA 6900070851 | E96: Deni | F96: SO2407-003 | G96: 0 | H96: 310000 | I96: 45502 | J96: 45502 | K96: 45502 | L96: Lunas
A97: Bulan : AGUSTUS 2024
B98: PT Eksporindo Mitra Logistic | C98: Handling & Trucking CPP Jakarta | D98: Mandiri 1200011577595 | E98: PT Eksporindo Mitra Logistic | F98: SO2407-010 | G98: 0 | H98: 6202314 | I98: 45507 | J98: 45513 | K98: 45520 | L98: Lunas
B99: PT Patogar Jaya Trans | C99: Trucking PT Obor & Fecalindo | D99: BCA 4142299368 | E99: Kopindo Siregar | F99: SO2407-003/013/016 | G99: 0 | H99: 8217641 | I99: 45507 | J99: 45520 | K99: 45520 | L99: Lunas
B100: PT Prasetya Mitra Persada | C100: Penitipan Gudang PT Obor Pratama Indonesia | D100: Mandiri 1250013602719 | E100: PT Prasetya Mitra Persada | F100: SO2405-001 | G100: 0 | H100: 7504491 | I100: 45507 | J100: 45520 | K100: 45527 | L100: Lunas
B101: PT Prasetya Mitra Persada | C101: Trucking PT Dolphin Food & Beverages | D101: Mandiri 1250013602719 | E101: PT Prasetya Mitra Persada | F101: SO2407-017 | G101: 0 | H101: 1700000 | I101: 45517 | J101: 45531
B102: PT Samudera Perdana Selaras | C102: Trucking dan Handling Victory Semarang | D102: BCA 8035008566 | E102: PT Samudera Perdana Selaras | F102: SO2407-004 | G102: 0 | H102: 5554004 | I102: 45517 | J102: 45548
B103: PT Samudera Perdana Selaras | C103: Trucking dan Handling CPP Semarang | D103: BCA 8035008566 | E103: PT Samudera Perdana Selaras | F103: SO2407-008 | G103: 0 | H103: 12892553 | I103: 45517 | J103: 45548
B104: PT GMS | C104: trucking SLB ckr-cakung-soetta | D104: BSI 7228964829 | E104: Gemilang Sukses Mandiri | F104: SO2408-007 | G104: 0 | H104: 1600000 | I104: 45531 | J104: 45532 | K104: 45532 | L104: Lunas
B105: PT Maxima Express Pratama | C105: OF Indopromo | D105: BCA 5440311778 | E105: PT Maxima Express Pratama | F105: SO2408-003 | G105: 0 | H105: 1150035 | I105: 45531 | J105: 45532 | K105: 45532 | L105: Lunas | M105: ada kurang bayar
B106: PT Samudera Perdana Selaras | C106: Trucking dan Handling CPP Semarang | D106: BCA 8035008566 | E106: PT Samudera Perdana Selaras | F106: SO2407-009 | G106: 0 | H106: 12159127 | I106: 45517 | J106: 45548
B107: PT Patogar Jaya Trans | C107: Trucking Pak Niko/Pak Tommy Customer Surya | D107: BCA 4142299368 | E107: Kopindo Siregar | F107: SO2408-005 | G107: 0 | H107: 1800000 | I107: 45518 | J107: 45520 | K107: 45527 | L107: Lunas
B108: PT Abe Transindo Perkasa | C108: Trucking dan Handling CPP Surabaya | D108: Mandiri 1400066028888 | E108: PT Abe Transindo Perkasa | F108: SO2407-011 | G108: 0 | H108: 3962950 | I108: 45520 | J108: 45551
B109: PT Abe Transindo Perkasa | C109: Trucking dan Handling CPP Surabaya | D109: Mandiri 1400066028888 | E109: PT Abe Transindo Perkasa | F109: SO2407-012 | G109: 0 | H109: 11066246 | I109: 45520 | J109: 45551
B110: PT Abe Transindo Perkasa | C110: Trucking dan Handling CPP Surabaya | D110: Mandiri 1400066028888 | E110: PT Abe Transindo Perkasa | F110: SO 2407-015 | G110: 0 | H110: 2117850 | I110: 45531 | J110: 45562
B111: PT Sarana Andalan Pasifik | C111: Trucking ACSL | D111: BCA 6590363535 | E111: PT Sarana Andalan Pasifik | F111: 2408-008-009 | G111: 0 | H111: 4927575 | I111: 45533 | J111: 45549
B112: PT Boston Indo Global | C112: Fumigasi SLB | D112: BCA 0661882599 | E112: PT Boston Indo Global | F112: 2408-007 | G112: 0 | H112: 425000 | I112: 45534 | J112: 45541
B113: PT Grha Saba Permana | C113: Handling PIB dan Custom Clearance Indopromo Jakarta | D113: BCA 5213888322 | E113: PT Grha Saba Permana | F113: SO2408-003 | G113: 0 | H113: 650000 | I113: 45534
B117: LIST HUTANG ESHAKA TO VENDOR
B118: PT Prasetya Mitra Persada | C118: Penitipan Gudang PT Obor Pratama Indonesia | D118: Mandiri 1250013602719 | E118: PT Prasetya Mitra Persada | F118: SO2405-001 | G118: 0
...

Sheet REKON MANDIRI EWILOG
B1: REKON REKENING MANDIRI PT ESHAKA WIJAYA LOGISTICS | H1: PETTY CASH OKTOBER 2023
B2: PERIODE OKTOBER 2023 | H2: Tgl | I2: Deskripsi | J2: Debit | K2: Kredit | L2: Penyesuaian
B3: Tanggal | C3: Deskripsi | D3: Debit | E3: Kredit | F3: Saldo | H3: 24/10/2023 | I3: Tarik Tunai Saldo Awal | K3: 711800 | L3: =K3 -> 711800
B4: 20/10/2023 | C4: Setor Tunai Profit Bepah | E4: 10000000 | F4: =E4-D4 -> 10000000 | H4: 25/10/2023 | I4: Materai Pos indo 50lbr | J4: 500000 | L4: =L3-J4+K4 -> 211800
B5: 25/10/2023 | C5: DO Maersk Line CPP SO2310-004 | D5: 1827877 | F5: =F4-D5 -> 8172123 | H5: 27/10/2023 | I5: JNE Kaka Trans Doc CPP | J5: 10000 | L5: =L4-J5+K5 -> 201800
B6: 25/10/2023 | C6: Pinjam Dana Eshaka From Asiah | E6: 100000000 | F6: =F5-D6+E6 -> 108172123 | H6: 27/10/2023 | I6: Amplop Folio, HVS A4 & Map | J6: 120000 | L6: =L5-J6+K6 -> 81800
B7: 26/10/2023 | C7: Storage CPP NPCT1 SO2310-004 | D7: 2777321 | F7: =F6-D7+E7 -> 105394802 | H7: 30/11/2023 | I7: Pulsa Eshaka | J7: 81800 | L7: =L6-J7+K7 -> 0
B8: 26/10/2023 | C8: Pembayaran Legalitas & Alat Office (Rincian Terpisah) | D8: 11449500 | F8: =F7-D8+E8 -> 93945302 | H8: TOTAL NILAI AKHIR | J8: =SUM(J3:J11) -> 1423600 | K8: =SUM(K3:K11) -> 1423600 | L8: =K8-J8 -> 0
B9: 26/10/2023 | C9: Admin Tf Bank Lain BCA | D9: 2500 | F9: =F8-D9+E9 -> 93942802
B10: 26/10/2023 | C10: Payment ATK | D10: 1450000 | F10: =F9-D10+E10 -> 92492802
B11: 30/10/2023 | C11: DO Maersk Line CPP 2310-005 | D11: 1849291 | F11: =F10-D11+E11 -> 90643511
B12: 30/10/2023 | C12: DO ONE CJH 2310-001 | D12: 1606320 | F12: =F11-D12+E12 -> 89037191
B13: 31/10/2023 | C13: Biaya Admin Bank | D13: 12500 | F13: =F12-D13+E13 -> 89024691
B14: 31/10/2023 | C14: Bunga Bank | E14: 11334.88 | F14: =F13-D14+E14 -> 89036026 | G14: =SUM(E4:E15) -> 1.1001133e+08 | H14: Kredit
B15: 31/10/2023 | C15: Pajak Bank | D15: 2266.98 | F15: =F14-D15+E15 -> 89033759 | G15: =SUM(D4:D15) -> 20977576 | H15: Debet
B16: PERIODE NOVEMBER 2023 | H16: PETTY CASH NOVEMBER 2023
B17: 44937 | C17: Storage CPP SO2310-005 | D17: 512921 | F17: =F15-D17+E17 -> 88520838 | H17: Tgl | I17: Deskripsi | J17: Debit | K17: Kredit | L17: Penyesuaian
B18: 44937 | C18: Storage CJH 2310-001 | D18: 371396 | F18: =F17-D18+E18 -> 88149442 | H18: 45149 | I18: Tarik Tunai Saldo Awal | K18: 200000 | L18: =K18-J18 -> 200000
B19: 45149 | C19: Tarik Tunai Petty Cash | D19: 200000 | F19: =F18-D19+E19 -> 87949442 | H19: 45149 | I19: JNE CPP/CJH 2310-001/005 | J19: 20000 | L19: =L18-J19+K19 -> 180000
B20: 45149 | C20: Adm Tarik Link Atm | D20: 7500 | F20: =F19-D20+E20 -> 87941942 | H20: 16/11/2023 | I20: Pulsa Eshaka | J20: 50000 | L20: =L19-J20+K20 -> 130000
B21: 15/11/2023 | C21: Payment PT CJH SO2310-001 | E21: 6052116 | F21: =F20-D21+E21 -> 93994058 | H21: 21/11/2023 | I21: JNE CPP/Dolphin 004/002 | J21: 20000 | L21: =L20-J21+K21 -> 110000
B22: 16/11/2023 | C22: PIB, Admin Custom & DO Kaka Trans SO2310-004/005/001 | D22: 925000 | F22: =F21-D22+E22 -> 93069058 | H22: 23/11/2023 | I22: JNE Agata+Gojek 2311-001 | J22: 25000 | L22: =L21-J22+K22 -> 85000
B23: 16/11/2023 | C23: Trucking & Lolo PT Hanabi SO2310-001 CJH 2310-005 CPP | D23: 4901400 | F23: =F22-D23+E23 -> 88167658 | H23: 29/11/2023 | I23: Gojek Agata Exodus 2311-001/003 | J23: 20000 | L23: =L22-J23+K23 -> 65000
B24: 16/11/2023 | C24: Trucking & Lolo PT Hanabi SO2310-004 CPP | D24: 2349500 | F24: =F23-D24+E24 -> 85818158 | H24: TOTAL NILAI AKHIR | J24: =SUM(J15:J23) -> 135000 | K24: =SUM(K15:K23) -> 200000 | L24: =K24-J24 -> 65000
B25: 18/11/2023 | C25: Lolo PT Dolphin SO2311-002 | D25: 999000 | F25: =F24-D25+E25 -> 84819158
B26: 20/11/2023 | C26: Storage PT Dolphin SO2311-002 | D26: 595238 | F26: =F25-D26+E26 -> 84223920
B27: 20/11/2023 | C27: Biaya Bulanan Kartu | D27: 5500 | F27: =F26-D27+E27 -> 84218420
B28: 21/11/2023 | C28: DO OOCL Agata SO2311-001 | D28: 3038575 | F28: =F27-D28+E28 -> 81179845
B29: 21/11/2023 | C29: Adm TF Bank Lain OCBC | D29: 2900 | F29: =F28-D29+E29 -> 81176945
B30: 23/11/2023 | C30: DP PT Exodus Trucking SO2311-003 | E30: 1365000 | F30: =F29-D30+E30 -> 82541945
B31: 24/11/2023 | C31: Storage Agata SO2311-001 | D31: 1945097 | F31: =F30-D31+E31 -> 80596848
B32: 30/11/2023 | C32: Ganti Pulsa Eshaka 100k + TF Trucking Budi (Agata) SO2311-001 & Sallary 2.120.547 | D32: 4886347 | F32: =F31-D32+E32 -> 75710501
B33: 30/11/2023 | C33: Biaya Admin Bank | D33: 12500 | F33: =F32-D33+E33 -> 75698001
B34: 30/11/2023 | C34: Bunga Bank | E34: 42021.4 | F34: =F33-D34+E34 -> 75740022 | G34: =SUM(E17:E35) -> 7459137.4 | H34: Kredit
B35: 30/11/2023 | C35: Pajak Bank | D35: 8404.28 | F35: =F34-D35+E35 -> 75731618 | G35: =SUM(D17:D35) -> 20761278 | H35: Debet
B36: PERIODE DESEMBER 2023 | H36: PETTY CASH DESEMBER 2023
B37: 44938 | C37: Payment Dolphin SO2311-002 | E37: 3626000 | F37: =F35-D37+E37 -> 79357618 | H37: Tgl | I37: Deskripsi | J37: Debit | K37: Kredit | L37: Penyesuaian
B38: 44938 | C38: Payment Exodus SO2311-003 | E38: 1262100 | F38: =F37-D38+E38 -> 80619718 | H38: 29/11/2023 | I38: Saldo Akhir November 2023 | L38: 65000
B39: 44938 | C39: Payment Inv Agata SO2311-001 | E39: 16082364 | F39: =F38-D39+E39 -> 96702082 | H39: 13/12/2023 | I39: Tarik Tunai | K39: 8100000 | L39: =L38-J39+K39 -> 8165000
B40: 44938 | C40: Payment Debit Note Agata SO2311-001 | E40: 5849472 | F40: =F39-D40+E40 -> 1.0255155e+08 | H40: 13/12/2023 | I40: Bayar Tunai Win Share BCA 2311-001 | J40: 8006200 | L40: =L39-J40+K40 -> 158800
B41: 44938 | C41: Trucking & Lolo MJT Exodus SO2311-003 | D41: 2327100 | F41: =F40-D41+E41 -> 1.0022445e+08 | H41: 14/12/2023 | I41: JNE Medan CPP 2312-004 | J41: 47000 | L41: =L40-J41+K41 -> 111800
B42: 45028 | C42: Refund CPP Dewi SO2310-002/004/005 | D42: 400000 | F42: =F41-D42+E42 -> 99824454 | H42: 18/12/2023 | I42: JNE CPP Tagihan & Fecalindo Saipan | J42: 20000 | L42: =L41-J42+K42 -> 91800
B43: 45028 | C43: Storage NPCT1 CPP SO2311-005 | D43: 1079021 | F43: =F42-D43+E43 -> 98745433 | H43: 20/12/2023 | I43: JNE Dolphin SO2312-006 | J43: 10000 | L43: =L42-J43+K43 -> 81800
B44: 45058 | C44: DO Maersk Line CPP SO2312-002 | D44: 3317369 | F44: =F43-D44+E44 -> 95428064 | H44: TOTAL NILAI AKHIR | J44: =SUM(J38:J43) -> 8083200 | K44: =SUM(K35:K43) -> 8100000 | L44: =L43 -> 81800
B45: 45089 | C45: Payment Quanterm SO2312-005 | E45: 6000000 | F45: =F44-D45+E45 -> 1.0142806e+08
B46: 45089 | C46: Trucking & Lolo 1x40HQ Dolphin Cikupa SO2311-002 | D46: 1600000 | F46: =F45-D46+E46 -> 99828064
B47: 45089 | C47: Talangan Byr DO Maerskline CPP SO2310-002/2311-005 | D47: 4357379 | F47: =F46-D47+E47 -> 95470685
B48: 45089 | C48: Penumpukan CPP SO2312-002 | D48: 1003642 | F48: =F47-D48+E48 -> 94467043
B49: 13/12/2023 | C49: Tarik Tunai Petty Cash Total 8.1jt | D49: 2500000 | F49: =F48-D49+E49 -> 91967043
B50: 13/12/2023 | C50: Tarik Tunai Petty Cash Total 8.1jt | D50: 2500000 | F50: =F49-D50+E50 -> 89467043
B51: 13/12/2023 | C51: Tarik Tunai Petty Cash Total 8.1jt | D51: 2500000 | F51: =F50-D51+E51 -> 86967043
B52: 13/12/2023 | C52: Tarik Tunai Petty Cash Total 8.1jt | D52: 600000 | F52: =F51-D52+E52 -> 86367043
B53: 14/12/2023 | C53: Payment Pelunasan PT Quanterm SO2312-005 | E53: 11120000 | F53: =F52-D53+E53 -> 97487043
B54: 14/12/2023 | C54: Trucking & Inap PT PMP untuk SO2312-005 Quanterm | D54: 12500000 | F54: =F53-D54+E54 -> 84987043
B55: 14/12/2023 | C55: Payment PIB Handling & Trucking SPS SO2310-002 CPP | D55: 25051601 | F55: =F54-D55+E55 -> 59935442
B56: 14/12/2023 | C56: PIB Dan Handling Jakarta 2311-005 & 2312-002 | D56: 550000 | F56: =F55-D56+E56 -> 59385442
B57: 19/12/2023 | C57: Storage Dolphin SO2312-006 | D57: 762948 | F57: =F56-D57+E57 -> 58622494
B58: 20/12/2023 | C58: Biaya Kartu Bulan Des | D58: 5500 | F58: =F57-D58+E58 -> 58616994 | G58: =SUM(E37:E66) -> 47603636 | H58: Kredit
B59: 28/12/2023 | C59: Payment Dolphin SO2312-006 | E59: 3626000 | F59: =F58-D59+E59 -> 62242994 | G59: =SUM(D37:D66) -> 68064913 | H59: Debet
B60: 28/12/2023 | C60: Biaya Pengantar DO Fecalindo SO2312-001 Cargo Partner | D60: 1970250 | F60: =F59-D60+E60 -> 60272744
B61: 28/12/2023 | C61: Biaya TF Bank Lain | D61: 2500 | F61: =F60-D61+E61 -> 60270244
B62: 28/12/2023 | C62: Biaya DO Maersk line Fecalindo SO2312-001 | D62: 2782023 | F62: =F61-D62+E62 -> 57488221
B63: 30/12/2023 | C63: Biaya Bahandle Karantina Fecalindo SO2312-001 | D63: 2235540 | F63: =F62-D63+E63 -> 55252681
B64: 31/12/2023 | C64: Biaya Admin Bank | D64: 12500 | F64: =F63-D64+E64 -> 55240181
B65: 31/12/2023 | C65: Bunga Bank | E65: 37700.41 | F65: =F64-D65+E65 -> 55277881
B66: 31/12/2023 | C66: Pajak Bank | D66: 7540.08 | F66: =F65-D66+E66 -> 55270341
B67: PERIODE JANUARI 2024 | H67: PETTY CASH JANUARI 2024
B68: 45323 | C68: Storage Fecalindo SO2312-001 | D68: 2488999 | F68: =F66-D68+E68 -> 52781342 | H68: Tgl | I68: Deskripsi | J68: Debit | K68: Kredit | L68: Penyesuaian
B69: 45323 | C69: Trucking CPP SO2311-005 & SO2312-002 | D69: 6798500 | F69: =F68-D69+E69 -> 45982842 | H69: 31/12/2023 | I69: Saldo Akhir Desember 2024 | L69: 81800
B70: 45383 | C70: Payment CPP SO2310-002 | E70: 31380652 | F70: =F69-D70+E70 -> 77363494 | H70: 45566 | I70: JNE CPP SO2312-003, KAY 2401-001, Fecalindo 2312-001, Primaplast 2312-007 | J70: 42000 | L70: =L69-J70+K70 -> 39800
B71: 45383 | C71: PIB SSM & DO Fecalindo SO2312-001 Deni PPJK | D71: 410000 | F71: =F70-D71+E71 -> 76953494 | L71: =L70-J71+K71 -> 39800
B72: 45383 | C72: Admin Tf Bank Lain BCA | D72: 2500 | F72: =F71-D72+E72 -> 76950994 | L72: =L71-J72+K72 -> 39800
B73: 45383 | C73: Refund CPP Bulan Nov - Desember 2023 | D73: 2950000 | F73: =F72-D73+E73 -> 74000994 | L73: =L72-J73+K73 -> 39800
B74: 45383 | C74: Admin Tf Bank Lain BCA | D74: 2500 | F74: =F73-D74+E74 -> 73998494 | L74: =L73-J74+K74 -> 39800
B75: 45383 | C75: Ganti Talangan DO 7.051.500 & Sallary 15jt | D75: 22051500 | F75: =F74-D75+E75 -> 51946994 | H75: TOTAL NILAI AKHIR | J75: =SUM(J69:J74) -> 42000 | K75: =SUM(K66:K74) -> 0 | L75: =L74 -> 39800
B76: 45444 | C76: Refund Primaplast SO2312-007 | D76: 300000 | F76: =F75-D76+E76 -> 51646994
B77: 45444 | C77: Payment Trucking Kay Ocean SO2401-001 | D77: 700000 | F77: =F76-D77+E77 -> 50946994
B78: 45597 | C78: Storage Dolphin SO2401-008 | D78: 762949 | F78: =F77-D78+E78 -> 50184045
F79: =F78-D79+E79 -> 50184045
F80: =F79-D80+E80 -> 50184045
F81: =F80-D81+E81 -> 50184045
F82: =F81-D82+E82 -> 50184045
F83: =F82-D83+E83 -> 50184045
F84: =F83-D84+E84 -> 50184045
F85: =F84-D85+E85 -> 50184045
F86: =F85-D86+E86 -> 50184045
F87: =F86-D87+E87 -> 50184045
F88: =F87-D88+E88 -> 50184045
F89: =F88-D89+E89 -> 50184045
F90: =F89-D90+E90 -> 50184045
... F105: =F104-D105+E105 -> 50184045

Sheet LIST KANVAS
A1: LIST KANVAS HARIAN MUSTIKA
A2: PERIODE : DESEMBER 2023
A3: AREA : Rukan Malibu Raya Cengkareng - Jakbar
A4: No. | B4: Tgl Visit | C4: Tgl Penawaran | D4: Perusahaan | E4: Alamat | F4: PIC | G4: Email/HP | H4: Product/Commodity | I4: Type Shipment | J4: Keterangan
A5: 1 | B5: 44938 | D5: PT Avilla Jaya Teknik | E5: Ruko Citypark Business District (CBD) , Jl. Malibu Raya No. 2 Cengkareng Timur 11730 | F5: Pa Agus | G5: 081285105090 | H5: Genset | I5: Import Borongan China DTD
A6: 2 | B6: 44938 | D6: PT Meijing | E6: Ruko Citypark Business District (CBD) , Jl. Malibu Raya No. 1 Cengkareng Timur 11730 | F6: Pa Arief | G6: 081911191575 | H6: Kipas Portable & Aksesories | I6: Import Borongan China DTD
A7: 3 | B7: 44938 | D7: PT Hoki Darma Jaya | E7: Ruko Citypark Business District (CBD) , Jl. Malibu Raya Cengkareng Timur 11730 | F7: Pa Dede | G7: 081398071786 | H7: Sparepart Alat Berat | I7: Import Borongan China DTD & Domestik | J7: Boss nya Hanya hari kamis datang ke kantor
A8: AREA : Green Lake City Cipondoh Tangerang
A9: 1 | B9: 45242 | D9: PT Warmwave International Trading | E9: Rukan Sentra Niaga Green Lake City, Jl. Green Lake City Boulevard No. 27, RT.6 RW.8 Duri Kosambi, Cengkareng West Jakarta 11750 | G9: 0811658299
A10: 2 | D10: PT Indobest Technology | E10: Green Lake City Ruko Sentra Niaga, Blok K No. 32 RT.7 RW.8 Duri Kosambi Cengkareng Jakarta Barat 11750 | G10: 81293559672 | H10: Power Tools / Mesin Bor
A11: 3 | D11: PT Indonesia Huaxin International | E11: Rukan Crown, Jl. Green Lake City Boulevard No. 30, RT. 16/ RW.6 Petir Cipondoh Tangerang 15147
A12: 4 | D12: PT Formisa Internasional (Premix and Syrup Supplies) | E12: Ruko Sentra Niaga Blok O Jl. Green Lake City Boulevard No. 11 Duri Kosambi, Cengkaraeng11750 | G12: 081908092222 | H12: Kebutuhan Cafe, Resto, Hotel, Kedai & Coffee Shop
A13: 5 | D13: Tomiko Car Multimedia | E13: Rukan Crown Blok F No. 21. Jl Green Lake City Boulevard RT.04/RW.08 Petir Cipondoh 15147 | G13: 085351888868 | H13: Head Unit Mobil
A14: 6 | D14: PT Multi Inovasi Teknologi | E14: Rukan Crown, Jl. Green Lake City Boulevard No. 9 Petir, Kec Cipondoh Kota Tangerang Banten 15147 | H14: Alat Ukur & Uji Listrik, Hydraulic, Stripping Tool
A15: 7 | D15: PT Karya Tirta Perkasa | E15: West Europe Boulevard Green Lake City Ruko Food City No. 36 Duri Kosambi Cengkareng 11750 | G15: 0811852625 | H15: Distributor Tozen Valve
A16: 8 | D16: PT Tetramas Internusa | E16: Komplek Ruko Crown, Jl. Green Lake City Boulevard, Petir Kec. Cipondoh Tangerang 15147 | G16: 081318665907 | H16: Distributor Peralatan Industri (Battery, Electric Board, Pipes, Cable, Power Supply, Equipment & Charger)
A17: 9 | D17: PT Universal Jaya Perkasa | E17: Green Lake City Ruko Sentra Niaga, Blok B No. 9 RT.7 RW.8 Duri Kosambi Cengkareng Jakarta Barat 11750 | G17: 08111688202 | H17: Packaging
A18: 10 | D18: Distributor Oli Industri | E18: West Europe Boulevard Green Lake City Ruko Food City No. 39 Duri Kosambi Cengkareng 11750 | G18: 08119569119 | H18: Distributor Oli Mesin

Sheet LR OKT 23
E1: Talangan Oktober
B2: PT ESHAKA WIJAYA LOGISTICS | E2: Rincian Talangan Mustika
B3: Laporan Laba Rugi | E3: No. | F3: Deskripsi | G3: Nilai
B4: Periode 11 - 31 Oktober 2023 | E4: 1 | F4: Hosting Email | G4: 1080000
E5: 2 | F5: Kuota Eshaka | G5: 83000
B6: Description | C6: Penyesuaian | E6: 3 | F6: Stemple Eshaka & CPP | G6: 160000
B7: Modal / Harta : | E7: 4 | F7: JNE Kaka Trans CPP | G7: 10000
B8: Kas | E8: 5 | F8: Potonga Tf Agent WS | G8: 52000
B9: Opening Balance Bank Mandiri | C9: ='REKON MANDIRI EWILOG'!E6 -> 100000000 | E9: 6 | F9: HVS A4 | G9: 65000
B10: Total Modal | C10: =SUM(C8:C9) -> 100000000 | E10: Total | G10: =SUM(G4:G9) -> 1450000
B12: Pendapatan: | E12: Rincian Talangan Asiah
B13: Pendapatan Jasa Oktober | C13: =SHIPMENT!#REF! -> #REF! | E13: 1 | F13: DP 50% Perizinan PT | G13: 2750000
B14: Pendapatan Lain-Lain (Bunga Bank) | C14: ='REKON MANDIRI EWILOG'!E14 -> 11334.88 | E14: 2 | F14: Sewa Office 1thn | G14: 1800000
B15: Jumlah Pendapatan | C15: =SUM(C13:C14) -> #REF! | E15: 3 | F15: Kartu Nama | G15: 152000
E16: 4 | F16: Pelunasan Perizinan | G16: 2750000
B17: Hutang | E17: 5 | F17: Compro Jasa | G17: 500000
B18: Cicilan Modal Awal IDR 100,000,000; | E18: 6 | F18: Printer | G18: 3500000
E19: Total | G19: =SUM(G12:G18) -> 11452000
E21: Beban Gaji Karyawan
E22: No | F22: Nama | G22: Divisi | H22: Nominal
B23: Beban Usaha : | E23: 1 | F23: Asiah | G23: HRD-KOM | H23: 0
B24: Beban Gaji Karyawan | C24: =H25 -> 0 | E24: 2 | F24: Mustika | G24: MKT | H24: 0
B25: Beban Perjalanan Dinas | C25: 0 | E25: Total | H25: =SUM(H21:H24) -> 0
B26: Beban Iklan | C26: 0
B27: Beban Telepon | C27: 0 | E27: Beban Perlengkapan Kantor / ATK
B28: Beban Listrik & Air | C28: 0 | E28: 1 | F28: Hosting Email | G28: 1080000
B29: Beban Internet | C29: 83000 | E29: 2 | F29: Stemple Eshaka | G29: 80000
B30: Beban Sewa 1 Thn | C30: 1800000 | E30: 3 | F30: Potongan TF Agent | G30: 52000
B31: Beban Perlengkapan Kantor / ATK | C31: =G34 -> 1929000 | E31: 4 | F31: HVS A4 | G31: 65000
B32: Beban Pembuatan Legalitas Awal & Printer | C32: =G39 -> 9000000 | E32: 5 | F32: Kartu Nama | G32: 152000
B33: Beban Entertaint | C33: 0 | E33: 6 | F33: Jasa Design Compro | G33: 500000
B34: Beban Bensin & Tol Market | C34: 0 | E34: Total | G34: =SUM(G28:G33) -> 1929000
B35: Beban Operasional Lapang | C35: 0
B36: Beban Lain-lain (Admin Bank) | C36: =G45 -> 17266.98 | E36: Beban Legalitas & Printer
B37: Beban Potong Pph 23 (2%) | C37: 0 | E37: 1 | F37: Jasa Perizinan PT | G37: 5500000
B38: Jumlah Beban Usaha | C38: =SUM(C24:C37) -> 12829267 | E38: 2 | F38: Printer | G38: 3500000
E39: Total | G39: =SUM(G37:G38) -> 9000000
E41: Admin Bank Mandiri
B42: Laba Bersih | C42: =C15-C38 -> #REF! | E42: 1 | F42: Admin Tf Bank Lain | G42: 2500
E43: 2 | F43: Biaya Admin Bank | G43: 12500
E44: 3 | F44: Pajak Bank | G44: 2266.98
B45: Closing Balance Bank Mandiri | C45: ='REKON MANDIRI EWILOG'!F15 -> 89033759 | E45: Total | G45: =SUM(G42:G44) -> 17266.98

Sheet LR DES 2023
E1: Pendapatan Agustus 2024
B2: PT ESHAKA WIJAYA LOGISTICS | E2: No | F2: SO No. | G2: Customer | H2: Profit
B3: Laporan Laba Rugi | E3: 1 | F3: 2312-001 | G3: FDI | H3: 8795141
B4: Periode 01-31 Desember 2023 | E4: 2 | F4: 2312-002 | G4: CPP | H4: 1425000
E5: 3 | F5: 2312-003 | G5: CPP | H5: 3568000
B6: Description | C6: Penyesuaian | E6: 4 | F6: 2312-004 | G6: CPP | H6: 4911450
B7: Modal / Harta : | E7: 5 | F7: 2312-005 | G7: QL | H7: 4620000
B8: Kas | E8: 6 | F8: 2312-006 | G8: DBI | H8: 281552
B9: Opening Balance Bank Mandiri | C9: ='LR NOV 2023'!C45 -> 75731618 | E9: 7 | F9: 2312-007 | G9: PPI | H9: 18899865
B10: Total Modal | C10: =SUM(C8:C9) -> 75731618 | E10: 8 | F10: 2312-008 | G10: CPP | H10: 16232000
E11: 9 | F11: 2312-009 | G11: CPP | H11: 10427000
B12: Pendapatan: | E12: 10 | F12: 2312-010 | G12: OIP | H12: 250000
B13: Pendapatan Jasa Oktober | C13: =H13 -> 69410008 | E13: Total | H13: =SUM(H3:H12) -> 69410008
B14: Pendapatan Lain-Lain (Bunga Bank) | C14: 37700.41
B15: Jumlah Pendapatan | C15: =SUM(C13:C14) -> 69447708 | E15: Beban Gaji Karyawan
E16: No | F16: Nama | G16: Divisi | H16: Nominal
B17: Hutang | E17: 1 | F17: Asiah | G17: HRD-KOM | H17: 0
B18: Cicilan Modal Awal IDR 100,000,000; | E18: 2 | F18: Mustika | G18: MKT | H18: 15000000 | I18: Dibayar perhitungan bulan Januari
E20: Admin Bank Mandiri
E21: 1 | F21: Monthly Card | G21: 5500
E22: 2 | F22: Adm tf Bank | G22: 2500
B23: Beban Usaha : | E23: 3 | F23: Admin Bank | G23: 12500
B24: Beban Gaji Karyawan | C24: =H18 -> 15000000 | E24: 4 | F24: Pajak Bunga | G24: 7540.08
B25: Beban Perjalanan Dinas | C25: 0 | E25: Total | G25: =SUM(G21:G24) -> 28040.08
B26: Beban Iklan | C26: 0
B27: Beban Telepon | C27: 0
B28: Beban Listrik & Air | C28: 0
B29: Beban Internet | C29: 230000
B30: Beban Sewa 1 Thn | C30: 0
B31: Beban Perlengkapan Kantor / ATK | C31: 0
B32: Beban Pembuatan Legalitas Awal & Printer | C32: 0
B33: Beban Entertaint | C33: 0
B34: Beban Bensin & Tol Market | C34: 0
B35: Beban Operasional Lapang | C35: 0
B36: Beban Lain-lain (Admin Bank) | C36: =G25 -> 28040.08
B37: Beban Potong Pph 23 (2%)
B38: Jumlah Beban Usaha | C38: =SUM(C24:C37) -> 15258040
B42: Laba Bersih | C42: =C15-C38 -> 54189668
B45: Closing Balance Bank Mandiri | C45: ='LR NOV 2023'!C45 -> 75731618

Sheet LR JAN 2024
B2: PT ESHAKA WIJAYA LOGISTICS
B3: Laporan Laba Rugi
B4: Periode 01-31 JANUARI 2024
B6: Description | C6: Penyesuaian
B7: Modal / Harta :
B8: Kas | C8: 81800
B9: Bank Mandiri | C9: 55270341
B10: Total Modal | C10: =SUM(C8:C9) -> 55352141
B12: Pendapatan:
B13: Pendapatan Jasa Januari 2024 | C13: 38650912
B14: Pendapatan Lain-Lain (Bunga Bank) | C14: 37243.43
B15: Jumlah Pendapatan | C15: =SUM(C13:C14) -> 38688155
B17: Hutang
B18: Cicilan Modal Awal IDR 100,000,000;
B20: Piutang Oktober
B23: Beban Usaha :
B24: Beban Gaji Karyawan | C24: 9753822
B25: Beban Perjalanan Dinas
B26: Beban Iklan
B27: Beban Telepon / Kuota | C27: 120000
B28: Beban Listrik & Air
B29: Beban Internet
B30: Beban Sewa
B31: Beban Perlengkapan Kantor / ATK
B32: Beban Pembuatan Legalitas Awal & Printer
B33: Beban Entertaint
B34: Beban Bensin & Tol Market
B35: Beban Operasional Lapang
B36: Beban Lain-lain (Admin Bank) | C36: 19948.69
B38: Jumlah Beban Usaha | C38: =SUM(C24:C37) -> 9893770.7
B42: Laba Bersih | C42: =C15-C17+C20-C38 -> 28794385
C44: Saldo Akhir Jan 29 IDR 118.408.728.35

Sheet LR FEB 2024
B2: PT ESHAKA WIJAYA LOGISTICS
B3: Laporan Laba Rugi
B4: Periode 01-29 FEBRUARI 2024
B6: Description | C6: Penyesuaian
B7: Modal / Harta :
B8: Kas | C8: 39800
B9: Bank Mandiri | C9: 1.1840873e+08
B10: Total Modal | C10: =SUM(C8:C9) -> 1.1844853e+08
B12: Pendapatan:
B13: Pendapatan Jasa Februari 2024 | C13: 30052482
B14: Pendapatan Lain-Lain (Bunga Bank) | C14: 33329.8
B15: Jumlah Pendapatan | C15: =SUM(C13:C14) -> 30085812
B17: Hutang
B18: Cicilan Modal Awal IDR 100,000,000;
B20: Piutang S/D End Februari 2024
B21: Hutang S/D End Februari 2024
B23: Beban Usaha :
B24: Beban Gaji Karyawan | C24: 9753822
B25: Beban Perjalanan Dinas
B26: Beban Iklan
B27: Beban Telepon / Kuota | C27: 250000
B28: Beban Listrik & Air
B29: Beban Internet
B30: Beban Sewa
B31: Beban Perlengkapan Kantor / ATK
B32: Beban Pembuatan Legalitas Awal & Printer
B33: Beban Entertaint
B34: Beban Bensin & Tol Market
B35: Beban Operasional Lapang
B36: Beban Lain-lain (Admin Bank) | C36: 27165.96
B38: Jumlah Beban Usaha | C38: =SUM(C24:C37) -> 10030988
B42: Laba Bersih | C42: =C15-C17+C20-C21-C38 -> 20054824
C44: Saldo Akhir Feb 2024 IDR 221.762.983.93

Sheet LR MAR 2024
B2: PT ESHAKA WIJAYA LOGISTICS
B3: Laporan Laba Rugi
B4: Periode 01-31 MAR 2024
B6: Description | C6: Penyesuaian
B7: Modal / Harta :
B8: Kas | C8: 92000
B9: Bank Mandiri | C9: 3.0649372e+08
B10: Total Modal | C10: =SUM(C8:C9) -> 3.0658572e+08
B12: Pendapatan:
B13: Pendapatan Jasa Maret 2024 | C13: 13330964
B14: Pendapatan Lain-Lain (Bunga Bank) | C14: 89020.63
B15: Jumlah Pendapatan | C15: =SUM(C13:C14) -> 13419985
B17: Hutang
B18: Cicilan Modal Awal IDR 100,000,000;
B20: Piutang S/D End Maret 2024 | C20: 104830786
B21: Hutang S/D End Maret 2024 | C21: 190286162
B23: Beban Usaha :
B24: Beban Gaji Karyawan | C24: 6000000
B25: Beban Perjalanan Dinas
B26: Beban Iklan
B27: Beban Telepon / Kuota | C27: 150000
B28: Beban Listrik & Air
B29: Beban Internet
B30: Beban Sewa
B31: Beban Perlengkapan Kantor / ATK
B32: Beban Pembuatan Legalitas Awal & Printer
B33: Beban Entertaint
B34: Beban Bensin & Tol Market
B35: Beban Operasional Lapang
B36: Beban Lain-lain (Admin Bank) | C36: 35804.13
B38: Jumlah Beban Usaha | C38: =SUM(C24:C37) -> 6185804.1
B42: Laba Bersih | C42: =C10+C15-C17+C20-C21-C38 -> 2.2836453e+08

Sheet LR APR 2024
B2: PT ESHAKA WIJAYA LOGISTICS
B3: Laporan Laba Rugi
B4: Periode April 2024
B6: Description | C6: Penyesuaian
B7: Modal / Harta :
B8: Kas | C8: 62000
B9: Bank Mandiri | C9: 2.100385e+08
B10: Total Modal | C10: =SUM(C8:C9) -> 2.101005e+08
B12: Pendapatan:
B13: Pendapatan Jasa April 2024 | C13: 12869562
B14: Pendapatan Lain-Lain (Bunga Bank) | C14: 106544.27
B15: Jumlah Pendapatan | C15: =SUM(C13:C14) -> 12976106
B17: Hutang
B18: Cicilan Modal Awal IDR 100,000,000;
B20: Piutang S/D End April 2024 | C20: 85072989
B21: Hutang S/D End April 2024 | C21: 47489773
B22: Pinjaman Modal s/d April 2024 | C22: 100000000
B24: Beban Usaha :
B25: Beban Gaji Karyawan
B26: Beban Perjalanan Dinas
B27: Beban Iklan
B28: Beban Telepon / Kuota | C28: 120000
B29: Beban Listrik & Air
B30: Beban Internet
B31: Beban Sewa
B32: Beban Perlengkapan Kantor / ATK
B33: Beban Pembuatan Legalitas Awal & Printer
B34: Beban Entertaint
B35: Beban Bensin & Tol Market
B36: Beban Operasional Lapang
B37: Beban Lain-lain (Admin Bank) | C37: 41808.85
B39: Jumlah Beban Usaha | C39: =SUM(C25:C38) -> 161808.85
B43: Laba Bersih | C43: =C10+C15-C17+C20-C21-C22-C39 -> 1.6049801e+08

Sheet LR MEI 2024
B2: PT ESHAKA WIJAYA LOGISTICS
B3: Laporan Laba Rugi
B4: Periode Mei 2024
B6: Description | C6: Penyesuaian
B7: Modal / Harta :
B8: Kas | C8: 2000
B9: Bank Mandiri | C9: 2.6250454e+08
B10: Total Modal | C10: =SUM(C8:C9) -> 2.6250654e+08
B12: Pendapatan:
B13: Pendapatan Jasa Mei 2024 | C13: 50519681
B14: Pendapatan Lain-Lain (Bunga Bank)
B15: Jumlah Pendapatan | C15: =SUM(C13:C14) -> 50519681
B17: Hutang
B18: Cicilan Modal Awal IDR 100,000,000;
B20: Piutang S/D End Mei 2024 | C20: 21870490
B21: Hutang S/D End Mei 2024 | C21: 0
B22: Pinjaman Modal s/d April 2024 | C22: 100000000
B24: Beban Usaha :
B25: Beban Gaji Karyawan
B26: Beban Perjalanan Dinas
B27: Beban Iklan
B28: Beban Telepon / Kuota | C28: 150000
B29: Beban Listrik & Air
B30: Beban Internet
B31: Beban Sewa
B32: Beban Perlengkapan Kantor / ATK
B33: Beban Pembuatan Legalitas Awal & Printer
B34: Beban Entertaint
B35: Beban Bensin & Tol Market
B36: Beban Operasional Lapang
B37: Beban Lain-lain (Admin Bank)
B39: Jumlah Beban Usaha | C39: =SUM(C25:C38) -> 150000
B43: Laba Bersih | C43: =C10+C15-C17+C20-C21-C22-C39 -> 2.3474671e+08

Sheet LR JUN 2024
B2: PT ESHAKA WIJAYA LOGISTICS
B3: Laporan Laba Rugi
B4: Periode Juni 2024
B6: Description | C6: Penyesuaian
B7: Modal / Harta :
B8: Kas
B9: Bank Mandiri
B10: Total Modal | C10: =SUM(C8:C9) -> 0
B12: Pendapatan:
B13: Pendapatan Jasa Juni 2024 | C13: 19017000
B14: Pendapatan Lain-Lain (Bunga Bank) | C14: 115580.12
B15: Jumlah Pendapatan | C15: =SUM(C13:C14) -> 19132580
B17: Hutang
B18: Cicilan Modal Awal IDR 245,700,000;
B20: Piutang S/D End Juni 2024
B21: Hutang S/D End Juni 2024
B22: Pinjaman Modal s/d Juni 2024
B24: Beban Usaha :
B25: Beban Gaji Karyawan | C25: 2000000
B26: Beban Perjalanan Dinas
B27: Beban Iklan
B28: Beban Telepon / Kuota | C28: 150000
B29: Beban Listrik & Air
B30: Beban Internet
B31: Beban Sewa
B32: Beban Perlengkapan Kantor / ATK
B33: Beban Pembuatan Legalitas Awal & Printer
B34: Beban Entertaint
B35: Beban Bensin & Tol Market
B36: Beban Operasional Lapang
B37: Beban Lain-lain (Admin Bank) | C37: 46116.02
B39: Jumlah Beban Usaha | C39: =SUM(C25:C38) -> 2196116
B43: Laba Bersih | C43: =C10+C15-C17+C20-C21-C22-C39 -> 16936464

Sheet LR NOV 2023
E1: Pendapatan Agustus 2024
B2: PT ESHAKA WIJAYA LOGISTICS | E2: No | F2: SO No. | G2: Customer | H2: Profit
B3: Laporan Laba Rugi | E3: 1 | F3: 2311-001 | G3: AP-MRS073 | H3: 6484375
B4: Periode 01 - 30 November 2023 | E4: 2 | F4: 2311-002 | G4: DFB-MRS074 | H4: 271762
E5: 3 | F5: 2311-003 | G5: EXI-MRS075 | H5: 290000
B6: Description | C6: Penyesuaian | E6: 4 | F6: 2311-004 | G6: CPP-MRS071 | H6: 4430000
B7: Modal / Harta : | E7: 5 | F7: 2311-005 | G7: CPP-MRS071 | H7: 1123000
B8: Kas | E8: 6 | F8: 2311-006 | G8: CPP-MRS071 | H8: 4430000
B9: Opening Balance Bank Mandiri | C9: ='LR OKT 23'!C45 -> 89033759 | E9: Total | H9: =SUM(H3:H8) -> 17029137
B10: Total Modal | C10: =SUM(C8:C9) -> 89033759 | E10: Talangan Oktober
E11: Rincian Talangan Mustika
B12: Pendapatan: | E12: No. | F12: Deskripsi | G12: Nilai
B13: Pendapatan Jasa Oktober | C13: =H9 -> 17029137 | E13: 1
B14: Pendapatan Lain-Lain (Bunga Bank) | C14: 42021.4 | E14: Total | G14: =SUM(G8:G13) -> 0
B15: Jumlah Pendapatan | C15: =SUM(C13:C14) -> 17071158 | E15: 3
E16: 4
B17: Hutang | E17: 5
B18: Cicilan Modal Awal IDR 100,000,000; | E18: 6
E19: Total | G19: =SUM(G13:G18) -> 0
E21: Rincian Talangan Asiah
E22: 1
B23: Beban Usaha : | E23: Total | G23: =SUM(G17:G22) -> 0
B24: Beban Gaji Karyawan | C24: =H34 -> 2120547 | E24: 3
B25: Beban Perjalanan Dinas | C25: 0 | E25: 4
B26: Beban Iklan | C26: 0 | E26: 5
B27: Beban Telepon | C27: 0 | E27: 6
B28: Beban Listrik & Air | C28: 0 | E28: Total | G28: =SUM(G21:G27) -> 0
B29: Beban Internet | C29: 150000
B30: Beban Sewa 1 Thn | C30: 0 | E30: Beban Gaji Karyawan
B31: Beban Perlengkapan Kantor / ATK | C31: 0 | E31: No | F31: Nama | G31: Divisi | H31: Nominal
B32: Beban Pembuatan Legalitas Awal & Printer | C32: 0 | E32: 1 | F32: Asiah | G32: HRD-KOM | H32: 0
B33: Beban Entertaint | C33: 0 | E33: 2 | F33: Mustika | G33: MKT | H33: 2120547
B34: Beban Bensin & Tol Market | C34: 0 | E34: Total | H34: =SUM(H30:H33) -> 2120547
B35: Beban Operasional Lapang | C35: 0
B36: Beban Lain-lain (Admin Bank) | C36: =G50 -> 36804.28 | E36: Beban Perlengkapan Kantor / ATK
B37: Beban Potong Pph 23 (2%) | E37: 1
B38: Jumlah Beban Usaha | C38: =SUM(C24:C37) -> 2307351.3 | E38: Total | G38: =SUM(G37:G37) -> 0
E40: Beban Legalitas & Printer
E41: 1
B42: Laba Bersih | C42: =C15-C38 -> 14763807 | E42: Total | G42: =SUM(G41:G41) -> 0
E44: Admin Bank Mandiri
B45: Closing Balance Bank Mandiri | C45: ='REKON MANDIRI EWILOG'!F35 -> 75731618 | E45: 1 | F45: Admin Tarik Tunai | G45: 7500
E46: 2 | F46: Monthly Card | G46: 5500
E47: 3 | F47: Clearing Fee | G47: 2900
E48: 4 | F48: Admin Bank | G48: 12500
E49: 5 | F49: Pajak Bunga | G49: 8404.28
E50: Total | G50: =SUM(G45:G49) -> 36804.28

Sheet LR JAN 24
E1: Pendapatan Agustus 2024
B2: PT ESHAKA WIJAYA LOGISTICS | E2: No | F2: SO No. | G2: Customer | H2: Profit
B3: Laporan Laba Rugi | E3: 1 | F3: 2401-001 | G3: KOI | H3: 440000
B4: Periode 01-31 Januari 2024 | E4: 2 | F4: 2401-002 | G4: CPP | H4: 3290000
E5: 3 | F5: 2401-003 | G5: CPP | H5: 1560000
B6: Description | C6: Penyesuaian | E6: 4 | F6: 2401-004 | G6: CPP | H6: 910000
B7: Modal / Harta : | E7: 5 | F7: 2401-005 | G7: CPP | H7: 4259538
B8: Kas | E8: 6 | F8: 2401-006 | G8: CPP | H8: 2544926
B9: Opening Balance Bank Mandiri | C9: ='REKON MANDIRI EWILOG'!F66 -> 55270341 | E9: 7 | F9: 2401-007 | G9: CPP | H9: 9105000
B10: Total Modal | C10: =SUM(C8:C9) -> 55270341 | E10: 8 | F10: 2401-008 | G10: DFB | H10: 42551
E11: 9 | F11: 2401-009 | G11: GGN | H11: 7425800
B12: Pendapatan: | E12: 10 | F12: 2401-010 | G12: QL | H12: 916000
B13: Pendapatan Jasa Oktober | C13: =H16 -> 38647195 | E13: 11 | F13: 2401-011 | G13: QL | H13: 1340880
B14: Pendapatan Lain-Lain (Bunga Bank) | C14: 37243.43 | E14: 12 | F14: 2401-012 | G14: OIP | H14: 200000
B15: Jumlah Pendapatan | C15: =SUM(C13:C14) -> 38684438 | E15: 13 | F15: 2401-013 | G15: ELM | H15: 6612500
E16: Total | H16: =SUM(H3:H15) -> 38647195
B17: Hutang
B18: Cicilan Modal Awal IDR 100,000,000; | E18: Beban Gaji Karyawan
E19: No | F19: Nama | G19: Divisi | H19: Nominal
E20: 1 | F20: Asiah | G20: HRD-KOM | H20: 0
E21: 2 | F21: Mustika | G21: MKT | H21: 9223110
B23: Beban Usaha : | E23: Admin Bank Mandiri
B24: Beban Gaji Karyawan | C24: =H21 -> 9223110 | E24: 1 | F24: Monthly Card | G24: 5500
B25: Beban Perjalanan Dinas | C25: 0 | E25: 2 | F25: Adm tf Bank | G25: 2500
B26: Beban Iklan | C26: 0 | E26: 3 | F26: Admin Bank | G26: 12500
B27: Beban Telepon | C27: 0 | E27: 4 | F27: Pajak Bunga | G27: 7448.69
B28: Beban Listrik & Air | C28: 0 | E28: Total | G28: =SUM(G24:G27) -> 27948.69
B29: Beban Internet | C29: 120000
B30: Beban Sewa 1 Thn | C30: 0
B31: Beban Perlengkapan Kantor / ATK | C31: 0
B32: Beban Pembuatan Legalitas Awal & Printer | C32: 0
B33: Beban Entertaint | C33: 0
B34: Beban Bensin & Tol Market | C34: 0
B35: Beban Operasional Lapang | C35: 0
B36: Beban Lain-lain (Admin Bank) | C36: =G28 -> 27948.69
B37: Beban Potong Pph 23 (2%)
B38: Jumlah Beban Usaha | C38: =SUM(C24:C37) -> 9371058.7
B42: Laba Bersih | C42: =C15-C38 -> 29313380
B45: Closing Balance Bank Mandiri | C45: 67843185

Sheet LR FEB 24
E1: Pendapatan Agustus 2024
B2: PT ESHAKA WIJAYA LOGISTICS | E2: No | F2: SO No. | G2: Customer | H2: Profit
B3: Laporan Laba Rugi | E3: 1 | F3: 2402-001 | G3: CPP | H3: 4309500
B4: Periode 01-29 Februari 2024 | E4: 2 | F4: 2402-002 | G4: OIP | H4: 150000
E5: 3 | F5: 2402-003 | G5: OIP | H5: 450000
B6: Description | C6: Penyesuaian | E6: 4 | F6: 2402-004 | G6: CPP | H6: 3398702
B7: Modal / Harta : | E7: 5 | F7: 2402-005 | G7: OIP | H7: 150000
B8: Kas | E8: 6 | F8: 2402-006 | G8: MKT | H8: 656000
B9: Opening Balance Bank Mandiri | E9: 7 | F9: 2402-007 | G9: CPP | H9: 6118000
B10: Total Modal | C10: =SUM(C8:C9) -> 0 | E10: 8 | F10: 2402-008 | G10: CPP | H10: 978438
E11: 9 | F11: 2402-009 | G11: CPP | H11: 1624116
B12: Pendapatan: | E12: 10 | F12: 2402-010 | G12: CPP | H12: 3665584
B13: Pendapatan Jasa Oktober | C13: =H20 -> 33290104 | E13: 11 | F13: 2402-011 | G13: ATL | H13: 1040000
B14: Pendapatan Lain-Lain (Bunga Bank) | C14: 33329.8 | E14: 12 | F14: 2402-012 | G14: LGI | H14: 600000
B15: Jumlah Pendapatan | C15: =SUM(C13:C14) -> 33323434 | E15: 13 | F15: 2402-013 | G15: LGI | H15: 1190000
E16: 14 | F16: 2402-014 | G16: STL | H16: 2834880
B17: Hutang | E17: 15 | F17: 2402-015 | G17: CPP | H17: 1793332
B18: Cicilan Modal Awal IDR 100,000,000; | E18: 16 | F18: 2402-016 | G18: CPP | H18: 3967810
E19: 17 | F19: 2402-017 | G19: DFI | H19: 363742
E20: Total | H20: =SUM(H3:H19) -> 33290104
E22: Beban Gaji Karyawan
B23: Beban Usaha : | E23: No | F23: Nama | G23: Divisi | H23: Nominal
B24: Beban Gaji Karyawan | C24: =SUM(H24:H25) -> 9753822 | E24: 1 | F24: Asiah | G24: HRD-KOM | H24: 2327556
B25: Beban Perjalanan Dinas | C25: 0 | E25: 2 | F25: Mustika | G25: MKT | H25: 7426266
B26: Beban Iklan | C26: 0
B27: Beban Telepon | C27: 0 | E27: Admin Bank Mandiri
B28: Beban Listrik & Air | C28: 0 | E28: 1 | F28: Monthly Card | G28: 5500
B29: Beban Internet | C29: 150000 | E29: 2 | F29: Adm tf Bank | G29: 2500
B30: Beban Sewa 1 Thn | C30: 0 | E30: 3 | F30: Admin Bank | G30: 12500
B31: Beban Perlengkapan Kantor / ATK | C31: 0 | E31: 4 | F31: Pajak Bunga | G31: 6665.96
B32: Beban Pembuatan Legalitas Awal & Printer | C32: 0 | E32: Total | G32: =SUM(G28:G31) -> 27165.96
B33: Beban Entertaint | C33: 0
B34: Beban Bensin & Tol Market | C34: 0
B35: Beban Operasional Lapang | C35: 0
B36: Beban Lain-lain (Admin Bank) | C36: =G32 -> 27165.96
B37: Beban Potong Pph 23 (2%)
B38: Jumlah Beban Usaha | C38: =SUM(C24:C37) -> 9930988
B42: Laba Bersih | C42: =C15-C38 -> 23392446
B45: Closing Balance Bank Mandiri | C45: 2.2176298e+08

Sheet LR MAR 24
E1: Pendapatan Agustus 2024
B2: PT ESHAKA WIJAYA LOGISTICS | E2: No | F2: SO No. | G2: Customer | H2: Profit
B3: Laporan Laba Rugi | E3: 1 | F3: 2403-001 | G3: OIP | H3: 400000
B4: Periode 01-31 MARET 2024 | E4: 2 | F4: 2403-002 | G4: OIP | H4: 1800000
E5: 3 | F5: 2403-003 | G5: OIP | H5: 400000
B6: Description | C6: Penyesuaian | E6: 4 | F6: 2403-004 | G6: CPP | H6: 1476000
B7: Modal / Harta : | E7: 5 | F7: 2403-005 | G7: SL | H7: 2604250
B8: Kas | E8: 6 | F8: 2403-006 | G8: KOI | H8: 5771000
B9: Opening Balance Bank Mandiri | C9: ='LR FEB 24'!C45 -> 2.2176298e+08 | E9: 7 | F9: 2403-007 | G9: RCS | H9: 690000
B10: Total Modal | C10: =SUM(C8:C9) -> 2.2176298e+08 | E10: Total | H10: =SUM(H3:H9) -> 13141250
B12: Pendapatan: | E12: Beban Gaji Karyawan
B13: Pendapatan Jasa Maret 2024 | C13: =H10 -> 13141250 | E13: No | F13: Nama | G13: Divisi | H13: Nominal
B14: Pendapatan Lain-Lain (Bunga Bank) | C14: 89020.63 | E14: 1 | F14: Asiah | G14: HRD-KOM | H14: 1000000
B15: Jumlah Pendapatan | C15: =SUM(C13:C14) -> 13230271 | E15: 2 | F15: Mustika | G15: MKT | H15: 5000000
B17: Hutang | E17: Admin Bank Mandiri
B18: Cicilan Modal Awal IDR 100,000,000; | E18: 1 | F18: Monthly Card | G18: 5500
E19: 2 | F19: Admin Bank | G19: 12500
E20: 3 | F20: Pajak Bunga | G20: 17804.13
E21: Total | G21: =SUM(G18:G20) -> 35804.13
B23: Beban Usaha :
B24: Beban Gaji Karyawan | C24: =SUM(H14:H15) -> 6000000
B25: Beban Perjalanan Dinas | C25: 0
B26: Beban Iklan | C26: 0
B27: Beban Telepon | C27: 0
B28: Beban Listrik & Air | C28: 0
B29: Beban Internet | C29: 150000
B30: Beban Sewa 1 Thn | C30: 0
B31: Beban Perlengkapan Kantor / ATK | C31: 0
B32: Beban Pembuatan Legalitas Awal & Printer | C32: 0
B33: Beban Entertaint | C33: 0
B34: Beban Bensin & Tol Market | C34: 0
B35: Beban Operasional Lapang | C35: 0
B36: Beban Lain-lain (Admin Bank) | C36: =G21 -> 35804.13
B37: Beban Potong Pph 23 (2%)
B38: Jumlah Beban Usaha | C38: =SUM(C24:C37) -> 6185804.1
B42: Laba Bersih | C42: =C15-C38 -> 7044466.5
B45: Closing Balance Bank Mandiri | C45: 3.0649372e+08

Sheet LR APR 24
E1: Pendapatan Agustus 2024
B2: PT ESHAKA WIJAYA LOGISTICS | E2: No | F2: SO No. | G2: Customer | H2: Profit
B3: Laporan Laba Rugi | E3: 1 | F3: 2404-001 | G3: QL | H3: 2637562
B4: Periode 01-30 APRIL 2024 | E4: 2 | F4: 2404-002 | G4: CWI | H4: 1634100
E5: 3 | F5: 2404-003 | G5: CPP | H5: 3175000
B6: Description | C6: Penyesuaian | E6: 4 | F6: 2404-004 | G6: CPP | H6: 6150000
B7: Modal / Harta : | E7: 5 | F7: 2404-005 | G7: CPP | H7: 6150000
B8: Kas | E8: 6 | F8: 2404-006 | G8: KOI | H8: 3570000
B9: Opening Balance Bank Mandiri | C9: ='LR MAR 24'!C45 -> 3.0649372e+08 | E9: Total | H9: =SUM(H3:H8) -> 23316662
B10: Total Modal | C10: =SUM(C8:C9) -> 3.0649372e+08
E11: Beban Gaji Karyawan
B12: Pendapatan: | E12: No | F12: Nama | G12: Divisi | H12: Nominal
B13: Pendapatan Jasa April 2024 | C13: =H9 -> 23316662 | E13: 1 | F13: Asiah | G13: HRD-KOM | H13: 800000
B14: Pendapatan Lain-Lain (Bunga Bank) | C14: 106544.27 | E14: 2 | F14: Mustika | G14: MKT | H14: 1026500
B15: Jumlah Pendapatan | C15: =SUM(C13:C14) -> 23423206
E16: Admin Bank Mandiri
B17: Hutang | E17: 1 | F17: Monthly Card | G17: 5500
B18: Cicilan Modal Awal IDR 100,000,000; | E18: 2 | F18: Admin Bank | G18: 12500
E19: 3 | F19: Admin tf | G19: 2500
E20: 4 | F20: Pajak Bunga | G20: 21308.85
E21: Total | G21: =SUM(G17:G20) -> 41808.85
B23: Beban Usaha :
B24: Beban Gaji Karyawan | C24: =SUM(H13:H14) -> 1826500
B25: Beban Perjalanan Dinas | C25: 0
B26: Beban Iklan | C26: 0
B27: Beban Telepon | C27: 0
B28: Beban Listrik & Air | C28: 0
B29: Beban Internet | C29: 150000
B30: Beban Sewa 1 Thn | C30: 0
B31: Beban Perlengkapan Kantor / ATK | C31: 0
B32: Beban Pembuatan Legalitas Awal & Printer | C32: 0
B33: Beban Entertaint | C33: 0
B34: Beban Bensin & Tol Market | C34: 0
B35: Beban Operasional Lapang | C35: 0
B36: Beban Lain-lain (Admin Bank) | C36: =G21 -> 41808.85
B37: Beban Potong Pph 23 (2%)
B38: Jumlah Beban Usaha | C38: =SUM(C24:C37) -> 2018308.9
B42: Laba Bersih | C42: =C15-C38 -> 21404897
B45: Closing Balance Bank Mandiri | C45: 2.100385e+08

Sheet LR MAY 24
E1: Pendapatan Agustus 2024
B2: PT ESHAKA WIJAYA LOGISTICS | E2: No | F2: SO No. | G2: Customer | H2: Profit
B3: Laporan Laba Rugi | E3: 1 | F3: 2405-001 | G3: OIP | H3: 14566703
B4: Periode 01-31 MAY2024 | E4: 2 | F4: 2405-002 | G4: AVM | H4: 541000
E5: 3 | F5: 2405-003 | G5: CPP | H5: 1725900
B6: Description | C6: Penyesuaian | E6: 4 | F6: 2405-004 | G6: CPP | H6: 867500
B7: Modal / Harta : | E7: 5 | F7: 2405-005 | G7: IDG/GGN | H7: 29477440
B8: Kas | E8: 6 | F8: 2405-006 | G8: MMW/DESPI | H8: 3365000
B9: Opening Balance Bank Mandiri | C9: ='LR APR 24'!C45 -> 2.100385e+08 | E9: 7 | F9: 2405-007 | G9: PIM | H9: 1500000
B10: Total Modal | C10: =SUM(C8:C9) -> 2.100385e+08 | E10: 8 | F10: 2405-008 | G10: DFB | H10: 255181
E11: Total | H11: =SUM(H3:H10) -> 52298724
B12: Pendapatan:
B13: Pendapatan Jasa May 2024 | C13: =H11 -> 52298724 | E13: Beban Gaji Karyawan
B14: Pendapatan Lain-Lain (Bunga Bank) | C14: 111057.97 | E14: No | F14: Nama | G14: Divisi | H14: Nominal
B15: Jumlah Pendapatan | C15: =SUM(C13:C14) -> 52409782 | E15: 1 | F15: Asiah | G15: HRD-KOM | H15: 2000000
E16: 2 | F16: Mustika | G16: MKT | H16: 15000000
B17: Hutang
B18: Cicilan Modal Awal IDR 100,000,000; | E18: Admin Bank Mandiri
E19: 1 | F19: Monthly Card | G19: 5500
E20: 2 | F20: Admin Bank | G20: 12500
E21: 3 | F21: Admin tf | G21: 2500
E22: 4 | F22: Pajak Bunga | G22: 22211.59
B23: Beban Usaha : | E23: Total | G23: =SUM(G19:G22) -> 42711.59
B24: Beban Gaji Karyawan | C24: =SUM(H15:H16) -> 17000000
B25: Beban Perjalanan Dinas | C25: 0
B26: Beban Iklan | C26: 0
B27: Beban Telepon | C27: 0
B28: Beban Listrik & Air | C28: 0
B29: Beban Internet | C29: 150000
B30: Beban Sewa 1 Thn | C30: 0
B31: Beban Perlengkapan Kantor / ATK | C31: 0
B32: Beban Pembuatan Legalitas Awal & Printer | C32: 0
B33: Beban Entertaint | C33: 0
B34: Beban Bensin & Tol Market | C34: 0
B35: Beban Operasional Lapang | C35: 0
B36: Beban Lain-lain (Admin Bank) | C36: =G23 -> 42711.59
B37: Beban Potong Pph 23 (2%)
B38: Jumlah Beban Usaha | C38: =SUM(C24:C37) -> 17192712
B42: Laba Bersih | C42: =C15-C38 -> 35217070
B45: Closing Balance Bank Mandiri | C45: 2.3926488e+08

Sheet LR JUN 24
E1: Pendapatan Agustus 2024
B2: PT ESHAKA WIJAYA LOGISTICS | E2: No | F2: SO No. | G2: Customer | H2: Profit
B3: Laporan Laba Rugi | E3: 1 | F3: 2406-001 | G3: GPI | H3: 2042000
B4: Periode 01-30 JUNI 2024 | E4: 2 | F4: 2406-002 | G4: OIP | H4: 1400000
E5: 3 | F5: 2406-003 | G5: DFB | H5: 569242
B6: Description | C6: Penyesuaian | E6: 4 | F6: 2406-004 | G6: GPI | H6: 719250
B7: Modal / Harta : | E7: 5 | F7: 2406-005 | G7: ET | H7: 14500000
B8: Kas | E8: Total | H8: =SUM(H3:H7) -> 19230492
B9: Opening Balance Bank Mandiri | C9: ='LR MAY 24'!C45 -> 2.3926488e+08
B10: Total Modal | C10: =SUM(C8:C9) -> 2.3926488e+08 | E10: Beban Gaji Karyawan
E11: No | F11: Nama | G11: Divisi | H11: Nominal
B12: Pendapatan: | E12: 1 | F12: Asiah | G12: HRD-KOM | H12: 2000000
B13: Pendapatan Jasa Jun 2024 | C13: =H8 -> 19230492 | E13: 2 | F13: Mustika | G13: MKT | H13: 5739775
B14: Pendapatan Lain-Lain (Bunga Bank) | C14: 115580.12
B15: Jumlah Pendapatan | C15: =SUM(C13:C14) -> 19346072 | E15: Admin Bank Mandiri
E16: 1 | F16: Monthly Card | G16: 5500
B17: Hutang | E17: 2 | F17: Admin Bank | G17: 12500
B18: Cicilan Modal Awal IDR 100,000,000; | E18: 3 | F18: Pajak Bunga | G18: 23116.02
E19: Total | G19: =SUM(G16:G18) -> 41116.02
B23: Beban Usaha :
B24: Beban Gaji Karyawan | C24: =SUM(H12:H13) -> 7739775
B25: Beban Perjalanan Dinas | C25: 0
B26: Beban Iklan | C26: 0
B27: Beban Telepon | C27: 0
B28: Beban Listrik & Air | C28: 0
B29: Beban Internet | C29: 150000
B30: Beban Sewa 1 Thn | C30: 0
B31: Beban Perlengkapan Kantor / ATK | C31: 0
B32: Beban Pembuatan Legalitas Awal & Printer | C32: 0
B33: Beban Entertaint | C33: 0
B34: Beban Bensin & Tol Market | C34: 0
B35: Beban Operasional Lapang (Jumat Berkah) | C35: 450000
B36: Beban Lain-lain (Admin Bank) | C36: =G19 -> 41116.02
B37: Beban Potong Pph 23 (2%)
B38: Jumlah Beban Usaha | C38: =SUM(C24:C37) -> 8380891
B42: Laba Bersih | C42: =C15-C38 -> 10965181
B45: Closing Balance Bank Mandiri | C45: 2.6264103e+08

Sheet LR JUL 2024
E1: Pendapatan July 2024
B2: PT ESHAKA WIJAYA LOGISTICS | E2: No | F2: SO No. | G2: Customer | H2: Profit
B3: Laporan Laba Rugi | E3: 1 | F3: 2407-001 | G3: JT | H3: -19329324
B4: Periode 01-31 JULY 2024 | E4: 2 | F4: 2407-002 | G4: JT | H4: 9149570
E5: 3 | F5: 2407-003 | G5: FDI | H5: 11465000
B6: Description | C6: Penyesuaian | E6: 4 | F6: 2407-004 | G6: VAM | H6: 1308000
B7: Modal / Harta : | E7: 5 | F7: 2407-005 | G7: GPI | H7: 229750
B8: Kas | E8: 6 | F8: 2407-006 | G8: JT | H8: 2063460
B9: Opening Balance Bank Mandiri | C9: ='LR JUN 24'!C45 -> 2.6264103e+08 | E9: 7 | F9: 2407-007 | G9: CPP | H9: 1070500
B10: Total Modal | C10: =SUM(C8:C9) -> 2.6264103e+08 | E10: 8 | F10: 2407-008 | G10: CPP | H10: 3081500
E11: 9 | F11: 2407-009 | G11: CPP | H11: 3078000
B12: Pendapatan: | E12: 10 | F12: 2407-010 | G12: CPP | H12: 921000
B13: Pendapatan Jasa Jun 2024 | C13: =H21 -> 26911600 | E13: 11 | F13: 2407-011 | G13: CPP | H13: 1865626
B14: Pendapatan Lain-Lain (Bunga Bank) | C14: 131894.93 | E14: 12 | F14: 2407-012 | G14: CPP | H14: 2297738
B15: Jumlah Pendapatan | C15: =SUM(C13:C14) -> 27043495 | E15: 13 | F15: 2407-013 | G15: OIP | H15: 2300000
E16: 14 | F16: 2407-014 | G16: CPP | H16: 1141538
B17: Hutang | E17: 15 | F17: 2407-015 | G17: CPP | H17: 1141538
B18: Cicilan Modal Awal IDR 100,000,000; | E18: 16 | F18: 2407-016 | G18: OIP | H18: 850000
E19: 17 | F19: 2407-017 | G19: DFB | H19: 443712
E20: 18 | F20: 2407-018 | G20: CPP | H20: 3833992
E21: Total | H21: =SUM(H3:H20) -> 26911600
B23: Beban Usaha : | E23: Beban Gaji Karyawan
B24: Beban Gaji Karyawan | C24: =SUM(H25:H26) -> 7739775 | E24: No | F24: Nama | G24: Divisi | H24: Nominal
B25: Beban Perjalanan Dinas | C25: 0 | E25: 1 | F25: Asiah | G25: HRD-KOM | H25: 2000000
B26: Beban Iklan | C26: 0 | E26: 2 | F26: Mustika | G26: MKT | H26: 5739775
B27: Beban Telepon | C27: 0
B28: Beban Listrik & Air | C28: 0 | E28: Admin Bank Mandiri
B29: Beban Internet | C29: 212393 | E29: 1 | F29: Monthly Card | G29: 5500
B30: Beban Sewa 1 Thn | C30: 0 | E30: 2 | F30: Admin Bank | G30: 12500
B31: Beban Perlengkapan Kantor / ATK | C31: 0 | E31: 3 | F31: Pajak Bunga | G31: 26378.99
B32: Beban Pembuatan Legalitas Awal & Printer | C32: 0 | E32: Total | G32: =SUM(G29:G31) -> 44378.99
B33: Beban Entertaint | C33: 0
B34: Beban Bensin & Tol Market | C34: 0
B35: Beban Operasional Lapang | C35: 450000
B36: Beban Lain-lain (Admin Bank) | C36: =G32 -> 44378.99
B37: Beban Potong Pph 23 (2%)
B38: Jumlah Beban Usaha | C38: =SUM(C24:C37) -> 8446547
B42: Laba Bersih | C42: =C15-C38 -> 18596948
B45: Closing Balance Bank Mandiri | C45: 2.3429906e+08

Sheet LR AUG 2024
B2: PT ESHAKA WIJAYA LOGISTICS | F2: Pendapatan Agustus 2024
B3: Laporan Laba Rugi | F3: No | G3: SO No. | H3: Customer | I3: Profit
B4: Periode Agustus 2024 | F4: 1 | G4: 2408-001 | H4: CPP-MRS | I4: 3378000
F5: 2 | G5: 2408-002 | H5: CPP-MRS | I5: 1928000
B6: Description | C6: Penyesuaian | F6: 3 | G6: 2408-003 | H6: IML-MRS | I6: 8517856
B7: Modal / Harta : | F7: 4 | G7: 2408-004 | H7: ERW-MRS | I7: 2925000 | J7: Close, Sisa Masuk CN Des 24 | M7: Close Masuk CN Des 24
B8: Kas | C8: 1679500 | F8: 5 | G8: 2408-005 | H8: AML-SRY | I8: 500000
B9: Bank Mandiri | C9: ='LR JUL 2024'!C45 -> 2.3429906e+08 | F9: 6 | G9: 2408-006 | H9: CJH-MRS | I9: 1399000
B10: Bank BCA | C10: 0 | F10: 7 | G10: 2408-007 | H10: GSA-IAN | I10: 1815600
B11: Total Modal | C11: =SUM(C8:C10) -> 2.3597856e+08 | F11: 8 | G11: 2408-008 | H11: CSL-MRS | I11: 1080000
F12: 9 | G12: 2408-009 | H12: CSL-MRS | I12: 4400000
B13: Pendapatan: | F13: 10 | G13: 2408-010 | H13: CSL-MRS | I13: 3300000
B14: Pendapatan Jasa Agustus 2024 | C14: =I26 -> 74715292 | F14: 11 | G14: 2408-011 | H14: CPP-MRS | I14: 4798000
B15: Pendapatan Lain-Lain (Bunga Bank Mandiri) | C15: =I67 -> 135713.32 | F15: 12 | G15: 2408-012 | H15: RTS-SRY | I15: 1500000
B16: Pendapatan Lain-Lain (Bunga Bank BCA) | C16: 0 | F16: 13 | G16: 2408-013 | H16: CSL-MRS | I16: 1200000
B17: Jumlah Pendapatan | C17: =SUM(C14:C15) -> 74851005 | F17: 14 | G17: 2408-014 | H17: CSL-MRS | I17: 1200000
F18: 15 | G18: 2408-015 | H18: CPP-MRS | I18: 2969220
B19: Hutang | F19: 16 | G19: 2408-016 | H19: CPP-MRS | I19: 4656646
B20: Cicilan Modal Awal IDR 100,000,000; + IDR 233,594,567 | F20: 17 | G20: 2408-017 | H20: CPP-MRS | I20: 5294526
F21: 18 | G21: 2408-018 | H21: CSL-MRS | I21: 9850000
B22: Piutang S/D End Aug 2024 | C22: =I46 -> 78025720 | F22: 19 | G22: 2408-019 | H22: OIP-MRS | I22: 6128444
B23: Hutang S/D End Aug 2024 | C23: =I59 -> 62583105 | F23: 20 | G23: 2408-020 | H23: CSL-MRS | I23: 1000000
B24: Pinjaman Modal s/d End Aug 2024 | C24: 333594567 | F24: 21 | G24: 2408-021 | H24: CSL-MRS | I24: 5575000
F25: 22 | G25: 2408-022 | H25: CSL-MRS | I25: 1300000
B26: Beban Usaha : | F26: Total | I26: =SUM(I4:I25) -> 74715292
B27: Beban Gaji Karyawan | C27: =I35 -> 16242000
B28: Beban Perjalanan Dinas
B29: Beban Iklan | F29: Sallary Staff | J29: 45532
B30: Beban IPL Bulan Agustus | C30: 1431000 | F30: No | G30: Nama | H30: Divisi | I30: Nominal
B31: Beban Listrik | C31: 705250 | F31: 1 | G31: Mursidah | H31: OB | I31: 1917000 | J31: Dibayar Per Minggu
B32: Beban Quota Ewilog | C32: 50000 | F32: 2 | G32: Asiah | H32: HRD-KOM | I32: 2000000
B33: Beban Internet Indihome | C33: 243253 | F33: 3 | G33: Mustika | H33: MKT | I33: 10000000
B34: Beban Sewa | F34: 4 | G34: Surya | H34: MKT | I34: 2325000
B35: Beban Perlengkapan Kantor / ATK / Aqua | C35: 158000 | F35: Total | I35: =SUM(I31:I34) -> 16242000
B36: Beban Entertaint
B37: Beban Bensin & Tol Market | C37: 608500 | F37: PIUTANG LIST
B38: Beban Lain-lain (Admin Bank Mandiri) | C38: =H67 -> 45142.66 | F38: 1 | G38: Customer | H38: SO NO | I38: Total Transfer
B39: Beban Lain-lain (Admin Bank BCA) | C39: =H74 -> 55000 | F39: 2 | G39: CPP-MRS | H39: SO2407-007 | I39: 8153954
F40: 3 | G40: CPP-MRS | H40: SO2407-008 | I40: 16237053
B41: Jumlah Beban Usaha | C41: =SUM(C27:C40) -> 19538146 | F41: 4 | G41: CPP-MRS | H41: SO2407-009 | I41: 15497127
F42: 5 | G42: CPP-MRS | H42: SO2407-010 | I42: 9880814
F43: 6 | G43: CPP-MRS | H43: SO2407-011 | I43: 11243400
F44: 7 | G44: CPP-MRS | H44: SO2407-012 | I44: 13603984
B45: Laba Bersih | C45: =C17-C41 -> 55312860 | F45: 8 | G45: CPP-MRS | H45: SO2407-015 | I45: 3409388
F46: Total | I46: =SUM(I39:I45) -> 78025720
B48: Closing Balance Bank Mandiri | C48: 2.577605e+08 | F48: HUTANG
B49: Closing Balance Bank BCA | C49: 18819950 | F49: 1 | G49: PMP | H49: SO2407-017 | I49: 1700000
F50: 2 | G50: SPS | H50: SO2407-004 | I50: 5554004
C51: =SUM(C48:C49) -> 2.7658045e+08 | F51: 3 | G51: SPS | H51: SO2407-008 | I51: 12892553
F52: 4 | G52: SPS | H52: SO2407-009 | I52: 12159127
F53: 5 | G53: ABE | H53: SO2407-011 | I53: 3962950
F54: 6 | G54: ABE | H54: SO2407-012 | I54: 11066246
F55: 7 | G55: ABE | H55: SO 2407-015 | I55: 2117850
F56: 8 | G56: SAP | H56: 2408-008-009 | I56: 4927575
F57: 9 | G57: GSP | H57: SO2408-003 | I57: 650000
F58: 10 | G58: PMP | H58: SO2407-017 | I58: 7552800
F59: Total | I59: =SUM(I49:I58) -> 62583105
F61: Biaya Admin Bank (Mandiri)
F62: 1 | G62: KET | H62: DEBET | I62: KREDIT
F63: 2 | G63: Monthly Card | H63: 5500
F64: 3 | G64: Admin Bank | H64: 12500
F65: 4 | G65: Bunga Bank | I65: 135713.32
F66: 5 | G66: Pajak Bank | H66: 27142.66
F67: Total | H67: =SUM(H63:H66) -> 45142.66 | I67: =SUM(I63:I66) -> 135713.32
F70: Biaya Admin Bank (BCA)
F71: 1 | G71: KET | H71: DEBET | I71: KREDIT
F72: 2 | G72: Biaya Token Key | H72: 25000
F73: 3 | G73: Admin Bank | H73: 30000 | P73: V
F74: Total | H74: =SUM(H72:H73) -> 55000 | I74: =SUM(I72:I73) -> 0
F76: RINCIAN TALANGAN MUSTIKA | K76: PETTY CASH AGUSTUS 2024
G77: KETERANGAN | H77: SO NO | I77: Total Transfer | K77: No. | L77: Tgl | M77: KETERANGAN | N77: DEBIT | O77: KREDIT | P77: PENYESUAIAN
F78: 1 | G78: JNE FDI, CPP, DFB | H78: SHIPMENT | I78: 30000 | K78: 1 | L78: 45514 | M78: SALDO AWAL | O78: 700000
F79: 2 | G79: GOOD DAY KOPI | H79: OFFICE | I79: 32000 | K79: 2 | L79: 45514 | M79: SALLARY MINGGUAN | N79: 500000
F80: 3 | G80: BENSIN MOTOR | H80: OFFICE | I80: 30000 | K80: 3 | L80: 45513 | M80: GALON | N80: 21500
F81: 4 | G81: GALON | H81: OFFICE | I81: 21500 | K81: 4 | L81: 45517 | M81: JNE | N81: 10000
F82: 5 | G82: IPL AGUSTUS | H82: OFFICE | I82: 1431000 | K82: 5 | L82: 45519 | M82: KOPI | N82: 15000
F83: 6 | G83: INDIHOME | H83: OFFICE | I83: 243253 | K83: 6 | L83: 45519 | M83: AIR BIRU | N83: 9000
F84: 7 | G84: WPC,DLL | H84: OFFICE | I84: 41000 | K84: 7 | L84: 45520 | M84: TAMBAHAN SALDO | O84: 1000000
F85: 8 | G85: PETTY CASH ESH | H85: OFFICE | I85: 700000 | K85: 8 | L85: 45520 | M85: JNE | N85: 10000
F86: 9 | G86: PARKIR | H86: OFFICE | I86: 15000 | K86: 9 | L86: 45520 | M86: SALLARY MINGGUAN | N86: 417000
F87: 10 | G87: PLN TOK LISTRIK | H87: OFFICE | I87: 502750 | K87: 10 | L87: 45528 | M87: SALLARY MINGGUAN | N87: 500000
F88: 11 | G88: BENSIN MOBIL | H88: OFFICE | I88: 200000 | K88: 11 | L88: 45528 | M88: AIR BIRU | N88: 9000
F89: 12 | G89: PARKIR BATUCEPER | H89: OFFICE | I89: 5000 | K89: 12 | L89: 45534 | M89: GALON KOPI GULA | N89: 29000
F90: 13 | G90: TOL KANVAS | H90: OFFICE | I90: 85000 | K90: 13 | L90: 45535 | M90: TAMBAHAN SALDO | O90: 2000000
F91: 14 | G91: PARKIR DADAP | H91: OFFICE | I91: 5000 | K91: 14 | L91: 45535 | M91: SALLARY MINGGUAN | N91: 500000
F92: 15 | G92: MATERAI BCA/PKR | H92: OFFICE | I92: 45000 | K92: 15
F93: 16 | G93: RE ASURANSI IML | H93: 2408-003 | I93: 90000 | K93: 16
F94: 17 | G94: PARKIR PT SATWA | H94: OFFICE | I94: 5000 | K94: 17
F95: 18 | G95: BENSIN | H95: OFFICE | I95: 200000 | K95: 18
F96: 19 | G96: TOL KAPUK SKC/DH | H96: OFFICE | I96: 19000 | K96: 19
F97: 20 | G97: TOL HILMY | H97: OFFICE | I97: 55500 | K97: 20
F98: 21 | G98: TOL MKT CSL/BLR | H98: OFFICE | I98: 19000 | K98: 21
F99: 22 | G99: KOPI OFF ASH | H99: OFFICE | I99: 43690 | K99: 22
F100: 23 | G100: ENTERTAIN GSAP | H100: 2408-007 | I100: 154000 | K100: 23
F101: 24 | G101: SOLAR ACS SAP | H101: 2408-009 | I101: 100000 | K101: 24
F102: 25 | G102: CANCEL TRUC GSAP | H102: 2408-007 | I102: 400000 | K102: 25
F103: 26 | G103: KUOTA EWILOG | H103: OFFICE | I103: 49000 | K103: 26
F104: Total | I104: =SUM(I78:I103) -> 4521693 | K104: Total | N104: =SUM(N79:N103) -> 2020500 | O104: =SUM(O78:O103) -> 3700000 | P104: =SUM(O104-N104) -> 1679500

Sheet LR SEPT 2024
B2: PT ESHAKA WIJAYA LOGISTICS | F2: Pendapatan Agustus 2024 | L2: PETTY CASH AGUSTUS 2024
B3: Laporan Laba Rugi | F3: No | G3: SO No. | H3: Customer | I3: Profit | L3: No. | M3: Tgl | N3: KETERANGAN | O3: DEBIT | P3: KREDIT | Q3: PENYESUAIAN
B4: Periode September 2024 | F4: 1 | G4: 2409-0231 | H4: VICTORY | I4: 1227000 | L4: 1 | M4: 45536 | P4: ='LR AUG 2024'!P104 -> 1679500
F5: 2 | G5: 2409-0242 | H5: CPP | I5: 1791000 | L5: 2 | M5: 45538 | N5: GALON AIR BIRU | O5: 9000
B6: Description | C6: Penyesuaian | F6: 3 | G6: 2409-0253 | H6: SAS | I6: 1500000 | L6: 3 | M6: 45540 | N6: GALON AIR BIRU | O6: 9000
B7: Modal / Harta : | F7: 4 | G7: 2409-0264 | H7: GREEN | I7: 4102000 | L7: 4 | M7: 45540 | N7: JNE CSL + INDOPROMO | O7: 20000
B8: Kas | F8: 5 | G8: 2409-0275 | H8: CSL | I8: 3225000 | L8: 5 | M8: 45541 | N8: SALLARY MINGGUAN | O8: 417000
B9: Bank Mandiri | C9: ='LR AUG 2024'!C48 -> 2.577605e+08 | F9: 6 | G9: 2409-0286 | H9: CSL | I9: 5850000 | L9: 6 | M9: 45545 | N9: JNE CSL + CPP + CJH | O9: 30000
B10: Bank BCA | C10: ='LR AUG 2024'!C49 -> 18819950 | F10: 7 | G10: 2409-0297 | H10: BAUMA | I10: 11693972 | L10: 7 | M10: 45546 | N10: BENSIN MOTOR | O10: 20000
B11: Total Modal | C11: =SUM(C8:C10) -> 2.7658045e+08 | F11: 8 | G11: 2409-0308 | H11: CSL | I11: 1000000 | L11: 8 | M11: 45548 | N11: SALLARY MINGGUAN | O11: 417000
F12: 9 | G12: 2409-0319 | H12: CSL | I12: 1222500 | L12: 9 | M12: 45552 | N12: GALON AIR BIRU | O12: 9000
B13: Pendapatan: | F13: 10 | G13: 2409-03210 | H13: CSL | I13: 200000 | L13: 10 | M13: 45552 | N13: JNE VICTORY | O13: 10000
B14: Pendapatan Jasa September 2024 | C14: =I50 -> 118776094 | F14: 11 | G14: 2409-03311 | H14: CSL | I14: 2212500 | L14: 11 | M14: 45552 | N14: JNE CPP CSL + CPP | O14: 20000
B15: Pendapatan Lain-Lain (Bunga Bank Mandiri) | C15: 0 | F15: 12 | G15: 2409-03412 | H15: CSL | I15: 1275000 | L15: 12 | M15: 45555 | N15: JNE DOLPHIN | O15: 10000
B16: Pendapatan Lain-Lain (Bunga Bank BCA) | C16: 0 | F16: 13 | G16: 2409-03513 | H16: CSL | I16: 562500 | L16: 13 | M16: 45555 | N16: GALON AIR BIRU | O16: 9000
B17: Jumlah Pendapatan | C17: =SUM(C14:C15) -> 118776094 | F17: 14 | G17: 2409-03614 | H17: GSAP | I17: 587500 | L17: 14 | M17: 45555 | N17: SALLARY MINGGUAN | O17: 417000
F18: 15 | G18: 2409-03715 | H18: CSL | I18: 200000 | L18: 15 | M18: 45558 | N18: JNE CSL | O18: 10000
B19: Hutang | F19: 16 | G19: 2409-03816 | H19: CSL | I19: 962500 | L19: 16 | M19: 45561 | N19: GALON/KOPI/GULA | O19: 36000
B20: Cicilan Modal Awal IDR 100,000,000; + IDR 233,594,567 | F20: 17 | G20: 2409-03917 | H20: CSL | I20: 2425000 | L20: 17 | M20: 45561 | N20: JNE CSL YES | O20: 18000
